Workbook

Sheet Instructions
B1: 2026 NA Revenue Tracking — User Guide
B2: Questions? Contact Pedro
B3: HOW IT WORKS
B4: Forecast Input | C4: The only place anyone types. Vertical owners update forecast weekly and actuals monthly.
B5: Vertical tabs (Rotowire, Sports Affiliate, etc.) | C5: Read-only summaries. Pull from Forecast Input automatically. Show full detail + variances.
B6: Executive Dashboard | C6: Full-year snapshot + traffic light attainment. Auto-updates.
B7: VERTICAL OWNERS — WEEKLY (BY WEDNESDAY)
B8: Step 1 | C8: Go to Forecast Input tab.
B9: Step 2 | C9: Find your vertical section and the 🟡 yellow Forecast rows. Update each open month with your best current estimate.
B10: Step 3 | C10: Save and notify #sds-budget-owners Slack channel
B11: Step 4 | C11: Enter confirmed Actuals in the 🟦 teal rows on the Forecast Input tab after each month closes.
B12: DEFINITIONS
B13: 🟡 Forecast (yellow) | C13: Owner's weekly best estimate. Update every Wednesday.
B14: 🟦 Actual 26' (teal) | C14: Confirmed 2026 revenue entered after each month closes.
B15: Actual 25' | C15: Prior year actuals — locked reference, not editable.
B16: Budget | C16: Annual budget set in Dec 2025. Locked
B17: Target | C17: Stretch goal. Locked.
B18: Run-Rate ★ | C18: Closed Month Actuals + Forecast. Directional only until more months confirm.
B19: 🟢 On Track | C19: Forecast ≥ Budget.
B20: 🟡 Watch | C20: Forecast within 10% below Budget.
B21: 🔴 At Risk | C21: Forecast more than 10% below Budget — escalate.

Sheet Forecast Input
A1: 2026 SDS Revenue — Forecast Input
A2: 🟡 Yellow = Forecast (vertical owners — update weekly by Wednesday) · 🟦 Teal = Actuals (vertical owners — enter after month close)
A3: VERTICAL | B3: SUB-LINE | C3: METRIC | D3: Jan | E3: Feb | F3: Mar | G3: Apr | H3: May | I3: Jun | J3: Jul | K3: Aug | L3: Sep | M3: Oct | N3: Nov | O3: Dec | P3: FULL YEAR
A4: ROTOWIRE
A5: Rotowire | B5: B2C Subs | C5: Actual 26 🟦 | D5: 474038.26 | E5: 459134.72 | F5: 552360.2 | P5: =SUM(D5:O5) -> 1485533.2
B6: B2C Subs | C6: Forecast 🟡 | D6: 484326 | E6: =446408-3000 -> 443408 | F6: =543544-10000+2000-4000 -> 531544 | G6: =478073-5000-14000 -> 459073 | H6: =462554-10000 -> 452554 | I6: =487438-9000 -> 478438 | J6: =482501+9000 -> 491501 | K6: 751620 | L6: 784277 | M6: 731746 | N6: 714855 | O6: 681276 | P6: =SUM(D6:O6) -> 7004618
B7: Advertising | C7: Actual 26 🟦 | D7: 111988.73 | E7: 103856.8 | F7: 134400.81 | P7: =SUM(D7:O7) -> 350246.34
B8: Advertising | C8: Forecast 🟡 | D8: 73000 | E8: =67000+12000 -> 79000 | F8: =104000+5000+6000 -> 115000 | G8: 114000 | H8: 79000 | I8: 74000 | J8: 82000 | K8: 124000 | L8: 124000 | M8: 107000 | N8: 124000 | O8: 124000 | P8: =SUM(D8:O8) -> 1219000
B9: B2B Content | C9: Actual 26 🟦 | D9: 243987.32 | E9: 236446.5 | F9: 248430.63 | P9: =SUM(D9:O9) -> 728864.45 | Q9: Feb26 is a bit low because finance did not include DraftKings deal here. Getting to the bottom of why.
B10: B2B Content | C10: Forecast 🟡 | D10: 273000 | E10: =274000-15000 -> 259000 | F10: =270000-8000-4000-10000 -> 248000 | G10: =291000-9000-15000-8000-5000 -> 254000 | H10: =302000-15000-10000-8000-5000 -> 264000 | I10: =317000-20000-8000-10000-5000 -> 274000 | J10: =321000-10000 -> 311000 | K10: =326000-5000 -> 321000 | L10: =329000-5000 -> 324000 | M10: =335000-5000 -> 330000 | N10: =338000-5000 -> 333000 | O10: =342000-5000 -> 337000 | P10: =SUM(D10:O10) -> 3528000
B11: Rotowire Affiliate | C11: Actual 26 🟦 | D11: 373629.35 | E11: 478517.09 | F11: 568834.08 | P11: =SUM(D11:O11) -> 1420980.5
B12: Rotowire Affiliate | C12: Forecast 🟡 | D12: 390000 | E12: 350000 | F12: 600000 | G12: 500000 | H12: 350000 | I12: 350000 | J12: 350000 | K12: 500000 | L12: 600000 | M12: 500000 | N12: 500000 | O12: 500000 | P12: =SUM(D12:O12) -> 5490000 | Q12: Adjusted a few months in the summer down a bit as well as the last three months of the year. Nothing dramatic, just learning more about the seasonality of a site like RotoWire.
A13: SPORTS AFFILIATE
A14: Sports Affiliate | B14: Bookies US | C14: Actual 26 🟦 | D14: -3260.2155 | E14: 44660 | F14: 2249 | P14: =SUM(D14:O14) -> 43648.784
B15: Bookies US | C15: Forecast 🟡 | D15: 30000 | E15: 37500 | F15: 15000 | G15: 55000 | H15: 55000 | I15: 55000 | J15: 95000 | K15: 105000 | L15: 150000 | M15: 105000 | N15: 105000 | O15: 105000 | P15: =SUM(D15:O15) -> 912500
B16: Bookies UK | C16: Actual 26 🟦 | D16: 212757.88 | E16: 148559.81 | F16: 9433 | P16: =SUM(D16:O16) -> 370750.69
B17: Bookies UK | C17: Forecast 🟡 | D17: 175000 | E17: 177000 | F17: 150000 | G17: 150000 | H17: 150000 | I17: 150000 | J17: 150000 | K17: 215000 | L17: 205000 | M17: 200000 | N17: 200000 | O17: 200000 | P17: =SUM(D17:O17) -> 2122000
B18: Bookies IE | C18: Actual 26 🟦 | D18: 2024.5313 | E18: 6347.5797 | F18: 6358 | P18: =SUM(D18:O18) -> 14730.111
B19: Bookies IE | C19: Forecast 🟡 | D19: 12500 | E19: 13500 | F19: 13000 | G19: 13500 | H19: 12000 | I19: 13500 | J19: 12000 | K19: 14000 | L19: 16000 | M19: 10000 | N19: 10000 | O19: 10000 | P19: =SUM(D19:O19) -> 150000
B20: Bookies IN | C20: Actual 26 🟦 | D20: 5566.1161 | E20: 14370.106 | F20: 7935 | P20: =SUM(D20:O20) -> 27871.222
B21: Bookies IN | C21: Forecast 🟡 | D21: 10000 | E21: 10000 | F21: 8500 | G21: 8000 | H21: 8000 | I21: 8000 | J21: 8000 | K21: 8000 | L21: 8000 | M21: 8000 | N21: 8000 | O21: 8000 | P21: =SUM(D21:O21) -> 100500
B22: Bookies CA | C22: Actual 26 🟦 | D22: 9408.0531 | E22: 4565.4974 | F22: 14841 | P22: =SUM(D22:O22) -> 28814.55
B23: Bookies CA | C23: Forecast 🟡 | D23: 17500 | E23: 15000 | F23: 14500 | G23: 14500 | H23: 14500 | I23: 15000 | J23: 16500 | K23: 16500 | L23: 20000 | M23: 18500 | N23: 18000 | O23: 18000 | P23: =SUM(D23:O23) -> 198500
B24: Bookies AU | C24: Actual 26 🟦 | D24: 2960.88 | E24: 687.37603 | F24: -1533 | P24: =SUM(D24:O24) -> 2115.2561
B25: Bookies AU | C25: Forecast 🟡 | D25: 1500 | E25: 1500 | F25: 1500 | G25: 1500 | H25: 1500 | I25: 1500 | J25: 1500 | K25: 1500 | L25: 1500 | M25: 1500 | N25: 1500 | O25: 1500 | P25: =SUM(D25:O25) -> 18000
B26: Bookies NZ | C26: Actual 26 🟦 | D26: 1721.4416 | E26: 4112.945 | F26: 4550 | P26: =SUM(D26:O26) -> 10384.387
B27: Bookies NZ | C27: Forecast 🟡 | D27: 10000 | E27: 5000 | F27: 10000 | G27: 7500 | H27: 8000 | I27: 8000 | J27: 8500 | K27: 8500 | L27: 7500 | M27: 10000 | N27: 10000 | O27: 8500 | P27: =SUM(D27:O27) -> 101500
B28: Bookies MX | C28: Actual 26 🟦 | D28: 8337.3099 | E28: 3992.0958 | F28: 1794 | P28: =SUM(D28:O28) -> 14123.406
B29: Bookies MX | C29: Forecast 🟡 | D29: 3000 | E29: 8000 | F29: 8000 | G29: 5500 | H29: 5500 | I29: 5500 | J29: 5500 | K29: 5500 | L29: 5500 | M29: 5500 | N29: 5500 | O29: 5500 | P29: =SUM(D29:O29) -> 68500
B30: Bookies NG | C30: Actual 26 🟦 | D30: 0.648964 | E30: 0 | P30: =SUM(D30:O30) -> 0.648964
B31: Bookies NG | C31: Forecast 🟡 | P31: =SUM(D31:O31) -> 0 | Q31: Not market we are focusing on. Pulling out of mkt.
B32: Bookies NL | C32: Actual 26 🟦 | D32: 601.71932 | E32: 224.09292 | F32: 15 | P32: =SUM(D32:O32) -> 840.81223
B33: Bookies NL | C33: Forecast 🟡 | D33: 1500 | E33: 1500 | F33: 1500 | G33: 1500 | H33: 1500 | I33: 1500 | J33: 1500 | K33: 1500 | L33: 1500 | M33: 1500 | N33: 1500 | O33: 1500 | P33: =SUM(D33:O33) -> 18000
B34: Bookies BR | C34: Actual 26 🟦 | D34: 111.69258 | E34: 260.21518 | F34: -77 | P34: =SUM(D34:O34) -> 294.90776
B35: Bookies BR | C35: Forecast 🟡 | D35: 100 | E35: 100 | F35: 100 | G35: 100 | H35: 100 | I35: 100 | J35: 100 | K35: 100 | L35: 100 | M35: 100 | N35: 100 | O35: 100 | P35: =SUM(D35:O35) -> 1200 | Q35: Most likely out of market by end of Q1
B36: Bookies GX | C36: Actual 26 🟦 | D36: 167.97545 | E36: 546 | F36: 651 | P36: =SUM(D36:O36) -> 1364.9755
B37: Bookies GX | C37: Forecast 🟡 | D37: 100 | E37: 100 | F37: 100 | G37: 100 | H37: 100 | I37: 100 | J37: 100 | K37: 100 | L37: 100 | M37: 100 | N37: 100 | O37: 100 | P37: =SUM(D37:O37) -> 1200
B38: Bookies ES | C38: Actual 26 🟦 | E38: 5.797546 | F38: 289 | P38: =SUM(D38:O38) -> 294.79755
B39: Bookies ES | C39: Forecast 🟡 | D39: 100 | E39: 100 | F39: 100 | G39: 500 | H39: 500 | I39: 500 | J39: 1000 | K39: 1000 | L39: 1000 | M39: 1000 | N39: 1000 | O39: 1000 | P39: =SUM(D39:O39) -> 7800
B40: Bookmakers | C40: Actual 26 🟦 | D40: -13263.989 | E40: 17347.598 | F40: 14186 | P40: =SUM(D40:O40) -> 18269.609
B41: Bookmakers | C41: Forecast 🟡 | D41: 12500 | E41: 12500 | F41: 18500 | G41: 12500 | H41: 12500 | I41: 12500 | J41: 12500 | K41: 12500 | L41: 12500 | M41: 12500 | N41: 12500 | O41: 12500 | P41: =SUM(D41:O41) -> 156000
B42: BetSync | C42: Actual 26 🟦 | E42: 1498 | F42: 5273 | P42: =SUM(D42:O42) -> 6771
B43: Bet Sync | C43: Forecast 🟡 | G43: 7382 | H43: 8859 | I43: 10631 | J43: 11694 | K43: 14032 | L43: 16839 | M43: 20207 | N43: 24248 | O43: 29097 | P43: =SUM(D43:O43) -> 142989
A44: PARTNERSHIPS
A45: Partnerships | B45: GAN Affiliate | C45: Actual 26 🟦 | D45: 618795.88 | E45: 746747.75 | F45: 496449.58 | P45: =SUM(D45:O45) -> 1861993.2
B46: GAN Affiliate | C46: Forecast 🟡 | D46: 500000 | E46: 700000 | F46: 550000 | G46: 350000 | H46: 300000 | I46: 300000 | J46: 300000 | K46: 400000 | L46: 600000 | M46: 500000 | N46: 500000 | O46: 500000 | P46: =SUM(D46:O46) -> 5500000 | Q46: I reduced almost every month $50-100k due to the recent fluctuations in rankings persisting. As mentioned, this volatile business has cratered underneath us before and we can't do as much to combat the trends when we don't control the product so need to temper our expectations.
A47: LOCAL
A48: Local | B48: BetArizona | C48: Actual 26 🟦 | D48: 13350.067 | E48: 8927.3897 | F48: 15835.692 | P48: =SUM(D48:O48) -> 38113.149
B49: BetArizona | C49: Forecast 🟡 | D49: 20000 | E49: 12000 | F49: 10000 | G49: 5000 | H49: 3000 | I49: 3000 | J49: 3000 | K49: 5000 | L49: 20000 | M49: 15000 | N49: 15000 | O49: 15000 | P49: =SUM(D49:O49) -> 126000
B50: BetVirginia | C50: Actual 26 🟦 | D50: 10130.181 | E50: 2170.761 | F50: 4496.6503 | P50: =SUM(D50:O50) -> 16797.592
B51: BetVirginia | C51: Forecast 🟡 | D51: 15000 | E51: 12000 | F51: 10000 | G51: 8000 | H51: 3000 | I51: 3000 | J51: 3000 | K51: 5000 | L51: 10000 | M51: 8000 | N51: 8000 | O51: 10000 | P51: =SUM(D51:O51) -> 95000
B52: BetKansas | C52: Actual 26 🟦 | D52: -9.983818 | E52: 14220.312 | F52: 9727.514 | P52: =SUM(D52:O52) -> 23937.842
B53: BetKansas | C53: Forecast 🟡 | D53: 20000 | E53: 5000 | F53: 5000 | G53: 2000 | H53: 1000 | I53: 1000 | J53: 1000 | K53: 5000 | L53: 15000 | M53: 10000 | N53: 10000 | O53: 15000 | P53: =SUM(D53:O53) -> 90000
B54: BetOhio | C54: Actual 26 🟦 | D54: 4945.2445 | E54: 2880.0743 | F54: 8564.9448 | P54: =SUM(D54:O54) -> 16390.264
B55: BetOhio | C55: Forecast 🟡 | D55: 10000 | E55: 5000 | F55: 5000 | G55: 2000 | H55: 1000 | I55: 1000 | J55: 1000 | K55: 3000 | L55: 10000 | M55: 8000 | N55: 8000 | O55: 10000 | P55: =SUM(D55:O55) -> 64000
B56: BetKentucky | C56: Actual 26 🟦 | D56: 2176.933 | E56: 1425.0822 | F56: 3628.2569 | P56: =SUM(D56:O56) -> 7230.272
B57: BetKentucky | C57: Forecast 🟡 | D57: 5000 | E57: 3000 | F57: 3000 | G57: 2000 | H57: 1000 | I57: 1000 | J57: 1000 | K57: 3000 | L57: 5000 | M57: 4000 | N57: 4000 | O57: 5000 | P57: =SUM(D57:O57) -> 37000
B58: BetMassachusetts | C58: Actual 26 🟦 | D58: 7974.6974 | E58: 6956.5644 | F58: 2045.0664 | P58: =SUM(D58:O58) -> 16976.328
B59: BetMassachusetts | C59: Forecast 🟡 | D59: 15000 | E59: 12000 | F59: 10000 | G59: 8000 | H59: 3000 | I59: 3000 | J59: 3000 | K59: 5000 | L59: 10000 | M59: 8000 | N59: 8000 | O59: 10000 | P59: =SUM(D59:O59) -> 95000
B60: BetTennessee | C60: Actual 26 🟦 | D60: 1911.806 | E60: -363.29582 | F60: 2161.5845 | P60: =SUM(D60:O60) -> 3710.0947
B61: BetTennessee | C61: Forecast 🟡 | D61: 5000 | E61: 3000 | F61: 3000 | G61: 2000 | H61: 1000 | I61: 1000 | J61: 1000 | K61: 3000 | L61: 5000 | M61: 4000 | N61: 4000 | O61: 5000 | P61: =SUM(D61:O61) -> 37000
B62: LouisianaBets | C62: Actual 26 🟦 | D62: -376.13058 | E62: -1212.1453 | F62: 1384.8506 | P62: =SUM(D62:O62) -> -203.42531
B63: LouisianaBets | C63: Forecast 🟡 | D63: 5000 | E63: 1000 | F63: 1000 | G63: 1000 | H63: 1000 | I63: 1000 | J63: 1000 | K63: 1000 | L63: 1000 | M63: 1000 | N63: 1000 | O63: 1000 | P63: =SUM(D63:O63) -> 16000
B64: BetColorado | C64: Actual 26 🟦 | D64: 1756.431 | E64: 7497.8106 | F64: 1043.8384 | P64: =SUM(D64:O64) -> 10298.08
B65: BetColorado | C65: Forecast 🟡 | D65: 5000 | E65: 3000 | F65: 3000 | G65: 2000 | H65: 1000 | I65: 1000 | J65: 1000 | K65: 3000 | L65: 5000 | M65: 4000 | N65: 4000 | O65: 5000 | P65: =SUM(D65:O65) -> 37000
B66: IndianaBets | C66: Actual 26 🟦 | D66: 2.894005 | E66: 42.601367 | F66: 39.869312 | P66: =SUM(D66:O66) -> 85.364684
B67: IndianaBets | C67: Forecast 🟡 | D67: 0 | E67: 0 | F67: 0 | G67: 0 | H67: 0 | I67: 0 | J67: 0 | K67: 0 | L67: 0 | M67: 0 | N67: 0 | O67: 0 | P67: =SUM(D67:O67) -> 0
B68: IowaBets | C68: Actual 26 🟦 | D68: 84.286657 | E68: 268.81932 | F68: -18.937923 | P68: =SUM(D68:O68) -> 334.16806
B69: IowaBets | C69: Forecast 🟡 | D69: 100 | E69: 100 | F69: 100 | G69: 100 | H69: 100 | I69: 100 | J69: 100 | K69: 100 | L69: 100 | M69: 100 | N69: 100 | O69: 100 | P69: =SUM(D69:O69) -> 1200
B70: EmpireStakes | C70: Actual 26 🟦 | D70: 353.48925 | E70: 275.81462 | F70: 355.8336 | P70: =SUM(D70:O70) -> 985.13747
B71: EmpireStakes | C71: Forecast 🟡 | D71: 500 | E71: 500 | F71: 500 | G71: 500 | H71: 500 | I71: 500 | J71: 500 | K71: 500 | L71: 500 | M71: 500 | N71: 500 | O71: 500 | P71: =SUM(D71:O71) -> 6000
B72: IllinoisBet | C72: Actual 26 🟦 | D72: 2255.8122 | E72: 2409.3806 | F72: 577.10828 | P72: =SUM(D72:O72) -> 5242.3011
B73: IllinoisBet | C73: Forecast 🟡 | D73: 1000 | E73: 1000 | F73: 1000 | G73: 1000 | H73: 1000 | I73: 1000 | J73: 1000 | K73: 1000 | L73: 1000 | M73: 1000 | N73: 1000 | O73: 1000 | P73: =SUM(D73:O73) -> 12000
B74: BetMaryland | C74: Actual 26 🟦 | D74: 4598.3043 | E74: 1835.8361 | F74: 2995.1123 | P74: =SUM(D74:O74) -> 9429.2527
B75: BetMaryland | C75: Forecast 🟡 | D75: 15000 | E75: 12000 | F75: 10000 | G75: 8000 | H75: 3000 | I75: 3000 | J75: 3000 | K75: 5000 | L75: 10000 | M75: 8000 | N75: 8000 | O75: 10000 | P75: =SUM(D75:O75) -> 95000
B76: PennStakes | C76: Actual 26 🟦 | D76: -453.70796 | E76: 9662.2558 | F76: 4833.3068 | P76: =SUM(D76:O76) -> 14041.855
B77: PennStakes | C77: Forecast 🟡 | D77: 5000 | E77: 1000 | F77: 1000 | G77: 1000 | H77: 1000 | I77: 1000 | J77: 1000 | K77: 1000 | L77: 1000 | M77: 1000 | N77: 1000 | O77: 1000 | P77: =SUM(D77:O77) -> 16000
B78: BetMichigan | C78: Actual 26 🟦 | D78: 2133.9535 | E78: 3677.5283 | F78: 1909.74 | P78: =SUM(D78:O78) -> 7721.2218
B79: BetMichigan | C79: Forecast 🟡 | D79: 5000 | E79: 3000 | F79: 3000 | G79: 2000 | H79: 1000 | I79: 1000 | J79: 1000 | K79: 1000 | L79: 1000 | M79: 1000 | N79: 1000 | O79: 1000 | P79: =SUM(D79:O79) -> 21000
B80: FloridaBet | C80: Actual 26 🟦 | D80: 142.19681 | E80: 69.952983 | F80: -849.1366 | P80: =SUM(D80:O80) -> -636.98681
B81: FloridaBet | C81: Forecast 🟡 | D81: 500 | E81: 500 | F81: 500 | G81: 500 | H81: 500 | I81: 500 | J81: 500 | K81: 500 | L81: 500 | M81: 500 | N81: 500 | O81: 500 | P81: =SUM(D81:O81) -> 6000
B82: BetCarolina | C82: Actual 26 🟦 | D82: 4363.5494 | E82: 5298.6387 | F82: 5417.3922 | P82: =SUM(D82:O82) -> 15079.58
B83: BetCarolina | C83: Forecast 🟡 | D83: 20000 | E83: 10000 | F83: 5000 | G83: 3000 | H83: 3000 | I83: 3000 | J83: 3000 | K83: 4000 | L83: 8000 | M83: 5000 | N83: 5000 | O83: 5000 | P83: =SUM(D83:O83) -> 74000
B84: BetTexas | C84: Actual 26 🟦 | D84: 936.26584 | E84: -432.94901 | F84: -426.49199 | P84: =SUM(D84:O84) -> 76.824841
B85: BetTexas | C85: Forecast 🟡 | D85: 500 | E85: 500 | F85: 500 | G85: 500 | H85: 500 | I85: 500 | J85: 500 | K85: 500 | L85: 500 | M85: 500 | N85: 500 | O85: 500 | P85: =SUM(D85:O85) -> 6000
B86: BetCalifornia | C86: Actual 26 🟦 | D86: 1059.3762 | E86: 485.38376 | F86: -1908.3346 | P86: =SUM(D86:O86) -> -363.57463
B87: BetCalifornia | C87: Forecast 🟡 | D87: 500 | E87: 500 | F87: 500 | G87: 500 | H87: 500 | I87: 500 | J87: 500 | K87: 500 | L87: 500 | M87: 500 | N87: 500 | O87: 500 | P87: =SUM(D87:O87) -> 6000
B88: BetGeorgia | C88: Actual 26 🟦 | D88: -2553.5342 | E88: 778.41681 | F88: -4.983664 | P88: =SUM(D88:O88) -> -1780.1011
B89: BetGeorgia | C89: Forecast 🟡 | D89: 500 | E89: 500 | F89: 500 | G89: 500 | H89: 500 | I89: 500 | J89: 500 | K89: 500 | L89: 500 | M89: 500 | N89: 500 | O89: 500 | P89: =SUM(D89:O89) -> 6000
B90: MinnesotaBets | C90: Actual 26 🟦 | D90: 0 | E90: 0 | F90: 0 | P90: =SUM(D90:O90) -> 0
B91: MinnesotaBets | C91: Forecast 🟡 | D91: 500 | E91: 500 | F91: 500 | G91: 500 | H91: 500 | I91: 500 | J91: 500 | K91: 500 | L91: 500 | M91: 500 | N91: 500 | O91: 500 | P91: =SUM(D91:O91) -> 6000
B92: BetMissouri | C92: Actual 26 🟦 | D92: 75517.58 | E92: 62921.899 | F92: 3415.6737 | P92: =SUM(D92:O92) -> 141855.15
B93: BetMissouri | C93: Forecast 🟡 | D93: 50000 | E93: 20000 | F93: 20000 | G93: 10000 | H93: 5000 | I93: 5000 | J93: 5000 | K93: 10000 | L93: 25000 | M93: 20000 | N93: 20000 | O93: 25000 | P93: =SUM(D93:O93) -> 215000
B94: OntarioBets | C94: Actual 26 🟦 | D94: 10202.617 | E94: 11728.955 | F94: 13670.577 | P94: =SUM(D94:O94) -> 35602.149
B95: OntarioBets | C95: Forecast 🟡 | D95: 15000 | E95: 15000 | F95: 15000 | G95: 15000 | H95: 15000 | I95: 15000 | J95: 20000 | K95: 20000 | L95: 20000 | M95: 30000 | N95: 30000 | O95: 30000 | P95: =SUM(D95:O95) -> 240000
B96: BetCanada | C96: Actual 26 🟦 | D96: 564.956 | E96: 935.49918 | F96: 209.72987 | P96: =SUM(D96:O96) -> 1710.1851
B97: BetCanada | C97: Forecast 🟡 | D97: 500 | E97: 500 | F97: 500 | G97: 500 | H97: 500 | I97: 500 | J97: 500 | K97: 500 | L97: 500 | M97: 500 | N97: 500 | O97: 500 | P97: =SUM(D97:O97) -> 6000
B98: ApuestaMexico | C98: Actual 26 🟦 | D98: 251.0037 | E98: -133.23708 | F98: 516.74519 | P98: =SUM(D98:O98) -> 634.51181
B99: ApuestaMexico | C99: Forecast 🟡 | D99: 0 | E99: 0 | F99: 0 | G99: 0 | H99: 0 | I99: 0 | J99: 0 | K99: 0 | L99: 0 | M99: 0 | N99: 0 | O99: 0 | P99: =SUM(D99:O99) -> 0
B100: Brasilpostas | C100: Actual 26 🟦 | D100: 202.81864 | E100: 86.489927 | F100: 106.29764 | P100: =SUM(D100:O100) -> 395.60621
...

Sheet Management View--->

Sheet Executive Dashboard
A1: 2026 SDS Revenue Forecast
A2: FULL-YEAR SUMMARY — ALL VERTICALS COMBINED
B3: 2025 Actuals | C3: 2026 Budget | D3: 2026 Target | E3: 2026 Forecast | F3: 26F vs 25A
A4: Total SDS | B4: =B82 -> 57053617 | C4: =SUM(B11:B16) -> 68369348 | D4: =I17 -> 69382852 | E4: =Forecast!N65 -> 67162174 | F4: =(E4-B4)/B4 -> 0.17717645
A5: Forecast = Actuals + Forecast · Updates automatically as actuals are entered
A8: BUDGET vs FORECAST ANNUAL | H8: TARGET vs FORECAST | N8: Comments
A9: Are we on track to hit our committed plan? | H9: Based on actuals + forecasted months
A10: VERTICAL | B10: 2026 Budget | C10: Forecast | D10: $ Difference | E10: % Diff | F10: STATUS | H10: VERTICAL | I10: 2026 Target | J10: Forecast | K10: $ Difference | L10: % Diff | M10: STATUS
A11: Rotowire | B11: 14045617 | C11: =J11 -> 17380964 | D11: =IFERROR(C11-B11,0) -> 3335347.5 | E11: =IFERROR((C11-B11)/ABS(B11),0) -> 0.23746536 | F11: =IF(E11>=0,"🟢 On Track",IF(E11>=-0.1,"🟡 Watch","🔴 At Risk")) -> 🟢 On Track | H11: Rotowire | I11: 14850000 | J11: =Forecast!N8 -> 17380964 | K11: =IFERROR(J11-I11,0) -> 2530964.5 | L11: =IFERROR((J11-I11)/ABS(I11),0) -> 0.17043532 | M11: =IF(L11>=0,"🟢 On Track",IF(L11>=-0.1,"🟡 Watch","🔴 At Risk")) -> 🟢 On Track | N11: Big boost in affiliate revenue continues. Subs also on a steady positive trend in early March, a good start considering sub growth is typically higher in the back half of the month (more renewals in system). Affiliate 3/16: Commercial reported a solid first half of the month so upped the the forecasts for the summer months a bit as I feel the floor continues to rise even with sports out of season.
A12: Bookies | B12: 6233352 | C12: =J12 -> 3742664.2 | D12: =IFERROR(C12-B12,0) -> -2490687.8 | E12: =IFERROR((C12-B12)/ABS(B12),0) -> -0.39957439 | F12: =IF(E12>=0,"🟢 On Track",IF(E12>=-0.1,"🟡 Watch","🔴 At Risk")) -> 🔴 At Risk | H12: Bookies | I12: 6233352 | J12: =Forecast!N25 -> 3742664.2 | K12: =IFERROR(J12-I12,0) -> -2490687.8 | L12: =IFERROR((J12-I12)/ABS(I12),0) -> -0.39957439 | M12: =IF(L12>=0,"🟢 On Track",IF(L12>=-0.1,"🟡 Watch","🔴 At Risk")) -> 🔴 At Risk | N12: 4/15 UK saw large negative rev share hit from William Hill in March. Lowering UK slightly, but seemingly a one-off.
A13: Partnerships | B13: 999996 | C13: =J13 -> 5611993.2 | D13: =IFERROR(C13-B13,0) -> 4611997.2 | E13: =IFERROR((C13-B13)/ABS(B13),0) -> 4.6120157 | F13: =IF(E13>=0,"🟢 On Track",IF(E13>=-0.1,"🟡 Watch","🔴 At Risk")) -> 🟢 On Track | H13: Partnerships | I13: 1258000 | J13: =Forecast!N28 -> 5611993.2 | K13: =IFERROR(J13-I13,0) -> 4353993.2 | L13: =IFERROR((J13-I13)/ABS(I13),0) -> 3.4610439 | M13: =IF(L13>=0,"🟢 On Track",IF(L13>=-0.1,"🟡 Watch","🔴 At Risk")) -> 🟢 On Track | N13: 4/1: Commercial reported a solid first half of the month so upped the March and April forecasts a bit.
A14: Local | B14: 3731000 | C14: =J14 -> 1233562.8 | D14: =IFERROR(C14-B14,0) -> -2497437.2 | E14: =IFERROR((C14-B14)/ABS(B14),0) -> -0.66937474 | F14: =IF(E14>=0,"🟢 On Track",IF(E14>=-0.1,"🟡 Watch","🔴 At Risk")) -> 🔴 At Risk | H14: Local | I14: 3731000 | J14: =Forecast!N57 -> 1233562.8 | K14: =IFERROR(J14-I14,0) -> -2497437.2 | L14: =IFERROR((J14-I14)/ABS(I14),0) -> -0.66937474 | M14: =IF(L14>=0,"🟢 On Track",IF(L14>=-0.1,"🟡 Watch","🔴 At Risk")) -> 🔴 At Risk | N14: 4/1: No Changes
A15: OddsJam | B15: 20765167 | C15: =J15 -> 16915715 | D15: =IFERROR(C15-B15,0) -> -3849452.3 | E15: =IFERROR((C15-B15)/ABS(B15),0) -> -0.18538027 | F15: =IF(E15>=0,"🟢 On Track",IF(E15>=-0.1,"🟡 Watch","🔴 At Risk")) -> 🔴 At Risk | H15: OddsJam | I15: 19027500 | J15: =Forecast!N59+Forecast!N60+Forecast!N61 -> 16915715 | K15: =IFERROR(J15-I15,0) -> -2111785.3 | L15: =IFERROR((J15-I15)/ABS(I15),0) -> -0.11098596 | M15: =IF(L15>=0,"🟢 On Track",IF(L15>=-0.1,"🟡 Watch","🔴 At Risk")) -> 🔴 At Risk | N15: 4/22: $71k of contraction on prediction insiders bringing MRR down from $165k to $105k. Combined with churn from seasonality.
A16: OpticOdds | B16: 22594216 | C16: =J16 -> 22277275 | D16: =IFERROR(C16-B16,0) -> -316941.46 | E16: =IFERROR((C16-B16)/ABS(B16),0) -> -0.014027548 | F16: =IF(E16>=0,"🟢 On Track",IF(E16>=-0.1,"🟡 Watch","🔴 At Risk")) -> 🟡 Watch | H16: OpticOdds | I16: 24283000 | J16: =Forecast!N63+Forecast!N62 -> 22277275 | K16: =IFERROR(J16-I16,0) -> -2005725.5 | L16: =IFERROR((J16-I16)/ABS(I16),0) -> -0.082597927 | M16: =IF(L16>=0,"🟢 On Track",IF(L16>=-0.1,"🟡 Watch","🔴 At Risk")) -> 🟡 Watch
A17: TOTAL SDS | B17: =SUM(B11:B16) -> 68369348 | C17: =SUM(C11:C16) -> 67162174 | D17: =IFERROR(C17-B17,0) -> -1207174.1 | E17: =IFERROR((C17-B17)/ABS(B17),0) -> -0.017656656 | F17: =IF(E17>=0,"🟢 On Track",IF(E17>=-0.1,"🟡 Watch","🔴 At Risk")) -> 🟡 Watch | H17: TOTAL SDS | I17: =SUM(I11:I16) -> 69382852 | J17: =SUM(J11:J16) -> 67162174 | K17: =IFERROR(J17-I17,0) -> -2220678.1 | L17: =IFERROR((J17-I17)/ABS(I17),0) -> -0.032006151 | M17: =IF(L17>=0,"🟢 On Track",IF(L17>=-0.1,"🟡 Watch","🔴 At Risk")) -> 🟡 Watch
A18: 🟢 Forecast ≥ Budget · 🟡 Forecast within 10% below Budget · 🔴 Forecast more than 10% below Budget | H18: 🟢 Rolling Forecast ≥ Budget · 🟡 Rolling Forecast within 10% below Budget · 🔴 Rolling Forecast more than 10% below Budget
A21: BUDGET vs FORECAST Q1 | H21: TARGET vs FORECAST Q1
A22: Based on actuals + forecasted months | H22: Based on actuals + forecasted months
A23: VERTICAL | B23: 2026 Budget | C23: Forecast | D23: $ Difference | E23: % Diff | F23: STATUS | H23: VERTICAL | I23: 2026 Target | J23: Forecast | K23: $ Difference | L23: % Diff | M23: STATUS
A24: Rotowire | B24: 2993779 | C24: =Forecast!B8+Forecast!C8+Forecast!D8 -> 3985624.5 | D24: =IFERROR(C24-B24,0) -> 991845.49 | E24: =IFERROR((C24-B24)/ABS(B24),0) -> 0.33130217 | F24: =IF(E24>=0,"🟢 On Track",IF(E24>=-0.1,"🟡 Watch","🔴 At Risk")) -> 🟢 On Track | H24: Rotowire | I24: 3165230.7 | J24: =C24 -> 3985624.5 | K24: =IFERROR(J24-I24,0) -> 820393.79 | L24: =IFERROR((J24-I24)/ABS(I24),0) -> 0.25918925 | M24: =IF(L24>=0,"🟢 On Track",IF(L24>=-0.1,"🟡 Watch","🔴 At Risk")) -> 🟢 On Track
A25: Bookies | B25: 1330788 | C25: =Forecast!B25+Forecast!C25+Forecast!D25 -> 540375.15 | D25: =IFERROR(C25-B25,0) -> -790412.85 | E25: =IFERROR((C25-B25)/ABS(B25),0) -> -0.59394347 | F25: =IF(E25>=0,"🟢 On Track",IF(E25>=-0.1,"🟡 Watch","🔴 At Risk")) -> 🔴 At Risk | H25: Bookies | I25: 1330788 | J25: =C25 -> 540375.15 | K25: =IFERROR(J25-I25,0) -> -790412.85 | L25: =IFERROR((J25-I25)/ABS(I25),0) -> -0.59394347 | M25: =IF(L25>=0,"🟢 On Track",IF(L25>=-0.1,"🟡 Watch","🔴 At Risk")) -> 🔴 At Risk
A26: Partnerships | B26: 249999 | C26: =Forecast!B28+Forecast!C28+Forecast!D28 -> 1861993.2 | D26: =IFERROR(C26-B26,0) -> 1611994.2 | E26: =IFERROR((C26-B26)/ABS(B26),0) -> 6.4480026 | F26: =IF(E26>=0,"🟢 On Track",IF(E26>=-0.1,"🟡 Watch","🔴 At Risk")) -> 🟢 On Track | H26: Partnerships | I26: 314500 | J26: =C26 -> 1861993.2 | K26: =IFERROR(J26-I26,0) -> 1547493.2 | L26: =IFERROR((J26-I26)/ABS(I26),0) -> 4.9204871 | M26: =IF(L26>=0,"🟢 On Track",IF(L26>=-0.1,"🟡 Watch","🔴 At Risk")) -> 🟢 On Track
A27: Local | B27: 949500 | C27: =Forecast!B57+Forecast!C57+Forecast!D57 -> 365162.84 | D27: =IFERROR(C27-B27,0) -> -584337.16 | E27: =IFERROR((C27-B27)/ABS(B27),0) -> -0.61541565 | F27: =IF(E27>=0,"🟢 On Track",IF(E27>=-0.1,"🟡 Watch","🔴 At Risk")) -> 🔴 At Risk | H27: Local | I27: 949500 | J27: =C27 -> 365162.84 | K27: =IFERROR(J27-I27,0) -> -584337.16 | L27: =IFERROR((J27-I27)/ABS(I27),0) -> -0.61541565 | M27: =IF(L27>=0,"🟢 On Track",IF(L27>=-0.1,"🟡 Watch","🔴 At Risk")) -> 🔴 At Risk
A28: OddsJam | B28: 5470003 | C28: =SUM(Forecast!B59:D61) -> 4471835.7 | D28: =IFERROR(C28-B28,0) -> -998167.28 | E28: =IFERROR((C28-B28)/ABS(B28),0) -> -0.18248021 | F28: =IF(E28>=0,"🟢 On Track",IF(E28>=-0.1,"🟡 Watch","🔴 At Risk")) -> 🔴 At Risk | H28: OddsJam | I28: 5012263.2 | J28: =C28 -> 4471835.7 | K28: =IFERROR(J28-I28,0) -> -540427.46 | L28: =IFERROR((J28-I28)/ABS(I28),0) -> -0.10782105 | M28: =IF(L28>=0,"🟢 On Track",IF(L28>=-0.1,"🟡 Watch","🔴 At Risk")) -> 🔴 At Risk
A29: OpticOdds | B29: 4749914 | C29: =SUM(Forecast!B62:D63) -> 4731775.5 | D29: =IFERROR(C29-B29,0) -> -18138.459 | E29: =IFERROR((C29-B29)/ABS(B29),0) -> -0.0038186921 | F29: =IF(E29>=0,"🟢 On Track",IF(E29>=-0.1,"🟡 Watch","🔴 At Risk")) -> 🟡 Watch | H29: OpticOdds | I29: 5104942 | J29: =C29 -> 4731775.5 | K29: =IFERROR(J29-I29,0) -> -373166.44 | L29: =IFERROR((J29-I29)/ABS(I29),0) -> -0.073099056 | M29: =IF(L29>=0,"🟢 On Track",IF(L29>=-0.1,"🟡 Watch","🔴 At Risk")) -> 🟡 Watch
A30: TOTAL SDS | B30: =SUM(B24:B29) -> 15743983 | C30: =SUM(C24:C29) -> 15956767 | D30: =IFERROR(C30-B30,0) -> 212783.95 | E30: =IFERROR((C30-B30)/ABS(B30),0) -> 0.013515255 | F30: =IF(E30>=0,"🟢 On Track",IF(E30>=-0.1,"🟡 Watch","🔴 At Risk")) -> 🟢 On Track | H30: TOTAL SDS | I30: =SUM(I24:I29) -> 15877224 | J30: =SUM(J24:J29) -> 15956767 | K30: =IFERROR(J30-I30,0) -> 79543.088 | L30: =IFERROR((J30-I30)/ABS(I30),0) -> 0.0050098864 | M30: =IF(L30>=0,"🟢 On Track",IF(L30>=-0.1,"🟡 Watch","🔴 At Risk")) -> 🟢 On Track
A33: BUDGET vs FORECAST Q2 | H33: TARGET vs FORECAST Q2
A34: Based on actuals + forecasted months | H34: Based on actuals + forecasted months
A35: VERTICAL | B35: 2026 Budget | C35: Forecast | D35: $ Difference | E35: % Diff | F35: STATUS | H35: VERTICAL | I35: 2026 Target | J35: Forecast | K35: $ Difference | L35: % Diff | M35: STATUS
A36: Rotowire | B36: 2902566 | C36: =Forecast!E8+Forecast!F8+Forecast!G8 -> 3649065 | D36: =IFERROR(C36-B36,0) -> 746499 | E36: =IFERROR((C36-B36)/ABS(B36),0) -> 0.25718588 | F36: =IF(E36>=0,"🟢 On Track",IF(E36>=-0.1,"🟡 Watch","🔴 At Risk")) -> 🟢 On Track | H36: Rotowire | I36: 3068794 | J36: =C36 -> 3649065 | K36: =IFERROR(J36-I36,0) -> 580271.01 | L36: =IFERROR((J36-I36)/ABS(I36),0) -> 0.18908764 | M36: =IF(L36>=0,"🟢 On Track",IF(L36>=-0.1,"🟡 Watch","🔴 At Risk")) -> 🟢 On Track
A37: Bookies | B37: 1238076 | C37: =Forecast!E25+Forecast!F25+Forecast!G25 -> 837472 | D37: =IFERROR(C37-B37,0) -> -400604 | E37: =IFERROR((C37-B37)/ABS(B37),0) -> -0.3235698 | F37: =IF(E37>=0,"🟢 On Track",IF(E37>=-0.1,"🟡 Watch","🔴 At Risk")) -> 🔴 At Risk | H37: Bookies | I37: 1238076 | J37: =C37 -> 837472 | K37: =IFERROR(J37-I37,0) -> -400604 | L37: =IFERROR((J37-I37)/ABS(I37),0) -> -0.3235698 | M37: =IF(L37>=0,"🟢 On Track",IF(L37>=-0.1,"🟡 Watch","🔴 At Risk")) -> 🔴 At Risk
A38: Partnerships | B38: 249999 | C38: =Forecast!E28+Forecast!F28+Forecast!G28 -> 950000 | D38: =IFERROR(C38-B38,0) -> 700001 | E38: =IFERROR((C38-B38)/ABS(B38),0) -> 2.8000152 | F38: =IF(E38>=0,"🟢 On Track",IF(E38>=-0.1,"🟡 Watch","🔴 At Risk")) -> 🟢 On Track | H38: Partnerships | I38: 314500 | J38: =C38 -> 950000 | K38: =IFERROR(J38-I38,0) -> 635500 | L38: =IFERROR((J38-I38)/ABS(I38),0) -> 2.0206677 | M38: =IF(L38>=0,"🟢 On Track",IF(L38>=-0.1,"🟡 Watch","🔴 At Risk")) -> 🟢 On Track
A39: Local | B39: 570000 | C39: =Forecast!E57+Forecast!F57+Forecast!G57 -> 170800 | D39: =IFERROR(C39-B39,0) -> -399200 | E39: =IFERROR((C39-B39)/ABS(B39),0) -> -0.70035088 | F39: =IF(E39>=0,"🟢 On Track",IF(E39>=-0.1,"🟡 Watch","🔴 At Risk")) -> 🔴 At Risk | H39: Local | I39: 570000 | J39: =C39 -> 170800 | K39: =IFERROR(J39-I39,0) -> -399200 | L39: =IFERROR((J39-I39)/ABS(I39),0) -> -0.70035088 | M39: =IF(L39>=0,"🟢 On Track",IF(L39>=-0.1,"🟡 Watch","🔴 At Risk")) -> 🔴 At Risk
A40: OddsJam | B40: 5058106 | C40: =SUM(Forecast!E59:G61) -> 3884965 | D40: =IFERROR(C40-B40,0) -> -1173141 | E40: =IFERROR((C40-B40)/ABS(B40),0) -> -0.23193286 | F40: =IF(E40>=0,"🟢 On Track",IF(E40>=-0.1,"🟡 Watch","🔴 At Risk")) -> 🔴 At Risk | H40: OddsJam | I40: 4634834.5 | J40: =C40 -> 3884965 | K40: =IFERROR(J40-I40,0) -> -749869.48 | L40: =IFERROR((J40-I40)/ABS(I40),0) -> -0.16178992 | M40: =IF(L40>=0,"🟢 On Track",IF(L40>=-0.1,"🟡 Watch","🔴 At Risk")) -> 🔴 At Risk
A41: OpticOdds | B41: 5304568 | C41: =SUM(Forecast!E62:G63) -> 5339247 | D41: =IFERROR(C41-B41,0) -> 34679 | E41: =IFERROR((C41-B41)/ABS(B41),0) -> 0.0065375729 | F41: =IF(E41>=0,"🟢 On Track",IF(E41>=-0.1,"🟡 Watch","🔴 At Risk")) -> 🟢 On Track | H41: OpticOdds | I41: 5701053.1 | J41: =C41 -> 5339247 | K41: =IFERROR(J41-I41,0) -> -361806.08 | L41: =IFERROR((J41-I41)/ABS(I41),0) -> -0.063463026 | M41: =IF(L41>=0,"🟢 On Track",IF(L41>=-0.1,"🟡 Watch","🔴 At Risk")) -> 🟡 Watch
A42: TOTAL SDS | B42: =SUM(B36:B41) -> 15323315 | C42: =SUM(C36:C41) -> 14831549 | D42: =IFERROR(C42-B42,0) -> -491766 | E42: =IFERROR((C42-B42)/ABS(B42),0) -> -0.032092664 | F42: =IF(E42>=0,"🟢 On Track",IF(E42>=-0.1,"🟡 Watch","🔴 At Risk")) -> 🟡 Watch | H42: TOTAL SDS | I42: =SUM(I36:I41) -> 15527258 | J42: =SUM(J36:J41) -> 14831549 | K42: =IFERROR(J42-I42,0) -> -695708.55 | L42: =IFERROR((J42-I42)/ABS(I42),0) -> -0.04480563 | M42: =IF(L42>=0,"🟢 On Track",IF(L42>=-0.1,"🟡 Watch","🔴 At Risk")) -> 🟡 Watch
A45: BUDGET vs FORECAST Q3 | H45: TARGET vs FORECAST Q3
A46: Based on actuals + forecasted months | H46: Based on actuals + forecasted months
A47: VERTICAL | B47: 2026 Budget | C47: Forecast | D47: $ Difference | E47: % Diff | F47: STATUS | H47: VERTICAL | I47: 2026 Target | J47: Forecast | K47: $ Difference | L47: % Diff | M47: STATUS
A48: Rotowire | B48: 3827398 | C48: =Forecast!H8+Forecast!I8+Forecast!J8 -> 4763398 | D48: =IFERROR(C48-B48,0) -> 936000 | E48: =IFERROR((C48-B48)/ABS(B48),0) -> 0.24455257 | F48: =IF(E48>=0,"🟢 On Track",IF(E48>=-0.1,"🟡 Watch","🔴 At Risk")) -> 🟢 On Track | H48: Rotowire | I48: 4046590.5 | J48: =C48 -> 4763398 | K48: =IFERROR(J48-I48,0) -> 716807.5 | L48: =IFERROR((J48-I48)/ABS(I48),0) -> 0.17713863 | M48: =IF(L48>=0,"🟢 On Track",IF(L48>=-0.1,"🟡 Watch","🔴 At Risk")) -> 🟢 On Track
A49: Bookies | B49: 1744122 | C49: =Forecast!H25+Forecast!I25+Forecast!J25 -> 1172665 | D49: =IFERROR(C49-B49,0) -> -571457 | E49: =IFERROR((C49-B49)/ABS(B49),0) -> -0.32764738 | F49: =IF(E49>=0,"🟢 On Track",IF(E49>=-0.1,"🟡 Watch","🔴 At Risk")) -> 🔴 At Risk | H49: Bookies | I49: 1744122 | J49: =C49 -> 1172665 | K49: =IFERROR(J49-I49,0) -> -571457 | L49: =IFERROR((J49-I49)/ABS(I49),0) -> -0.32764738 | M49: =IF(L49>=0,"🟢 On Track",IF(L49>=-0.1,"🟡 Watch","🔴 At Risk")) -> 🔴 At Risk
A50: Partnerships | B50: 249999 | C50: =Forecast!H28+Forecast!I28+Forecast!J28 -> 1300000 | D50: =IFERROR(C50-B50,0) -> 1050001 | E50: =IFERROR((C50-B50)/ABS(B50),0) -> 4.2000208 | F50: =IF(E50>=0,"🟢 On Track",IF(E50>=-0.1,"🟡 Watch","🔴 At Risk")) -> 🟢 On Track | H50: Partnerships | I50: 314500 | J50: =C50 -> 1300000 | K50: =IFERROR(J50-I50,0) -> 985500 | L50: =IFERROR((J50-I50)/ABS(I50),0) -> 3.1335453 | M50: =IF(L50>=0,"🟢 On Track",IF(L50>=-0.1,"🟡 Watch","🔴 At Risk")) -> 🟢 On Track
A51: Local | B51: 930500 | C51: =Forecast!H57+Forecast!I57+Forecast!J57 -> 281800 | D51: =IFERROR(C51-B51,0) -> -648700 | E51: =IFERROR((C51-B51)/ABS(B51),0) -> -0.69715207 | F51: =IF(E51>=0,"🟢 On Track",IF(E51>=-0.1,"🟡 Watch","🔴 At Risk")) -> 🔴 At Risk | H51: Local | I51: 930500 | J51: =C51 -> 281800 | K51: =IFERROR(J51-I51,0) -> -648700 | L51: =IFERROR((J51-I51)/ABS(I51),0) -> -0.69715207 | M51: =IF(L51>=0,"🟢 On Track",IF(L51>=-0.1,"🟡 Watch","🔴 At Risk")) -> 🔴 At Risk
A52: OddsJam | B52: 4498125 | C52: =SUM(Forecast!H59:J61) -> 3634552 | D52: =IFERROR(C52-B52,0) -> -863573 | E52: =IFERROR((C52-B52)/ABS(B52),0) -> -0.1919851 | F52: =IF(E52>=0,"🟢 On Track",IF(E52>=-0.1,"🟡 Watch","🔴 At Risk")) -> 🔴 At Risk | H52: OddsJam | I52: 4121713.7 | J52: =C52 -> 3634552 | K52: =IFERROR(J52-I52,0) -> -487161.71 | L52: =IFERROR((J52-I52)/ABS(I52),0) -> -0.11819397 | M52: =IF(L52>=0,"🟢 On Track",IF(L52>=-0.1,"🟡 Watch","🔴 At Risk")) -> 🔴 At Risk
A53: OpticOdds | B53: 5923991 | C53: =SUM(Forecast!H62:J63) -> 5626595 | D53: =IFERROR(C53-B53,0) -> -297396 | E53: =IFERROR((C53-B53)/ABS(B53),0) -> -0.050201967 | F53: =IF(E53>=0,"🟢 On Track",IF(E53>=-0.1,"🟡 Watch","🔴 At Risk")) -> 🟡 Watch | H53: OpticOdds | I53: 6366774.3 | J53: =C53 -> 5626595 | K53: =IFERROR(J53-I53,0) -> -740179.29 | L53: =IFERROR((J53-I53)/ABS(I53),0) -> -0.11625656 | M53: =IF(L53>=0,"🟢 On Track",IF(L53>=-0.1,"🟡 Watch","🔴 At Risk")) -> 🔴 At Risk
A54: TOTAL SDS | B54: =SUM(B48:B53) -> 17174135 | C54: =SUM(C48:C53) -> 16779010 | D54: =IFERROR(C54-B54,0) -> -395125 | E54: =IFERROR((C54-B54)/ABS(B54),0) -> -0.023006981 | F54: =IF(E54>=0,"🟢 On Track",IF(E54>=-0.1,"🟡 Watch","🔴 At Risk")) -> 🟡 Watch | H54: TOTAL SDS | I54: =SUM(I48:I53) -> 17524200 | J54: =SUM(J48:J53) -> 16779010 | K54: =IFERROR(J54-I54,0) -> -745190.5 | L54: =IFERROR((J54-I54)/ABS(I54),0) -> -0.042523509 | M54: =IF(L54>=0,"🟢 On Track",IF(L54>=-0.1,"🟡 Watch","🔴 At Risk")) -> 🟡 Watch
A57: BUDGET vs FORECAST Q4 | H57: TARGET vs FORECAST Q4
A58: Based on actuals + forecasted months | H58: Based on actuals + forecasted months
A59: VERTICAL | B59: 2026 Budget | C59: Forecast | D59: $ Difference | E59: % Diff | F59: STATUS | H59: VERTICAL | I59: 2026 Target | J59: Forecast | K59: $ Difference | L59: % Diff | M59: STATUS
A60: Rotowire | B60: 4321874 | C60: =Forecast!K8+Forecast!L8+Forecast!M8 -> 4982877 | D60: =IFERROR(C60-B60,0) -> 661003 | E60: =IFERROR((C60-B60)/ABS(B60),0) -> 0.15294361 | F60: =IF(E60>=0,"🟢 On Track",IF(E60>=-0.1,"🟡 Watch","🔴 At Risk")) -> 🟢 On Track | H60: Rotowire | I60: 4569384.8 | J60: =C60 -> 4982877 | K60: =IFERROR(J60-I60,0) -> 413492.19 | L60: =IFERROR((J60-I60)/ABS(I60),0) -> 0.090491873 | M60: =IF(L60>=0,"🟢 On Track",IF(L60>=-0.1,"🟡 Watch","🔴 At Risk")) -> 🟢 On Track
A61: Bookies | B61: 1920366 | C61: =Forecast!K25+Forecast!L25+Forecast!M25 -> 1192152 | D61: =IFERROR(C61-B61,0) -> -728214 | E61: =IFERROR((C61-B61)/ABS(B61),0) -> -0.37920584 | F61: =IF(E61>=0,"🟢 On Track",IF(E61>=-0.1,"🟡 Watch","🔴 At Risk")) -> 🔴 At Risk | H61: Bookies | I61: 1920366 | J61: =C61 -> 1192152 | K61: =IFERROR(J61-I61,0) -> -728214 | L61: =IFERROR((J61-I61)/ABS(I61),0) -> -0.37920584 | M61: =IF(L61>=0,"🟢 On Track",IF(L61>=-0.1,"🟡 Watch","🔴 At Risk")) -> 🔴 At Risk
A62: Partnerships | B62: 249999 | C62: =Forecast!K28+Forecast!L28+Forecast!M28 -> 1500000 | D62: =IFERROR(C62-B62,0) -> 1250001 | E62: =IFERROR((C62-B62)/ABS(B62),0) -> 5.000024 | F62: =IF(E62>=0,"🟢 On Track",IF(E62>=-0.1,"🟡 Watch","🔴 At Risk")) -> 🟢 On Track | H62: Partnerships | I62: 314500 | J62: =C62 -> 1500000 | K62: =IFERROR(J62-I62,0) -> 1185500 | L62: =IFERROR((J62-I62)/ABS(I62),0) -> 3.7694754 | M62: =IF(L62>=0,"🟢 On Track",IF(L62>=-0.1,"🟡 Watch","🔴 At Risk")) -> 🟢 On Track
A63: Local | B63: 1281000 | C63: =Forecast!K57+Forecast!L57+Forecast!M57 -> 415800 | D63: =IFERROR(C63-B63,0) -> -865200 | E63: =IFERROR((C63-B63)/ABS(B63),0) -> -0.67540984 | F63: =IF(E63>=0,"🟢 On Track",IF(E63>=-0.1,"🟡 Watch","🔴 At Risk")) -> 🔴 At Risk | H63: Local | I63: 1281000 | J63: =C63 -> 415800 | K63: =IFERROR(J63-I63,0) -> -865200 | L63: =IFERROR((J63-I63)/ABS(I63),0) -> -0.67540984 | M63: =IF(L63>=0,"🟢 On Track",IF(L63>=-0.1,"🟡 Watch","🔴 At Risk")) -> 🔴 At Risk
A64: OddsJam | B64: 5738933 | C64: =SUM(Forecast!K59:M61) -> 4924362 | D64: =IFERROR(C64-B64,0) -> -814571 | E64: =IFERROR((C64-B64)/ABS(B64),0) -> -0.14193771 | F64: =IF(E64>=0,"🟢 On Track",IF(E64>=-0.1,"🟡 Watch","🔴 At Risk")) -> 🔴 At Risk | H64: OddsJam | I64: 5258688.6 | J64: =C64 -> 4924362 | K64: =IFERROR(J64-I64,0) -> -334326.63 | L64: =IFERROR((J64-I64)/ABS(I64),0) -> -0.063576046 | M64: =IF(L64>=0,"🟢 On Track",IF(L64>=-0.1,"🟡 Watch","🔴 At Risk")) -> 🟡 Watch
A65: OpticOdds | B65: 6615743 | C65: =SUM(Forecast!K62:M63) -> 6579657 | D65: =IFERROR(C65-B65,0) -> -36086 | E65: =IFERROR((C65-B65)/ABS(B65),0) -> -0.005454565 | F65: =IF(E65>=0,"🟢 On Track",IF(E65>=-0.1,"🟡 Watch","🔴 At Risk")) -> 🟡 Watch | H65: OpticOdds | I65: 7110230.7 | J65: =C65 -> 6579657 | K65: =IFERROR(J65-I65,0) -> -530573.66 | L65: =IFERROR((J65-I65)/ABS(I65),0) -> -0.07462116 | M65: =IF(L65>=0,"🟢 On Track",IF(L65>=-0.1,"🟡 Watch","🔴 At Risk")) -> 🟡 Watch
A66: TOTAL SDS | B66: =SUM(B60:B65) -> 20127915 | C66: =SUM(C60:C65) -> 19594848 | D66: =IFERROR(C66-B66,0) -> -533067 | E66: =IFERROR((C66-B66)/ABS(B66),0) -> -0.026483965 | F66: =IF(E66>=0,"🟢 On Track",IF(E66>=-0.1,"🟡 Watch","🔴 At Risk")) -> 🟡 Watch | H66: TOTAL SDS | I66: =SUM(I60:I65) -> 20454170 | J66: =SUM(J60:J65) -> 19594848 | K66: =IFERROR(J66-I66,0) -> -859322.1 | L66: =IFERROR((J66-I66)/ABS(I66),0) -> -0.042012074 | M66: =IF(L66>=0,"🟢 On Track",IF(L66>=-0.1,"🟡 Watch","🔴 At Risk")) -> 🟡 Watch
A74: 25A vs FORECAST
A75: VERTICAL | B75: 2025 Actuals | C75: Forecast | D75: $ Difference | E75: % Diff
A76: Rotowire | B76: 11303536 | C76: =C11 -> 17380964 | D76: =IFERROR(C76-B76,0) -> 6077428 | E76: =IFERROR((C76-B76)/ABS(B76),0) -> 0.53765722
A77: Bookies | B77: 4871880 | C77: =C12 -> 3742664.2 | D77: =IFERROR(C77-B77,0) -> -1129215.8 | E77: =IFERROR((C77-B77)/ABS(B77),0) -> -0.23178236
A78: Partnerships | B78: 1549731 | C78: =C13 -> 5611993.2 | D78: =IFERROR(C78-B78,0) -> 4062262.2 | E78: =IFERROR((C78-B78)/ABS(B78),0) -> 2.6212692
A79: Local | B79: 2800286 | C79: =C14 -> 1233562.8 | D79: =IFERROR(C79-B79,0) -> -1566723.2 | E79: =IFERROR((C79-B79)/ABS(B79),0) -> -0.55948684
A80: OddsJam | B80: 22207241 | C80: =C15 -> 16915715 | D80: =IFERROR(C80-B80,0) -> -5291526.4 | E80: =IFERROR((C80-B80)/ABS(B80),0) -> -0.23827932
A81: OpticOdds | B81: 14320942 | C81: =C16 -> 22277275 | D81: =IFERROR(C81-B81,0) -> 7956332.3 | E81: =IFERROR((C81-B81)/ABS(B81),0) -> 0.55557325
A82: TOTAL SDS | B82: =SUM(B76:B81) -> 57053617 | C82: =SUM(C76:C81) -> 67162174 | D82: =IFERROR(C82-B82,0) -> 10108557 | E82: =IFERROR((C82-B82)/ABS(B82),0) -> 0.17717645
A85: 25A vs TARGET
A86: VERTICAL | B86: 2025 Actuals | C86: 2026 Target | D86: $ Difference | E86: % Diff
A87: Rotowire | B87: =B76 -> 11303536 | C87: =I11 -> 14850000 | D87: =IFERROR(C87-B87,0) -> 3546463.6 | E87: =IFERROR((C87-B87)/ABS(B87),0) -> 0.31374814
A88: Bookies | B88: =B77 -> 4871880 | C88: =I12 -> 6233352 | D88: =IFERROR(C88-B88,0) -> 1361472 | E88: =IFERROR((C88-B88)/ABS(B88),0) -> 0.27945516
A89: Partnerships | B89: =B78 -> 1549731 | C89: =I13 -> 1258000 | D89: =IFERROR(C89-B89,0) -> -291731 | E89: =IFERROR((C89-B89)/ABS(B89),0) -> -0.18824622
A90: Local | B90: =B79 -> 2800286 | C90: =I14 -> 3731000 | D90: =IFERROR(C90-B90,0) -> 930714 | E90: =IFERROR((C90-B90)/ABS(B90),0) -> 0.33236391
A91: OddsJam | B91: =B80 -> 22207241 | C91: =I15 -> 19027500 | D91: =IFERROR(C91-B91,0) -> -3179741.1 | E91: =IFERROR((C91-B91)/ABS(B91),0) -> -0.14318488
A92: OpticOdds | B92: =B81 -> 14320942 | C92: =I16 -> 24283000 | D92: =IFERROR(C92-B92,0) -> 9962057.8 | E92: =IFERROR((C92-B92)/ABS(B92),0) -> 0.69562866
A93: TOTAL SDS | B93: =SUM(B87:B92) -> 57053617 | C93: =SUM(C87:C92) -> 69382852 | D93: =IFERROR(C93-B93,0) -> 12329235 | E93: =IFERROR((C93-B93)/ABS(B93),0) -> 0.2160991
A96: 25A vs BUDGET
A97: VERTICAL | B97: 2025 Actuals | C97: 2026 Budget | D97: $ Difference | E97: % Diff
A98: Rotowire | B98: =B76 -> 11303536 | C98: =B11 -> 14045617 | D98: =IFERROR(C98-B98,0) -> 2742080.6 | E98: =IFERROR((C98-B98)/ABS(B98),0) -> 0.24258608
A99: Bookies | B99: =B77 -> 4871880 | C99: =B12 -> 6233352 | D99: =IFERROR(C99-B99,0) -> 1361472 | E99: =IFERROR((C99-B99)/ABS(B99),0) -> 0.27945516
A100: Partnerships | B100: =B78 -> 1549731 | C100: =B13 -> 999996 | D100: =IFERROR(C100-B100,0) -> -549735 | E100: =IFERROR((C100-B100)/ABS(B100),0) -> -0.3547293
A101: Local | B101: =B79 -> 2800286 | C101: =B14 -> 3731000 | D101: =IFERROR(C101-B101,0) -> 930714 | E101: =IFERROR((C101-B101)/ABS(B101),0) -> 0.33236391
A102: OddsJam | B102: =B80 -> 22207241 | C102: =B15 -> 20765167 | D102: =IFERROR(C102-B102,0) -> -1442074.1 | E102: =IFERROR((C102-B102)/ABS(B102),0) -> -0.064937112
A103: OpticOdds | B103: =B81 -> 14320942 | C103: =B16 -> 22594216 | D103: =IFERROR(C103-B103,0) -> 8273273.8 | E103: =IFERROR((C103-B103)/ABS(B103),0) -> 0.57770457
A104: TOTAL SDS | B104: =SUM(B98:B103) -> 57053617 | C104: =SUM(C98:C103) -> 68369348 | D104: =IFERROR(C104-B104,0) -> 11315731 | E104: =IFERROR((C104-B104)/ABS(B104),0) -> 0.19833504

Sheet Forecast
A1: 2026 SDS Forecast
A2: VERTICAL / LINE | B2: Jan | C2: Feb | D2: Mar | E2: Apr | F2: May | G2: Jun | H2: Jul | I2: Aug | J2: Sep | K2: Oct | L2: Nov | M2: Dec | N2: FULL YEAR
A3: ROTOWIRE | B3: =IF(Rotowire!C4=0,"FORECAST","ACTUAL") -> ACTUAL | C3: =IF(Rotowire!D4=0,"FORECAST","ACTUAL") -> ACTUAL | D3: =IF(Rotowire!E4=0,"FORECAST","ACTUAL") -> ACTUAL | E3: =IF(Rotowire!F4=0,"FORECAST","ACTUAL") -> FORECAST | F3: =IF(Rotowire!G4=0,"FORECAST","ACTUAL") -> FORECAST | G3: =IF(Rotowire!H4=0,"FORECAST","ACTUAL") -> FORECAST | H3: =IF(Rotowire!I4=0,"FORECAST","ACTUAL") -> FORECAST | I3: =IF(Rotowire!J4=0,"FORECAST","ACTUAL") -> FORECAST | ... M3: =IF(Rotowire!N4=0,"FORECAST","ACTUAL") -> FORECAST
A4: B2C Subs | B4: =IF(Rotowire!C4=0,Rotowire!C6,Rotowire!C4) -> 474038.26 | C4: =IF(Rotowire!D4=0,Rotowire!D6,Rotowire!D4) -> 459134.72 | D4: =IF(Rotowire!E4=0,Rotowire!E6,Rotowire!E4) -> 552360.2 | E4: =IF(Rotowire!F4=0,Rotowire!F6,Rotowire!F4) -> 459073 | F4: =IF(Rotowire!G4=0,Rotowire!G6,Rotowire!G4) -> 452554 | G4: =IF(Rotowire!H4=0,Rotowire!H6,Rotowire!H4) -> 478438 | H4: =IF(Rotowire!I4=0,Rotowire!I6,Rotowire!I4) -> 491501 | I4: =IF(Rotowire!J4=0,Rotowire!J6,Rotowire!J4) -> 751620 | ... M4: =IF(Rotowire!N4=0,Rotowire!N6,Rotowire!N4) -> 681276 | N4: =SUM(B4:M4) -> 7030873.2
A5: Advertising | B5: =IF(Rotowire!C11=0,Rotowire!C13,Rotowire!C11) -> 111988.73 | C5: =IF(Rotowire!D11=0,Rotowire!D13,Rotowire!D11) -> 103856.8 | D5: =IF(Rotowire!E11=0,Rotowire!E13,Rotowire!E11) -> 134400.81 | E5: =IF(Rotowire!F11=0,Rotowire!F13,Rotowire!F11) -> 114000 | F5: =IF(Rotowire!G11=0,Rotowire!G13,Rotowire!G11) -> 79000 | G5: =IF(Rotowire!H11=0,Rotowire!H13,Rotowire!H11) -> 74000 | H5: =IF(Rotowire!I11=0,Rotowire!I13,Rotowire!I11) -> 82000 | I5: =IF(Rotowire!J11=0,Rotowire!J13,Rotowire!J11) -> 124000 | ... M5: =IF(Rotowire!N11=0,Rotowire!N13,Rotowire!N11) -> 124000 | N5: =SUM(B5:M5) -> 1302246.3
A6: B2B Content | B6: =IF(Rotowire!C18=0,Rotowire!C20,Rotowire!C18) -> 243987.32 | C6: =IF(Rotowire!D18=0,Rotowire!D20,Rotowire!D18) -> 236446.5 | D6: =IF(Rotowire!E18=0,Rotowire!E20,Rotowire!E18) -> 248430.63 | E6: =IF(Rotowire!F18=0,Rotowire!F20,Rotowire!F18) -> 254000 | F6: =IF(Rotowire!G18=0,Rotowire!G20,Rotowire!G18) -> 264000 | G6: =IF(Rotowire!H18=0,Rotowire!H20,Rotowire!H18) -> 274000 | H6: =IF(Rotowire!I18=0,Rotowire!I20,Rotowire!I18) -> 311000 | I6: =IF(Rotowire!J18=0,Rotowire!J20,Rotowire!J18) -> 321000 | ... M6: =IF(Rotowire!N18=0,Rotowire!N20,Rotowire!N18) -> 337000 | N6: =SUM(B6:M6) -> 3476864.5
A7: Rotowire Affiliate | B7: =IF(Bookies!C109=0,Bookies!C111,Bookies!C109) -> 373629.35 | C7: =IF(Bookies!D109=0,Bookies!D111,Bookies!D109) -> 478517.09 | D7: =IF(Bookies!E109=0,Bookies!E111,Bookies!E109) -> 568834.08 | E7: =IF(Bookies!F109=0,Bookies!F111,Bookies!F109) -> 500000 | F7: =IF(Bookies!G109=0,Bookies!G111,Bookies!G109) -> 350000 | G7: =IF(Bookies!H109=0,Bookies!H111,Bookies!H109) -> 350000 | H7: =IF(Bookies!I109=0,Bookies!I111,Bookies!I109) -> 350000 | I7: =IF(Bookies!J109=0,Bookies!J111,Bookies!J109) -> 500000 | ... M7: =IF(Bookies!N109=0,Bookies!N111,Bookies!N109) -> 500000 | N7: =SUM(B7:M7) -> 5570980.5
A8: SUBTOTAL — Rotowire | B8: =SUM(B4:B7) -> 1203643.7 | C8: =SUM(C4:C7) -> 1277955.1 | D8: =SUM(D4:D7) -> 1504025.7 | E8: =SUM(E4:E7) -> 1327073 | F8: =SUM(F4:F7) -> 1145554 | G8: =SUM(G4:G7) -> 1176438 | H8: =SUM(H4:H7) -> 1234501 | I8: =SUM(I4:I7) -> 1696620 | ... N8: =SUM(N4:N7) -> 17380964
A9: SPORTS AFFILIATE | B9: =IF(Bookies!C4=0,"FORECAST","ACTUAL") -> ACTUAL | C9: =IF(Bookies!D4=0,"FORECAST","ACTUAL") -> ACTUAL | D9: =IF(Bookies!E4=0,"FORECAST","ACTUAL") -> ACTUAL | E9: =IF(Bookies!F4=0,"FORECAST","ACTUAL") -> FORECAST | F9: =IF(Bookies!G4=0,"FORECAST","ACTUAL") -> FORECAST | G9: =IF(Bookies!H4=0,"FORECAST","ACTUAL") -> FORECAST | H9: =IF(Bookies!I4=0,"FORECAST","ACTUAL") -> FORECAST | I9: =IF(Bookies!J4=0,"FORECAST","ACTUAL") -> FORECAST | ... M9: =IF(Bookies!N4=0,"FORECAST","ACTUAL") -> FORECAST
A10: Bookies US | B10: =IF(Bookies!C4=0,Bookies!C6,Bookies!C4) -> -3260.2155 | C10: =IF(Bookies!D4=0,Bookies!D6,Bookies!D4) -> 44660 | D10: =IF(Bookies!E4=0,Bookies!E6,Bookies!E4) -> 2249 | E10: =IF(Bookies!F4=0,Bookies!F6,Bookies!F4) -> 55000 | F10: =IF(Bookies!G4=0,Bookies!G6,Bookies!G4) -> 55000 | G10: =IF(Bookies!H4=0,Bookies!H6,Bookies!H4) -> 55000 | H10: =IF(Bookies!I4=0,Bookies!I6,Bookies!I4) -> 95000 | I10: =IF(Bookies!J4=0,Bookies!J6,Bookies!J4) -> 105000 | ... M10: =IF(Bookies!N4=0,Bookies!N6,Bookies!N4) -> 105000 | N10: =SUM(B10:M10) -> 873648.78
A11: Bookies UK | B11: =IF(Bookies!C11=0,Bookies!C13,Bookies!C11) -> 212757.88 | C11: =IF(Bookies!D11=0,Bookies!D13,Bookies!D11) -> 148559.81 | D11: =IF(Bookies!E11=0,Bookies!E13,Bookies!E11) -> 9433 | E11: =IF(Bookies!F11=0,Bookies!F13,Bookies!F11) -> 150000 | F11: =IF(Bookies!G11=0,Bookies!G13,Bookies!G11) -> 150000 | G11: =IF(Bookies!H11=0,Bookies!H13,Bookies!H11) -> 150000 | H11: =IF(Bookies!I11=0,Bookies!I13,Bookies!I11) -> 150000 | I11: =IF(Bookies!J11=0,Bookies!J13,Bookies!J11) -> 215000 | ... M11: =IF(Bookies!N11=0,Bookies!N13,Bookies!N11) -> 200000 | N11: =SUM(B11:M11) -> 1990750.7
A12: Bookies IE | B12: =IF(Bookies!C18=0,Bookies!C20,Bookies!C18) -> 2024.5313 | C12: =IF(Bookies!D18=0,Bookies!D20,Bookies!D18) -> 6347.5797 | D12: =IF(Bookies!E18=0,Bookies!E20,Bookies!E18) -> 6358 | E12: =IF(Bookies!F18=0,Bookies!F20,Bookies!F18) -> 13500 | F12: =IF(Bookies!G18=0,Bookies!G20,Bookies!G18) -> 12000 | G12: =IF(Bookies!H18=0,Bookies!H20,Bookies!H18) -> 13500 | H12: =IF(Bookies!I18=0,Bookies!I20,Bookies!I18) -> 12000 | I12: =IF(Bookies!J18=0,Bookies!J20,Bookies!J18) -> 14000 | ... M12: =IF(Bookies!N18=0,Bookies!N20,Bookies!N18) -> 10000 | N12: =SUM(B12:M12) -> 125730.11
A13: Bookies IN | B13: =IF(Bookies!C25=0,Bookies!C27,Bookies!C25) -> 5566.1161 | C13: =IF(Bookies!D25=0,Bookies!D27,Bookies!D25) -> 14370.106 | D13: =IF(Bookies!E25=0,Bookies!E27,Bookies!E25) -> 7935 | E13: =IF(Bookies!F25=0,Bookies!F27,Bookies!F25) -> 8000 | F13: =IF(Bookies!G25=0,Bookies!G27,Bookies!G25) -> 8000 | G13: =IF(Bookies!H25=0,Bookies!H27,Bookies!H25) -> 8000 | H13: =IF(Bookies!I25=0,Bookies!I27,Bookies!I25) -> 8000 | I13: =IF(Bookies!J25=0,Bookies!J27,Bookies!J25) -> 8000 | ... M13: =IF(Bookies!N25=0,Bookies!N27,Bookies!N25) -> 8000 | N13: =SUM(B13:M13) -> 99871.222
A14: Bookies CA | B14: =IF(Bookies!C32=0,Bookies!C34,Bookies!C32) -> 9408.0531 | C14: =IF(Bookies!D32=0,Bookies!D34,Bookies!D32) -> 4565.4974 | D14: =IF(Bookies!E32=0,Bookies!E34,Bookies!E32) -> 14841 | E14: =IF(Bookies!F32=0,Bookies!F34,Bookies!F32) -> 14500 | F14: =IF(Bookies!G32=0,Bookies!G34,Bookies!G32) -> 14500 | G14: =IF(Bookies!H32=0,Bookies!H34,Bookies!H32) -> 15000 | H14: =IF(Bookies!I32=0,Bookies!I34,Bookies!I32) -> 16500 | I14: =IF(Bookies!J32=0,Bookies!J34,Bookies!J32) -> 16500 | ... M14: =IF(Bookies!N32=0,Bookies!N34,Bookies!N32) -> 18000 | N14: =SUM(B14:M14) -> 180314.55
A15: Bookies AU | B15: =IF(Bookies!C39=0,Bookies!C41,Bookies!C39) -> 2960.88 | C15: =IF(Bookies!D39=0,Bookies!D41,Bookies!D39) -> 687.37603 | D15: =IF(Bookies!E39=0,Bookies!E41,Bookies!E39) -> -1533 | E15: =IF(Bookies!F39=0,Bookies!F41,Bookies!F39) -> 1500 | F15: =IF(Bookies!G39=0,Bookies!G41,Bookies!G39) -> 1500 | G15: =IF(Bookies!H39=0,Bookies!H41,Bookies!H39) -> 1500 | H15: =IF(Bookies!I39=0,Bookies!I41,Bookies!I39) -> 1500 | I15: =IF(Bookies!J39=0,Bookies!J41,Bookies!J39) -> 1500 | ... M15: =IF(Bookies!N39=0,Bookies!N41,Bookies!N39) -> 1500 | N15: =SUM(B15:M15) -> 15615.256
A16: Bookies NZ | B16: =IF(Bookies!C46=0,Bookies!C48,Bookies!C46) -> 1721.4416 | C16: =IF(Bookies!D46=0,Bookies!D48,Bookies!D46) -> 4112.945 | D16: =IF(Bookies!E46=0,Bookies!E48,Bookies!E46) -> 4550 | E16: =IF(Bookies!F46=0,Bookies!F48,Bookies!F46) -> 7500 | F16: =IF(Bookies!G46=0,Bookies!G48,Bookies!G46) -> 8000 | G16: =IF(Bookies!H46=0,Bookies!H48,Bookies!H46) -> 8000 | H16: =IF(Bookies!I46=0,Bookies!I48,Bookies!I46) -> 8500 | I16: =IF(Bookies!J46=0,Bookies!J48,Bookies!J46) -> 8500 | ... M16: =IF(Bookies!N46=0,Bookies!N48,Bookies!N46) -> 8500 | N16: =SUM(B16:M16) -> 86884.387
A17: Bookies MX | B17: =IF(Bookies!C53=0,Bookies!C55,Bookies!C53) -> 8337.3099 | C17: =IF(Bookies!D53=0,Bookies!D55,Bookies!D53) -> 3992.0958 | D17: =IF(Bookies!E53=0,Bookies!E55,Bookies!E53) -> 1794 | E17: =IF(Bookies!F53=0,Bookies!F55,Bookies!F53) -> 5500 | F17: =IF(Bookies!G53=0,Bookies!G55,Bookies!G53) -> 5500 | G17: =IF(Bookies!H53=0,Bookies!H55,Bookies!H53) -> 5500 | H17: =IF(Bookies!I53=0,Bookies!I55,Bookies!I53) -> 5500 | I17: =IF(Bookies!J53=0,Bookies!J55,Bookies!J53) -> 5500 | ... M17: =IF(Bookies!N53=0,Bookies!N55,Bookies!N53) -> 5500 | N17: =SUM(B17:M17) -> 63623.406
A18: Bookies NG | B18: =IF(Bookies!C60=0,Bookies!C62,Bookies!C60) -> 0.648964 | C18: =IF(Bookies!D60=0,Bookies!D62,Bookies!D60) -> 0 | D18: =IF(Bookies!E60=0,Bookies!E62,Bookies!E60) -> 0 | E18: =IF(Bookies!F60=0,Bookies!F62,Bookies!F60) -> 0 | F18: =IF(Bookies!G60=0,Bookies!G62,Bookies!G60) -> 0 | G18: =IF(Bookies!H60=0,Bookies!H62,Bookies!H60) -> 0 | H18: =IF(Bookies!I60=0,Bookies!I62,Bookies!I60) -> 0 | I18: =IF(Bookies!J60=0,Bookies!J62,Bookies!J60) -> 0 | ... M18: =IF(Bookies!N60=0,Bookies!N62,Bookies!N60) -> 0 | N18: =SUM(B18:M18) -> 0.648964
A19: Bookies NL | B19: =IF(Bookies!C67=0,Bookies!C69,Bookies!C67) -> 601.71932 | C19: =IF(Bookies!D67=0,Bookies!D69,Bookies!D67) -> 224.09292 | D19: =IF(Bookies!E67=0,Bookies!E69,Bookies!E67) -> 15 | E19: =IF(Bookies!F67=0,Bookies!F69,Bookies!F67) -> 1500 | F19: =IF(Bookies!G67=0,Bookies!G69,Bookies!G67) -> 1500 | G19: =IF(Bookies!H67=0,Bookies!H69,Bookies!H67) -> 1500 | H19: =IF(Bookies!I67=0,Bookies!I69,Bookies!I67) -> 1500 | I19: =IF(Bookies!J67=0,Bookies!J69,Bookies!J67) -> 1500 | ... M19: =IF(Bookies!N67=0,Bookies!N69,Bookies!N67) -> 1500 | N19: =SUM(B19:M19) -> 14340.812
A20: Bookies BR | B20: =IF(Bookies!C74=0,Bookies!C76,Bookies!C74) -> 111.69258 | C20: =IF(Bookies!D74=0,Bookies!D76,Bookies!D74) -> 260.21518 | D20: =IF(Bookies!E74=0,Bookies!E76,Bookies!E74) -> -77 | E20: =IF(Bookies!F74=0,Bookies!F76,Bookies!F74) -> 100 | F20: =IF(Bookies!G74=0,Bookies!G76,Bookies!G74) -> 100 | G20: =IF(Bookies!H74=0,Bookies!H76,Bookies!H74) -> 100 | H20: =IF(Bookies!I74=0,Bookies!I76,Bookies!I74) -> 100 | I20: =IF(Bookies!J74=0,Bookies!J76,Bookies!J74) -> 100 | ... M20: =IF(Bookies!N74=0,Bookies!N76,Bookies!N74) -> 100 | N20: =SUM(B20:M20) -> 1194.9078
A21: Bookies GX | B21: =IF(Bookies!C81=0,Bookies!C83,Bookies!C81) -> 167.97545 | C21: =IF(Bookies!D81=0,Bookies!D83,Bookies!D81) -> 546 | D21: =IF(Bookies!E81=0,Bookies!E83,Bookies!E81) -> 651 | E21: =IF(Bookies!F81=0,Bookies!F83,Bookies!F81) -> 100 | F21: =IF(Bookies!G81=0,Bookies!G83,Bookies!G81) -> 100 | G21: =IF(Bookies!H81=0,Bookies!H83,Bookies!H81) -> 100 | H21: =IF(Bookies!I81=0,Bookies!I83,Bookies!I81) -> 100 | I21: =IF(Bookies!J81=0,Bookies!J83,Bookies!J81) -> 100 | ... M21: =IF(Bookies!N81=0,Bookies!N83,Bookies!N81) -> 100 | N21: =SUM(B21:M21) -> 2264.9755
A22: Bookies ES | B22: =IF(Bookies!C88=0,Bookies!C90,Bookies!C88) -> 100 | C22: =IF(Bookies!D88=0,Bookies!D90,Bookies!D88) -> 5.797546 | D22: =IF(Bookies!E88=0,Bookies!E90,Bookies!E88) -> 289 | E22: =IF(Bookies!F88=0,Bookies!F90,Bookies!F88) -> 500 | F22: =IF(Bookies!G88=0,Bookies!G90,Bookies!G88) -> 500 | G22: =IF(Bookies!H88=0,Bookies!H90,Bookies!H88) -> 500 | H22: =IF(Bookies!I88=0,Bookies!I90,Bookies!I88) -> 1000 | I22: =IF(Bookies!J88=0,Bookies!J90,Bookies!J88) -> 1000 | ... M22: =IF(Bookies!N88=0,Bookies!N90,Bookies!N88) -> 1000 | N22: =SUM(B22:M22) -> 7894.7975
A23: Bookmakers | B23: =IF(Bookies!C95=0,Bookies!C97,Bookies!C95) -> -13263.989 | C23: =IF(Bookies!D95=0,Bookies!D97,Bookies!D95) -> 17347.598 | D23: =IF(Bookies!E95=0,Bookies!E97,Bookies!E95) -> 14186 | E23: =IF(Bookies!F95=0,Bookies!F97,Bookies!F95) -> 12500 | F23: =IF(Bookies!G95=0,Bookies!G97,Bookies!G95) -> 12500 | G23: =IF(Bookies!H95=0,Bookies!H97,Bookies!H95) -> 12500 | H23: =IF(Bookies!I95=0,Bookies!I97,Bookies!I95) -> 12500 | I23: =IF(Bookies!J95=0,Bookies!J97,Bookies!J95) -> 12500 | ... M23: =IF(Bookies!N95=0,Bookies!N97,Bookies!N95) -> 12500 | N23: =SUM(B23:M23) -> 130769.61
A24: BetSync | B24: =IF(Bookies!C102=0,Bookies!C104,Bookies!C102) -> 0 | C24: =IF(Bookies!D102=0,Bookies!D104,Bookies!D102) -> 1498 | D24: =IF(Bookies!E102=0,Bookies!E104,Bookies!E102) -> 5273 | E24: =IF(Bookies!F102=0,Bookies!F104,Bookies!F102) -> 7382 | F24: =IF(Bookies!G102=0,Bookies!G104,Bookies!G102) -> 8859 | G24: =IF(Bookies!H102=0,Bookies!H104,Bookies!H102) -> 10631 | H24: =IF(Bookies!I102=0,Bookies!I104,Bookies!I102) -> 11694 | I24: =IF(Bookies!J102=0,Bookies!J104,Bookies!J102) -> 14032 | ... N24: =IF(Bookies!O102=0,Bookies!O104,Bookies!O102) -> 6771
A25: SUBTOTAL — Sports Affiliate | B25: =SUM(B10:B24) -> 227234.04 | C25: =SUM(C10:C24) -> 247177.11 | D25: =SUM(D10:D24) -> 65964 | E25: =SUM(E10:E24) -> 277582 | F25: =SUM(F10:F24) -> 278059 | G25: =SUM(G10:G24) -> 281831 | H25: =SUM(H10:H24) -> 323894 | I25: =SUM(I10:I24) -> 403232 | ... M25: =SUM(M10:M24) -> 400797 | N25: =SUM(B25:M25) -> 3742664.2
A26: PARTNERSHIPS | B26: =IF(Partnerships!C4=0,"FORECAST","ACTUAL") -> ACTUAL | C26: =IF(Partnerships!D4=0,"FORECAST","ACTUAL") -> ACTUAL | D26: =IF(Partnerships!E4=0,"FORECAST","ACTUAL") -> ACTUAL | E26: =IF(Partnerships!F4=0,"FORECAST","ACTUAL") -> FORECAST | F26: =IF(Partnerships!G4=0,"FORECAST","ACTUAL") -> FORECAST | G26: =IF(Partnerships!H4=0,"FORECAST","ACTUAL") -> FORECAST | H26: =IF(Partnerships!I4=0,"FORECAST","ACTUAL") -> FORECAST | I26: =IF(Partnerships!J4=0,"FORECAST","ACTUAL") -> FORECAST | ... M26: =IF(Partnerships!N4=0,"FORECAST","ACTUAL") -> FORECAST
A27: GAN Affiliate | B27: =IF(Partnerships!C4=0,Partnerships!C6,Partnerships!C4) -> 618795.88 | C27: =IF(Partnerships!D4=0,Partnerships!D6,Partnerships!D4) -> 746747.75 | D27: =IF(Partnerships!E4=0,Partnerships!E6,Partnerships!E4) -> 496449.58 | E27: =IF(Partnerships!F4=0,Partnerships!F6,Partnerships!F4) -> 350000 | F27: =IF(Partnerships!G4=0,Partnerships!G6,Partnerships!G4) -> 300000 | G27: =IF(Partnerships!H4=0,Partnerships!H6,Partnerships!H4) -> 300000 | H27: =IF(Partnerships!I4=0,Partnerships!I6,Partnerships!I4) -> 300000 | I27: =IF(Partnerships!J4=0,Partnerships!J6,Partnerships!J4) -> 400000 | ... M27: =IF(Partnerships!N4=0,Partnerships!N6,Partnerships!N4) -> 500000 | N27: =SUM(B27:M27) -> 5611993.2
A28: SUBTOTAL — Partnerships | B28: =SUM(B27:B27) -> 618795.88 | C28: =SUM(C27:C27) -> 746747.75 | D28: =SUM(D27:D27) -> 496449.58 | E28: =SUM(E27:E27) -> 350000 | F28: =SUM(F27:F27) -> 300000 | G28: =SUM(G27:G27) -> 300000 | H28: =SUM(H27:H27) -> 300000 | I28: =SUM(I27:I27) -> 400000 | ... M28: =SUM(M27:M27) -> 500000 | N28: =SUM(B28:M28) -> 5611993.2
A29: LOCAL | B29: =IF(Local!C4=0,"FORECAST","ACTUAL") -> ACTUAL | C29: =IF(Local!D4=0,"FORECAST","ACTUAL") -> ACTUAL | D29: =IF(Local!E4=0,"FORECAST","ACTUAL") -> ACTUAL | E29: =IF(Local!F4=0,"FORECAST","ACTUAL") -> FORECAST | F29: =IF(Local!G4=0,"FORECAST","ACTUAL") -> FORECAST | G29: =IF(Local!H4=0,"FORECAST","ACTUAL") -> FORECAST | H29: =IF(Local!I4=0,"FORECAST","ACTUAL") -> FORECAST | I29: =IF(Local!J4=0,"FORECAST","ACTUAL") -> FORECAST | ... M29: =IF(Local!N4=0,"FORECAST","ACTUAL") -> FORECAST
A30: BetArizona | B30: =IF(Local!C4=0,Local!C6,Local!C4) -> 13350.067 | C30: =IF(Local!D4=0,Local!D6,Local!D4) -> 8927.3897 | D30: =IF(Local!E4=0,Local!E6,Local!E4) -> 15835.692 | E30: =IF(Local!F4=0,Local!F6,Local!F4) -> 5000 | F30: =IF(Local!G4=0,Local!G6,Local!G4) -> 3000 | G30: =IF(Local!H4=0,Local!H6,Local!H4) -> 3000 | H30: =IF(Local!I4=0,Local!I6,Local!I4) -> 3000 | I30: =IF(Local!J4=0,Local!J6,Local!J4) -> 5000 | ... M30: =IF(Local!N4=0,Local!N6,Local!N4) -> 15000 | N30: =SUM(B30:M30) -> 122113.15
A31: BetVirginia | B31: =IF(Local!C11=0,Local!C13,Local!C11) -> 10130.181 | C31: =IF(Local!D11=0,Local!D13,Local!D11) -> 2170.761 | D31: =IF(Local!E11=0,Local!E13,Local!E11) -> 4496.6503 | E31: =IF(Local!F11=0,Local!F13,Local!F11) -> 8000 | F31: =IF(Local!G11=0,Local!G13,Local!G11) -> 3000 | G31: =IF(Local!H11=0,Local!H13,Local!H11) -> 3000 | H31: =IF(Local!I11=0,Local!I13,Local!I11) -> 3000 | I31: =IF(Local!J11=0,Local!J13,Local!J11) -> 5000 | ... M31: =IF(Local!N11=0,Local!N13,Local!N11) -> 10000 | N31: =SUM(B31:M31) -> 74797.592
A32: BetKansas | B32: =IF(Local!C18=0,Local!C20,Local!C18) -> -9.983818 | C32: =IF(Local!D18=0,Local!D20,Local!D18) -> 14220.312 | D32: =IF(Local!E18=0,Local!E20,Local!E18) -> 9727.514 | E32: =IF(Local!F18=0,Local!F20,Local!F18) -> 2000 | F32: =IF(Local!G18=0,Local!G20,Local!G18) -> 1000 | G32: =IF(Local!H18=0,Local!H20,Local!H18) -> 1000 | H32: =IF(Local!I18=0,Local!I20,Local!I18) -> 1000 | I32: =IF(Local!J18=0,Local!J20,Local!J18) -> 5000 | ... M32: =IF(Local!N18=0,Local!N20,Local!N18) -> 15000 | N32: =SUM(B32:M32) -> 83937.842
A33: BetOhio | B33: =IF(Local!C25=0,Local!C27,Local!C25) -> 4945.2445 | C33: =IF(Local!D25=0,Local!D27,Local!D25) -> 2880.0743 | D33: =IF(Local!E25=0,Local!E27,Local!E25) -> 8564.9448 | E33: =IF(Local!F25=0,Local!F27,Local!F25) -> 2000 | F33: =IF(Local!G25=0,Local!G27,Local!G25) -> 1000 | G33: =IF(Local!H25=0,Local!H27,Local!H25) -> 1000 | H33: =IF(Local!I25=0,Local!I27,Local!I25) -> 1000 | I33: =IF(Local!J25=0,Local!J27,Local!J25) -> 3000 | ... M33: =IF(Local!N25=0,Local!N27,Local!N25) -> 10000 | N33: =SUM(B33:M33) -> 60390.264
A34: BetKentucky | B34: =IF(Local!C32=0,Local!C34,Local!C32) -> 2176.933 | C34: =IF(Local!D32=0,Local!D34,Local!D32) -> 1425.0822 | D34: =IF(Local!E32=0,Local!E34,Local!E32) -> 3628.2569 | E34: =IF(Local!F32=0,Local!F34,Local!F32) -> 2000 | F34: =IF(Local!G32=0,Local!G34,Local!G32) -> 1000 | G34: =IF(Local!H32=0,Local!H34,Local!H32) -> 1000 | H34: =IF(Local!I32=0,Local!I34,Local!I32) -> 1000 | I34: =IF(Local!J32=0,Local!J34,Local!J32) -> 3000 | ... M34: =IF(Local!N32=0,Local!N34,Local!N32) -> 5000 | N34: =SUM(B34:M34) -> 33230.272
A35: BetMassachusetts | B35: =IF(Local!C39=0,Local!C41,Local!C39) -> 7974.6974 | C35: =IF(Local!D39=0,Local!D41,Local!D39) -> 6956.5644 | D35: =IF(Local!E39=0,Local!E41,Local!E39) -> 2045.0664 | E35: =IF(Local!F39=0,Local!F41,Local!F39) -> 8000 | F35: =IF(Local!G39=0,Local!G41,Local!G39) -> 3000 | G35: =IF(Local!H39=0,Local!H41,Local!H39) -> 3000 | H35: =IF(Local!I39=0,Local!I41,Local!I39) -> 3000 | I35: =IF(Local!J39=0,Local!J41,Local!J39) -> 5000 | ... M35: =IF(Local!N39=0,Local!N41,Local!N39) -> 10000 | N35: =SUM(B35:M35) -> 74976.328
A36: BetTennessee | B36: =IF(Local!C46=0,Local!C48,Local!C46) -> 1911.806 | C36: =IF(Local!D46=0,Local!D48,Local!D46) -> -363.29582 | D36: =IF(Local!E46=0,Local!E48,Local!E46) -> 2161.5845 | E36: =IF(Local!F46=0,Local!F48,Local!F46) -> 2000 | F36: =IF(Local!G46=0,Local!G48,Local!G46) -> 1000 | G36: =IF(Local!H46=0,Local!H48,Local!H46) -> 1000 | H36: =IF(Local!I46=0,Local!I48,Local!I46) -> 1000 | I36: =IF(Local!J46=0,Local!J48,Local!J46) -> 3000 | ... M36: =IF(Local!N46=0,Local!N48,Local!N46) -> 5000 | N36: =SUM(B36:M36) -> 29710.095
A37: LouisianaBets | B37: =IF(Local!C53=0,Local!C55,Local!C53) -> -376.13058 | C37: =IF(Local!D53=0,Local!D55,Local!D53) -> -1212.1453 | D37: =IF(Local!E53=0,Local!E55,Local!E53) -> 1384.8506 | E37: =IF(Local!F53=0,Local!F55,Local!F53) -> 1000 | F37: =IF(Local!G53=0,Local!G55,Local!G53) -> 1000 | G37: =IF(Local!H53=0,Local!H55,Local!H53) -> 1000 | H37: =IF(Local!I53=0,Local!I55,Local!I53) -> 1000 | I37: =IF(Local!J53=0,Local!J55,Local!J53) -> 1000 | ... M37: =IF(Local!N53=0,Local!N55,Local!N53) -> 1000 | N37: =SUM(B37:M37) -> 8796.5747
A38: BetColorado | B38: =IF(Local!C60=0,Local!C62,Local!C60) -> 1756.431 | C38: =IF(Local!D60=0,Local!D62,Local!D60) -> 7497.8106 | D38: =IF(Local!E60=0,Local!E62,Local!E60) -> 1043.8384 | E38: =IF(Local!F60=0,Local!F62,Local!F60) -> 2000 | F38: =IF(Local!G60=0,Local!G62,Local!G60) -> 1000 | G38: =IF(Local!H60=0,Local!H62,Local!H60) -> 1000 | H38: =IF(Local!I60=0,Local!I62,Local!I60) -> 1000 | I38: =IF(Local!J60=0,Local!J62,Local!J60) -> 3000 | ... M38: =IF(Local!N60=0,Local!N62,Local!N60) -> 5000 | N38: =SUM(B38:M38) -> 36298.08
A39: IndianaBets | B39: =IF(Local!C67=0,Local!C69,Local!C67) -> 2.894005 | C39: =IF(Local!D67=0,Local!D69,Local!D67) -> 42.601367 | D39: =IF(Local!E67=0,Local!E69,Local!E67) -> 39.869312 | E39: =IF(Local!F67=0,Local!F69,Local!F67) -> 0 | F39: =IF(Local!G67=0,Local!G69,Local!G67) -> 0 | G39: =IF(Local!H67=0,Local!H69,Local!H67) -> 0 | H39: =IF(Local!I67=0,Local!I69,Local!I67) -> 0 | I39: =IF(Local!J67=0,Local!J69,Local!J67) -> 0 | ... M39: =IF(Local!N67=0,Local!N69,Local!N67) -> 0 | N39: =SUM(B39:M39) -> 85.364684
A40: IowaBets | B40: =IF(Local!C74=0,Local!C76,Local!C74) -> 84.286657 | C40: =IF(Local!D74=0,Local!D76,Local!D74) -> 268.81932 | D40: =IF(Local!E74=0,Local!E76,Local!E74) -> -18.937923 | E40: =IF(Local!F74=0,Local!F76,Local!F74) -> 100 | F40: =IF(Local!G74=0,Local!G76,Local!G74) -> 100 | G40: =IF(Local!H74=0,Local!H76,Local!H74) -> 100 | H40: =IF(Local!I74=0,Local!I76,Local!I74) -> 100 | I40: =IF(Local!J74=0,Local!J76,Local!J74) -> 100 | ... M40: =IF(Local!N74=0,Local!N76,Local!N74) -> 100 | N40: =SUM(B40:M40) -> 1234.1681
A41: EmpireStakes | B41: =IF(Local!C81=0,Local!C83,Local!C81) -> 353.48925 | C41: =IF(Local!D81=0,Local!D83,Local!D81) -> 275.81462 | D41: =IF(Local!E81=0,Local!E83,Local!E81) -> 355.8336 | E41: =IF(Local!F81=0,Local!F83,Local!F81) -> 500 | F41: =IF(Local!G81=0,Local!G83,Local!G81) -> 500 | G41: =IF(Local!H81=0,Local!H83,Local!H81) -> 500 | H41: =IF(Local!I81=0,Local!I83,Local!I81) -> 500 | I41: =IF(Local!J81=0,Local!J83,Local!J81) -> 500 | ... M41: =IF(Local!N81=0,Local!N83,Local!N81) -> 500 | N41: =SUM(B41:M41) -> 5485.1375
A42: IllinoisBet | B42: =IF(Local!C88=0,Local!C90,Local!C88) -> 2255.8122 | C42: =IF(Local!D88=0,Local!D90,Local!D88) -> 2409.3806 | D42: =IF(Local!E88=0,Local!E90,Local!E88) -> 577.10828 | E42: =IF(Local!F88=0,Local!F90,Local!F88) -> 1000 | F42: =IF(Local!G88=0,Local!G90,Local!G88) -> 1000 | G42: =IF(Local!H88=0,Local!H90,Local!H88) -> 1000 | H42: =IF(Local!I88=0,Local!I90,Local!I88) -> 1000 | I42: =IF(Local!J88=0,Local!J90,Local!J88) -> 1000 | ... M42: =IF(Local!N88=0,Local!N90,Local!N88) -> 1000 | N42: =SUM(B42:M42) -> 14242.301
A43: BetMaryland | B43: =IF(Local!C95=0,Local!C97,Local!C95) -> 4598.3043 | C43: =IF(Local!D95=0,Local!D97,Local!D95) -> 1835.8361 | D43: =IF(Local!E95=0,Local!E97,Local!E95) -> 2995.1123 | E43: =IF(Local!F95=0,Local!F97,Local!F95) -> 8000 | F43: =IF(Local!G95=0,Local!G97,Local!G95) -> 3000 | G43: =IF(Local!H95=0,Local!H97,Local!H95) -> 3000 | H43: =IF(Local!I95=0,Local!I97,Local!I95) -> 3000 | I43: =IF(Local!J95=0,Local!J97,Local!J95) -> 5000 | ... M43: =IF(Local!N95=0,Local!N97,Local!N95) -> 10000 | N43: =SUM(B43:M43) -> 67429.253
A44: PennStakes | B44: =IF(Local!C102=0,Local!C104,Local!C102) -> -453.70796 | C44: =IF(Local!D102=0,Local!D104,Local!D102) -> 9662.2558 | D44: =IF(Local!E102=0,Local!E104,Local!E102) -> 4833.3068 | E44: =IF(Local!F102=0,Local!F104,Local!F102) -> 1000 | F44: =IF(Local!G102=0,Local!G104,Local!G102) -> 1000 | G44: =IF(Local!H102=0,Local!H104,Local!H102) -> 1000 | H44: =IF(Local!I102=0,Local!I104,Local!I102) -> 1000 | I44: =IF(Local!J102=0,Local!J104,Local!J102) -> 1000 | ... M44: =IF(Local!N102=0,Local!N104,Local!N102) -> 1000 | N44: =SUM(B44:M44) -> 23041.855
A45: BetMichigan | B45: =IF(Local!C109=0,Local!C111,Local!C109) -> 2133.9535 | C45: =IF(Local!D109=0,Local!D111,Local!D109) -> 3677.5283 | D45: =IF(Local!E109=0,Local!E111,Local!E109) -> 1909.74 | E45: =IF(Local!F109=0,Local!F111,Local!F109) -> 2000 | F45: =IF(Local!G109=0,Local!G111,Local!G109) -> 1000 | G45: =IF(Local!H109=0,Local!H111,Local!H109) -> 1000 | H45: =IF(Local!I109=0,Local!I111,Local!I109) -> 1000 | I45: =IF(Local!J109=0,Local!J111,Local!J109) -> 1000 | ... M45: =IF(Local!N109=0,Local!N111,Local!N109) -> 1000 | N45: =SUM(B45:M45) -> 17721.222
A46: FloridaBet | B46: =IF(Local!C116=0,Local!C118,Local!C116) -> 142.19681 | C46: =IF(Local!D116=0,Local!D118,Local!D116) -> 69.952983 | D46: =IF(Local!E116=0,Local!E118,Local!E116) -> -849.1366 | E46: =IF(Local!F116=0,Local!F118,Local!F116) -> 500 | F46: =IF(Local!G116=0,Local!G118,Local!G116) -> 500 | G46: =IF(Local!H116=0,Local!H118,Local!H116) -> 500 | H46: =IF(Local!I116=0,Local!I118,Local!I116) -> 500 | I46: =IF(Local!J116=0,Local!J118,Local!J116) -> 500 | ... M46: =IF(Local!N116=0,Local!N118,Local!N116) -> 500 | N46: =SUM(B46:M46) -> 3863.0132
A47: BetCarolina | B47: =IF(Local!C123=0,Local!C125,Local!C123) -> 4363.5494 | C47: =IF(Local!D123=0,Local!D125,Local!D123) -> 5298.6387 | D47: =IF(Local!E123=0,Local!E125,Local!E123) -> 5417.3922 | E47: =IF(Local!F123=0,Local!F125,Local!F123) -> 3000 | F47: =IF(Local!G123=0,Local!G125,Local!G123) -> 3000 | G47: =IF(Local!H123=0,Local!H125,Local!H123) -> 3000 | H47: =IF(Local!I123=0,Local!I125,Local!I123) -> 3000 | I47: =IF(Local!J123=0,Local!J125,Local!J123) -> 4000 | ... M47: =IF(Local!N123=0,Local!N125,Local!N123) -> 5000 | N47: =SUM(B47:M47) -> 54079.58
A48: BetTexas | B48: =IF(Local!C130=0,Local!C132,Local!C130) -> 936.26584 | C48: =IF(Local!D130=0,Local!D132,Local!D130) -> -432.94901 | D48: =IF(Local!E130=0,Local!E132,Local!E130) -> -426.49199 | E48: =IF(Local!F130=0,Local!F132,Local!F130) -> 500 | F48: =IF(Local!G130=0,Local!G132,Local!G130) -> 500 | G48: =IF(Local!H130=0,Local!H132,Local!H130) -> 500 | H48: =IF(Local!I130=0,Local!I132,Local!I130) -> 500 | I48: =IF(Local!J130=0,Local!J132,Local!J130) -> 500 | ... M48: =IF(Local!N130=0,Local!N132,Local!N130) -> 500 | N48: =SUM(B48:M48) -> 4576.8248
A49: BetCalifornia | B49: =IF(Local!C137=0,Local!C139,Local!C137) -> 1059.3762 | C49: =IF(Local!D137=0,Local!D139,Local!D137) -> 485.38376 | D49: =IF(Local!E137=0,Local!E139,Local!E137) -> -1908.3346 | E49: =IF(Local!F137=0,Local!F139,Local!F137) -> 500 | F49: =IF(Local!G137=0,Local!G139,Local!G137) -> 500 | G49: =IF(Local!H137=0,Local!H139,Local!H137) -> 500 | H49: =IF(Local!I137=0,Local!I139,Local!I137) -> 500 | I49: =IF(Local!J137=0,Local!J139,Local!J137) -> 500 | ... M49: =IF(Local!N137=0,Local!N139,Local!N137) -> 500 | N49: =SUM(B49:M49) -> 4136.4254
A50: BetGeorgia | B50: =IF(Local!C144=0,Local!C146,Local!C144) -> -2553.5342 | C50: =IF(Local!D144=0,Local!D146,Local!D144) -> 778.41681 | D50: =IF(Local!E144=0,Local!E146,Local!E144) -> -4.983664 | E50: =IF(Local!F144=0,Local!F146,Local!F144) -> 500 | F50: =IF(Local!G144=0,Local!G146,Local!G144) -> 500 | G50: =IF(Local!H144=0,Local!H146,Local!H144) -> 500 | H50: =IF(Local!I144=0,Local!I146,Local!I144) -> 500 | I50: =IF(Local!J144=0,Local!J146,Local!J144) -> 500 | ... M50: =IF(Local!N144=0,Local!N146,Local!N144) -> 500 | N50: =SUM(B50:M50) -> 2719.8989
A51: MinnesotaBets | B51: =IF(Local!C151=0,Local!C153,Local!C151) -> 500 | C51: =IF(Local!D151=0,Local!D153,Local!D151) -> 500 | D51: =IF(Local!E151=0,Local!E153,Local!E151) -> 500 | E51: =IF(Local!F151=0,Local!F153,Local!F151) -> 500 | F51: =IF(Local!G151=0,Local!G153,Local!G151) -> 500 | G51: =IF(Local!H151=0,Local!H153,Local!H151) -> 500 | H51: =IF(Local!I151=0,Local!I153,Local!I151) -> 500 | I51: =IF(Local!J151=0,Local!J153,Local!J151) -> 500 | ... M51: =IF(Local!N151=0,Local!N153,Local!N151) -> 500 | N51: =SUM(B51:M51) -> 6000
A52: BetMissouri | B52: =IF(Local!C158=0,Local!C160,Local!C158) -> 75517.58 | C52: =IF(Local!D158=0,Local!D160,Local!D158) -> 62921.899 | D52: =IF(Local!E158=0,Local!E160,Local!E158) -> 3415.6737 | E52: =IF(Local!F158=0,Local!F160,Local!F158) -> 10000 | F52: =IF(Local!G158=0,Local!G160,Local!G158) -> 5000 | G52: =IF(Local!H158=0,Local!H160,Local!H158) -> 5000 | H52: =IF(Local!I158=0,Local!I160,Local!I158) -> 5000 | I52: =IF(Local!J158=0,Local!J160,Local!J158) -> 10000 | ... M52: =IF(Local!N158=0,Local!N160,Local!N158) -> 25000 | N52: =SUM(B52:M52) -> 266855.15
A53: OntarioBets | B53: =IF(Local!C165=0,Local!C167,Local!C165) -> 10202.617 | C53: =IF(Local!D165=0,Local!D167,Local!D165) -> 11728.955 | D53: =IF(Local!E165=0,Local!E167,Local!E165) -> 13670.577 | E53: =IF(Local!F165=0,Local!F167,Local!F165) -> 15000 | F53: =IF(Local!G165=0,Local!G167,Local!G165) -> 15000 | G53: =IF(Local!H165=0,Local!H167,Local!H165) -> 15000 | H53: =IF(Local!I165=0,Local!I167,Local!I165) -> 20000 | I53: =IF(Local!J165=0,Local!J167,Local!J165) -> 20000 | ... M53: =IF(Local!N165=0,Local!N167,Local!N165) -> 30000 | N53: =SUM(B53:M53) -> 230602.15
A54: BetCanada | B54: =IF(Local!C172=0,Local!C174,Local!C172) -> 564.956 | C54: =IF(Local!D172=0,Local!D174,Local!D172) -> 935.49918 | D54: =IF(Local!E172=0,Local!E174,Local!E172) -> 209.72987 | E54: =IF(Local!F172=0,Local!F174,Local!F172) -> 500 | F54: =IF(Local!G172=0,Local!G174,Local!G172) -> 500 | G54: =IF(Local!H172=0,Local!H174,Local!H172) -> 500 | H54: =IF(Local!I172=0,Local!I174,Local!I172) -> 500 | I54: =IF(Local!J172=0,Local!J174,Local!J172) -> 500 | ... M54: =IF(Local!N172=0,Local!N174,Local!N172) -> 500 | N54: =SUM(B54:M54) -> 6210.1851
A55: ApuestaMexico | B55: =IF(Local!C179=0,Local!C181,Local!C179) -> 251.0037 | C55: =IF(Local!D179=0,Local!D181,Local!D179) -> -133.23708 | D55: =IF(Local!E179=0,Local!E181,Local!E179) -> 516.74519 | E55: =IF(Local!F179=0,Local!F181,Local!F179) -> 0 | F55: =IF(Local!G179=0,Local!G181,Local!G179) -> 0 | G55: =IF(Local!H179=0,Local!H181,Local!H179) -> 0 | H55: =IF(Local!I179=0,Local!I181,Local!I179) -> 0 | I55: =IF(Local!J179=0,Local!J181,Local!J179) -> 0 | ... M55: =IF(Local!N179=0,Local!N181,Local!N179) -> 0 | N55: =SUM(B55:M55) -> 634.51181
A56: Brasilpostas | B56: =IF(Local!C186=0,Local!C188,Local!C186) -> 202.81864 | C56: =IF(Local!D186=0,Local!D188,Local!D186) -> 86.489927 | D56: =IF(Local!E186=0,Local!E188,Local!E186) -> 106.29764 | E56: =IF(Local!F186=0,Local!F188,Local!F186) -> 0 | F56: =IF(Local!G186=0,Local!G188,Local!G186) -> 0 | G56: =IF(Local!H186=0,Local!H188,Local!H186) -> 0 | H56: =IF(Local!I186=0,Local!I188,Local!I186) -> 0 | I56: =IF(Local!J186=0,Local!J188,Local!J186) -> 0 | ... M56: =IF(Local!N186=0,Local!N188,Local!N186) -> 0 | N56: =SUM(B56:M56) -> 395.60621
A57: SUBTOTAL — Local | B57: =SUM(B30:B56) -> 142021.11 | C57: =SUM(C30:C56) -> 142913.84 | D57: =SUM(D30:D56) -> 80227.899 | E57: =SUM(E30:E56) -> 75600 | F57: =SUM(F30:F56) -> 47600 | G57: =SUM(G30:G56) -> 47600 | H57: =SUM(H30:H56) -> 52600 | I57: =SUM(I30:I56) -> 78600 | ... M57: =SUM(M30:M56) -> 152600 | N57: =SUM(B57:M57) -> 1233562.8
A58: ODDS / OPTICODDS | B58: =IF('OJ+OO'!C4=0,"FORECAST","ACTUAL") -> ACTUAL | C58: =IF('OJ+OO'!D4=0,"FORECAST","ACTUAL") -> ACTUAL | D58: =IF('OJ+OO'!E4=0,"FORECAST","ACTUAL") -> ACTUAL | E58: =IF('OJ+OO'!F4=0,"FORECAST","ACTUAL") -> FORECAST | F58: =IF('OJ+OO'!G4=0,"FORECAST","ACTUAL") -> FORECAST | G58: =IF('OJ+OO'!H4=0,"FORECAST","ACTUAL") -> FORECAST | H58: =IF('OJ+OO'!I4=0,"FORECAST","ACTUAL") -> FORECAST | I58: =IF('OJ+OO'!J4=0,"FORECAST","ACTUAL") -> FORECAST | ... M58: =IF('OJ+OO'!N4=0,"FORECAST","ACTUAL") -> FORECAST
A59: Subscriptions (OJ + DGF) | B59: =IF('OJ+OO'!C4=0,'OJ+OO'!C6,'OJ+OO'!C4) -> 1498880 | C59: =IF('OJ+OO'!D4=0,'OJ+OO'!D6,'OJ+OO'!D4) -> 1372295 | D59: =IF('OJ+OO'!E4=0,'OJ+OO'!E6,'OJ+OO'!E4) -> 1352236.2 | E59: =IF('OJ+OO'!F4=0,'OJ+OO'!F6,'OJ+OO'!F4) -> 1288619 | F59: =IF('OJ+OO'!G4=0,'OJ+OO'!G6,'OJ+OO'!G4) -> 1239950 | G59: =IF('OJ+OO'!H4=0,'OJ+OO'!H6,'OJ+OO'!H4) -> 1146396 | H59: =IF('OJ+OO'!I4=0,'OJ+OO'!I6,'OJ+OO'!I4) -> 1072744 | I59: =IF('OJ+OO'!J4=0,'OJ+OO'!J6,'OJ+OO'!J4) -> 1050237 | ... M59: =IF('OJ+OO'!N4=0,'OJ+OO'!N6,'OJ+OO'!N4) -> 1612359 | N59: =SUM(B59:M59) -> 16037290
A60: DGF Affiliate | B60: =IF('OJ+OO'!C11=0,'OJ+OO'!C13,'OJ+OO'!C11) -> 0 | C60: =IF('OJ+OO'!D11=0,'OJ+OO'!D13,'OJ+OO'!D11) -> 0 | D60: =IF('OJ+OO'!E11=0,'OJ+OO'!E13,'OJ+OO'!E11) -> 0 | E60: =IF('OJ+OO'!F11=0,'OJ+OO'!F13,'OJ+OO'!F11) -> 0 | F60: =IF('OJ+OO'!G11=0,'OJ+OO'!G13,'OJ+OO'!G11) -> 0 | G60: =IF('OJ+OO'!H11=0,'OJ+OO'!H13,'OJ+OO'!H11) -> 0 | H60: =IF('OJ+OO'!I11=0,'OJ+OO'!I13,'OJ+OO'!I11) -> 0 | I60: =IF('OJ+OO'!J11=0,'OJ+OO'!J13,'OJ+OO'!J11) -> 0 | ... M60: =IF('OJ+OO'!N11=0,'OJ+OO'!N13,'OJ+OO'!N11) -> 0 | N60: =SUM(B60:M60) -> 0
A61: OJ Affiliate | B61: =IF('OJ+OO'!C18=0,'OJ+OO'!C20,'OJ+OO'!C18) -> 92646.238 | C61: =IF('OJ+OO'!D18=0,'OJ+OO'!D20,'OJ+OO'!D18) -> 62782.833 | D61: =IF('OJ+OO'!E18=0,'OJ+OO'!E20,'OJ+OO'!E18) -> 92995.439 | E61: =IF('OJ+OO'!F18=0,'OJ+OO'!F20,'OJ+OO'!F18) -> 70000 | F61: =IF('OJ+OO'!G18=0,'OJ+OO'!G20,'OJ+OO'!G18) -> 70000 | G61: =IF('OJ+OO'!H18=0,'OJ+OO'!H20,'OJ+OO'!H18) -> 70000 | H61: =IF('OJ+OO'!I18=0,'OJ+OO'!I20,'OJ+OO'!I18) -> 70000 | I61: =IF('OJ+OO'!J18=0,'OJ+OO'!J20,'OJ+OO'!J18) -> 70000 | ... M61: =IF('OJ+OO'!N18=0,'OJ+OO'!N20,'OJ+OO'!N18) -> 70000 | N61: =SUM(B61:M61) -> 878424.51
A62: Optic Rev Share | B62: =IF('OJ+OO'!C25=0,'OJ+OO'!C27,'OJ+OO'!C25) -> 236708.1 | C62: =IF('OJ+OO'!D25=0,'OJ+OO'!D27,'OJ+OO'!D25) -> 175526.1 | D62: =IF('OJ+OO'!E25=0,'OJ+OO'!E27,'OJ+OO'!E25) -> 249908.77 | E62: =IF('OJ+OO'!F25=0,'OJ+OO'!F27,'OJ+OO'!F25) -> 202500 | F62: =IF('OJ+OO'!G25=0,'OJ+OO'!G27,'OJ+OO'!G25) -> 202500 | G62: =IF('OJ+OO'!H25=0,'OJ+OO'!H27,'OJ+OO'!H25) -> 202500 | H62: =IF('OJ+OO'!I25=0,'OJ+OO'!I27,'OJ+OO'!I25) -> 202500 | I62: =IF('OJ+OO'!J25=0,'OJ+OO'!J27,'OJ+OO'!J25) -> 202500 | ... M62: =IF('OJ+OO'!N25=0,'OJ+OO'!N27,'OJ+OO'!N25) -> 562500 | N62: =SUM(B62:M62) -> 3764643
A63: OpticOdds | B63: =IF('OJ+OO'!C32=0,'OJ+OO'!C34,'OJ+OO'!C32) -> 1395039.8 | C63: =IF('OJ+OO'!D32=0,'OJ+OO'!D34,'OJ+OO'!D32) -> 1172189.1 | D63: =IF('OJ+OO'!E32=0,'OJ+OO'!E34,'OJ+OO'!E32) -> 1502403.7 | E63: =IF('OJ+OO'!F32=0,'OJ+OO'!F34,'OJ+OO'!F32) -> 1555531 | F63: =IF('OJ+OO'!G32=0,'OJ+OO'!G34,'OJ+OO'!G32) -> 1588108 | G63: =IF('OJ+OO'!H32=0,'OJ+OO'!H34,'OJ+OO'!H32) -> 1588108 | H63: =IF('OJ+OO'!I32=0,'OJ+OO'!I34,'OJ+OO'!I32) -> 1591365 | I63: =IF('OJ+OO'!J32=0,'OJ+OO'!J34,'OJ+OO'!J32) -> 1591365 | ... M63: =IF('OJ+OO'!N32=0,'OJ+OO'!N34,'OJ+OO'!N32) -> 1734779 | N63: =SUM(B63:M63) -> 18512632
A64: SUBTOTAL — Odds / OpticOdds | B64: =SUM(B59:B63) -> 3223274.1 | C64: =SUM(C59:C63) -> 2782793 | D64: =SUM(D59:D63) -> 3197544.1 | E64: =SUM(E59:E63) -> 3116650 | F64: =SUM(F59:F63) -> 3100558 | G64: =SUM(G59:G63) -> 3007004 | H64: =SUM(H59:H63) -> 2936609 | I64: =SUM(I59:I63) -> 2914102 | ... M64: =SUM(M59:M63) -> 3979638 | N64: =SUM(B64:M64) -> 39192989
A65: TOTAL SDS | B65: =B8+B25+B28+B57+B64 -> 5414968.8 | C65: =C8+C25+C28+C57+C64 -> 5197586.8 | D65: =D8+D25+D28+D57+D64 -> 5344211.3 | E65: =E8+E25+E28+E57+E64 -> 5146905 | F65: =F8+F25+F28+F57+F64 -> 4871771 | G65: =G8+G25+G28+G57+G64 -> 4812873 | H65: =H8+H25+H28+H57+H64 -> 4847604 | I65: =I8+I25+I28+I57+I64 -> 5492554 | ... M65: =M8+M25+M28+M57+M64 -> 6675311 | N65: =SUM(B65:M65) -> 67162174

Sheet Rotowire
A1: Rotowire — 2026 Revenue Detail
A2: Read-only · All data flows from Forecast Input tab · Do not type here
A3: SUB-LINE | B3: METRIC | C3: Jan | D3: Feb | E3: Mar | F3: Apr | G3: May | H3: Jun | I3: Jul | J3: Aug | K3: Sep | L3: Oct | M3: Nov | N3: Dec | O3: FULL YEAR
A4: B2C Subs | B4: Actual 26' | C4: ='Forecast Input'!D5 -> 474038.26 | D4: ='Forecast Input'!E5 -> 459134.72 | E4: ='Forecast Input'!F5 -> 552360.2 | F4: ='Forecast Input'!G5 -> 0 | G4: ='Forecast Input'!H5 -> 0 | H4: ='Forecast Input'!I5 -> 0 | I4: ='Forecast Input'!J5 -> 0 | J4: ='Forecast Input'!K5 -> 0 | ... N4: ='Forecast Input'!O5 -> 0 | O4: =SUM(C4:N4) -> 1485533.2
B5: Actual 25' | C5: 475949 | D5: 440366 | E5: 525216 | F5: 453059 | G5: 413871 | H5: 403322 | I5: 413273 | J5: 487182 | K5: 584970 | L5: 525388 | M5: 499582 | N5: 576723 | O5: =SUM(C5:N5) -> 5798901
B6: Forecast | C6: ='Forecast Input'!D6 -> 484326 | D6: ='Forecast Input'!E6 -> 443408 | E6: ='Forecast Input'!F6 -> 531544 | F6: ='Forecast Input'!G6 -> 459073 | G6: ='Forecast Input'!H6 -> 452554 | H6: ='Forecast Input'!I6 -> 478438 | I6: ='Forecast Input'!J6 -> 491501 | J6: ='Forecast Input'!K6 -> 751620 | ... N6: ='Forecast Input'!O6 -> 681276 | O6: =SUM(C6:N6) -> 7004618 | P6: NOTES PLACED IN NEXT TAB
B7: Actual vs Forecast $ | C7: =IF(C4=0,"-",C4-C6) -> -10287.736 | D7: =IF(D4=0,"-",D4-D6) -> 15726.718 | E7: =IF(E4=0,"-",E4-E6) -> 20816.196 | F7: =IF(F4=0,"-",F4-F6) -> - | G7: =IF(G4=0,"-",G4-G6) -> - | H7: =IF(H4=0,"-",H4-H6) -> - | I7: =IF(I4=0,"-",I4-I6) -> - | J7: =IF(J4=0,"-",J4-J6) -> - | ... N7: =IF(N4=0,"-",N4-N6) -> -
B8: Actual vs Forecast % | C8: =IFERROR(C7/C4,"-") -> -0.021702332 | D8: =IFERROR(D7/D4,"-") -> 0.034252948 | E8: =IFERROR(E7/E4,"-") -> 0.037685909 | F8: =IFERROR(F7/F4,"-") -> - | G8: =IFERROR(G7/G4,"-") -> - | H8: =IFERROR(H7/H4,"-") -> - | I8: =IFERROR(I7/I4,"-") -> - | J8: =IFERROR(J7/J4,"-") -> - | ... N8: =IFERROR(N7/N4,"-") -> -
B9: Forecast vs PY $ | C9: =IFERROR(C6-C5,"-") -> 8377 | D9: =IFERROR(D6-D5,"-") -> 3042 | E9: =IFERROR(E6-E5,"-") -> 6328 | F9: =IFERROR(F6-F5,"-") -> 6014 | G9: =IFERROR(G6-G5,"-") -> 38683 | H9: =IFERROR(H6-H5,"-") -> 75116 | I9: =IFERROR(I6-I5,"-") -> 78228 | J9: =IFERROR(J6-J5,"-") -> 264438 | ... N9: =IFERROR(N6-N5,"-") -> 104553
B10: Forecast vs PY % | C10: =IFERROR(C9/C5,"-") -> 0.017600625 | D10: =IFERROR(D9/D5,"-") -> 0.0069078903 | E10: =IFERROR(E9/E5,"-") -> 0.012048376 | F10: =IFERROR(F9/F5,"-") -> 0.013274209 | G10: =IFERROR(G9/G5,"-") -> 0.093466322 | H10: =IFERROR(H9/H5,"-") -> 0.18624325 | I10: =IFERROR(I9/I5,"-") -> 0.18928892 | J10: =IFERROR(J9/J5,"-") -> 0.54279099 | ... N10: =IFERROR(N9/N5,"-") -> 0.18128807
A11: Advertising | B11: Actual 26' | C11: ='Forecast Input'!D7 -> 111988.73 | D11: ='Forecast Input'!E7 -> 103856.8 | E11: ='Forecast Input'!F7 -> 134400.81 | F11: ='Forecast Input'!G7 -> 0 | G11: ='Forecast Input'!H7 -> 0 | H11: ='Forecast Input'!I7 -> 0 | I11: ='Forecast Input'!J7 -> 0 | J11: ='Forecast Input'!K7 -> 0 | ... N11: ='Forecast Input'!O7 -> 0 | O11: =SUM(C11:N11) -> 350246.34
B12: Actual 25' | C12: 59518 | D12: 59327 | E12: 106033 | F12: 131901 | G12: 65346 | H12: 90721 | I12: 112099 | J12: 111648 | K12: 100884 | L12: 121514 | M12: 180968 | N12: 122875 | O12: =SUM(C12:N12) -> 1262834
B13: Forecast | C13: ='Forecast Input'!D8 -> 73000 | D13: ='Forecast Input'!E8 -> 79000 | E13: ='Forecast Input'!F8 -> 115000 | F13: ='Forecast Input'!G8 -> 114000 | G13: ='Forecast Input'!H8 -> 79000 | H13: ='Forecast Input'!I8 -> 74000 | I13: ='Forecast Input'!J8 -> 82000 | J13: ='Forecast Input'!K8 -> 124000 | ... N13: ='Forecast Input'!O8 -> 124000 | O13: =SUM(C13:N13) -> 1219000
B14: Actual vs Forecast $ | C14: =IF(C11=0,"-",C11-C13) -> 38988.725 | D14: =IF(D11=0,"-",D11-D13) -> 24856.796 | E14: =IF(E11=0,"-",E11-E13) -> 19400.815 | F14: =IF(F11=0,"-",F11-F13) -> - | G14: =IF(G11=0,"-",G11-G13) -> - | H14: =IF(H11=0,"-",H11-H13) -> - | I14: =IF(I11=0,"-",I11-I13) -> - | J14: =IF(J11=0,"-",J11-J13) -> - | ... N14: =IF(N11=0,"-",N11-N13) -> -
B15: Actual vs Forecast % | C15: =IFERROR(C14/C11,"-") -> 0.34814866 | D15: =IFERROR(D14/D11,"-") -> 0.23933721 | E15: =IFERROR(E14/E11,"-") -> 0.14435042 | F15: =IFERROR(F14/F11,"-") -> - | G15: =IFERROR(G14/G11,"-") -> - | H15: =IFERROR(H14/H11,"-") -> - | I15: =IFERROR(I14/I11,"-") -> - | J15: =IFERROR(J14/J11,"-") -> - | ... N15: =IFERROR(N14/N11,"-") -> -
B16: Forecast vs PY $ | C16: =IFERROR(C13-C12,"-") -> 13482 | D16: =IFERROR(D13-D12,"-") -> 19673 | E16: =IFERROR(E13-E12,"-") -> 8967 | F16: =IFERROR(F13-F12,"-") -> -17901 | G16: =IFERROR(G13-G12,"-") -> 13654 | H16: =IFERROR(H13-H12,"-") -> -16721 | I16: =IFERROR(I13-I12,"-") -> -30099 | J16: =IFERROR(J13-J12,"-") -> 12352 | ... N16: =IFERROR(N13-N12,"-") -> 1125
B17: Forecast vs PY % | C17: =IFERROR(C16/C12,"-") -> 0.22651971 | D17: =IFERROR(D16/D12,"-") -> 0.33160281 | E17: =IFERROR(E16/E12,"-") -> 0.084568012 | F17: =IFERROR(F16/F12,"-") -> -0.13571542 | G17: =IFERROR(G16/G12,"-") -> 0.20894929 | H17: =IFERROR(H16/H12,"-") -> -0.18431234 | I17: =IFERROR(I16/I12,"-") -> -0.26850373 | J17: =IFERROR(J16/J12,"-") -> 0.11063342 | ... N17: =IFERROR(N16/N12,"-") -> 0.009155646
A18: B2B Content | B18: Actual 26' | C18: ='Forecast Input'!D9 -> 243987.32 | D18: ='Forecast Input'!E9 -> 236446.5 | E18: ='Forecast Input'!F9 -> 248430.63 | F18: ='Forecast Input'!G9 -> 0 | G18: ='Forecast Input'!H9 -> 0 | H18: ='Forecast Input'!I9 -> 0 | I18: ='Forecast Input'!J9 -> 0 | J18: ='Forecast Input'!K9 -> 0 | ... N18: ='Forecast Input'!O9 -> 0 | O18: =SUM(C18:N18) -> 728864.45
B19: Actual 25' | C19: 281596 | D19: 256251 | E19: 254563 | F19: 288186 | G19: 266344 | H19: 268658 | I19: 257179 | J19: 258775 | K19: 270002 | L19: 258897 | M19: 264648 | N19: 264986 | O19: =SUM(C19:N19) -> 3190085
B20: Forecast | C20: ='Forecast Input'!D10 -> 273000 | D20: ='Forecast Input'!E10 -> 259000 | E20: ='Forecast Input'!F10 -> 248000 | F20: ='Forecast Input'!G10 -> 254000 | G20: ='Forecast Input'!H10 -> 264000 | H20: ='Forecast Input'!I10 -> 274000 | I20: ='Forecast Input'!J10 -> 311000 | J20: ='Forecast Input'!K10 -> 321000 | ... N20: ='Forecast Input'!O10 -> 337000 | O20: =SUM(C20:N20) -> 3528000
B21: Actual vs Forecast $ | C21: =IF(C18=0,"-",C18-C20) -> -29012.682 | D21: =IF(D18=0,"-",D18-D20) -> -22553.5 | E21: =IF(E18=0,"-",E18-E20) -> 430.63376 | F21: =IF(F18=0,"-",F18-F20) -> - | G21: =IF(G18=0,"-",G18-G20) -> - | H21: =IF(H18=0,"-",H18-H20) -> - | I21: =IF(I18=0,"-",I18-I20) -> - | J21: =IF(J18=0,"-",J18-J20) -> - | ... N21: =IF(N18=0,"-",N18-N20) -> -
B22: Actual vs Forecast % | C22: =IFERROR(C21/C18,"-") -> -0.11891062 | D22: =IFERROR(D21/D18,"-") -> -0.095385213 | E22: =IFERROR(E21/E18,"-") -> 0.0017334165 | F22: =IFERROR(F21/F18,"-") -> - | G22: =IFERROR(G21/G18,"-") -> - | H22: =IFERROR(H21/H18,"-") -> - | I22: =IFERROR(I21/I18,"-") -> - | J22: =IFERROR(J21/J18,"-") -> - | ... N22: =IFERROR(N21/N18,"-") -> -
B23: Forecast vs PY $ | C23: =IFERROR(C20-C19,"-") -> -8596 | D23: =IFERROR(D20-D19,"-") -> 2749 | E23: =IFERROR(E20-E19,"-") -> -6563 | F23: =IFERROR(F20-F19,"-") -> -34186 | G23: =IFERROR(G20-G19,"-") -> -2344 | H23: =IFERROR(H20-H19,"-") -> 5342 | I23: =IFERROR(I20-I19,"-") -> 53821 | J23: =IFERROR(J20-J19,"-") -> 62225 | ... N23: =IFERROR(N20-N19,"-") -> 72014
B24: Forecast vs PY % | C24: =IFERROR(C23/C19,"-") -> -0.030526002 | D24: =IFERROR(D23/D19,"-") -> 0.010727763 | E24: =IFERROR(E23/E19,"-") -> -0.025781437 | F24: =IFERROR(F23/F19,"-") -> -0.11862478 | G24: =IFERROR(G23/G19,"-") -> -0.0088006488 | H24: =IFERROR(H23/H19,"-") -> 0.019884016 | I24: =IFERROR(I23/I19,"-") -> 0.20927447 | J24: =IFERROR(J23/J19,"-") -> 0.24045986 | ... N24: =IFERROR(N23/N19,"-") -> 0.2717653
A26: TOTAL ROTOWIRE | C26: =IFERROR(IF(C4+C11+C18>0,C4+C11+C18,C6+C13+C20),C6+C13+C20) -> 830014.31 | D26: =IFERROR(IF(D4+D11+D18>0,D4+D11+D18,D6+D13+D20),D6+D13+D20) -> 799438.01 | E26: =IFERROR(IF(E4+E11+E18>0,E4+E11+E18,E6+E13+E20),E6+E13+E20) -> 935191.64 | F26: =IFERROR(IF(F4+F11+F18>0,F4+F11+F18,F6+F13+F20),F6+F13+F20) -> 827073 | G26: =IFERROR(IF(G4+G11+G18>0,G4+G11+G18,G6+G13+G20),G6+G13+G20) -> 795554 | H26: =IFERROR(IF(H4+H11+H18>0,H4+H11+H18,H6+H13+H20),H6+H13+H20) -> 826438 | I26: =IFERROR(IF(I4+I11+I18>0,I4+I11+I18,I6+I13+I20),I6+I13+I20) -> 884501 | J26: =IFERROR(IF(J4+J11+J18>0,J4+J11+J18,J6+J13+J20),J6+J13+J20) -> 1196620 | ... N26: =IFERROR(IF(N4+N11+N18>0,N4+N11+N18,N6+N13+N20),N6+N13+N20) -> 1142276 | O26: =SUM(C26:N26) -> 11809984

Sheet RotoWire Notes
A1: 46134 | B1: B2C Subs | C1: Jul26 | D1: Raising slightly under the assumption that all the things we're working on right now will start to click in. July
A2: 46134 | B2: B2C Subs | C2: May26-Jun26 | D2: Lowering slightly just to match ho-hum April, things won't pick up until peak NFL sign-up season'
A3: 46134 | B3: B2B Content | C3: Apr26-Dec26 | D3: Lowering B2B across the board. Simply not picking up as much new business as expected and lost a few key clients. Shannon has a plan to re-double efforts on pro teams
A4: 46127 | B4: B2C Subs | C4: Apr26 | D4: Drop 14K n renewal revenue vs. previous months is slightly worrying
A5: 46127 | B5: B2B Content | C5: Jun26 | D5: Down 8K ... just a slow market right now for new B2B content deals
A6: 46127 | B6: B2B Content | C6: May26 | D6: Down 8K ... just a slow market right now for new B2B content deals
A7: 46127 | B7: B2B Content | C7: Apr26 | D7: Down 8K ... just a slow market right now for new B2B content deals
A8: 46120 | B8: B2C Subs | C8: Apr26 | D8: Down 5K because we made a big push to grab $$$ in the last week of March, so there's a trickle-down slightly adverse effect on NEW SUBS for early April
A9: 46120 | B9: B2B Content | C9: Jun26 | D9: Down 20K to account for slower-than-expected growth on new B2B API deals this year
A10: 46120 | B10: B2B Content | C10: May26 | D10: Down 10K to account for slower-than-expected growth on new B2B API deals this year
A11: 46112 | B11: B2B Content | C11: Mar26 | D11: Down 10K to account for some renewing contracts held up ... we will pick up this revenue in future months
A12: 46112 | B12: B2B Content | C12: May26 | D12: Dropped by 15K to meet realities of losing a few B2B partners and not a huge demand in the short term
... A36: 46037 | B36: B2B Content | C36: Jan26 | D36: Down $281,000 to $273,000
A39: 2025 data
H40: Q1 | T40: Q1 Total | X40: Q2 | AJ40: Q2 Total | AN40: Q3 | BD40: Q3 Total | BH40: Q4 | BT40: Q4 Total
D41: YTD | H41: Jan | L41: Feb | P41: Mar | T41: Q1 | X41: Apr | AB41: May | AF41: Jun | AJ41: Q2 | AN41: Jul | AR41: Aug | AX41: Sep | BD41: Q3 | BH41: Oct | BL41: Nov | BP41: Dec | BT41: Q4
D42: Actual | E42: Acutal 24' | F42: Target | G42: Forecast | H42: Actual | I42: Acutal 24' | J42: Target | K42: Forecast | L42: Actual | M42: Acutal 24' | N42: Target | O42: Forecast | P42: Actual | Q42: Acutal 24' | R42: Target | S42: Forecast | T42: Actual | U42: Acutal 24' | V42: Target | W42: Forecast | X42: Actual | Y42: Acutal 24' | Z42: Target | AA42: Forecast | AB42: Actual | AC42: Acutal 24' | AD42: Target | AE42: Forecast | AF42: Actual | AG42: Acutal 24' | AH42: Target | AI42: Forecast | AJ42: Actual | AK42: Acutal 24' | AL42: Target | AM42: Forecast | AN42: Actual | AO42: Acutal 24' | AP42: Target | AQ42: Forecast | AR42: Actual | AS42: Acutal 24' | AT42: Actual | AU42: Acutal 24' | AV42: Target | AW42: Forecast | AX42: Actual | AY42: Acutal 24' | AZ42: Actual | BA42: Acutal 24' | BB42: Target | BC42: Forecast | BD42: Actual | BE42: Acutal 24' | BF42: Target | BG42: Forecast | BH42: Actual | BI42: Acutal 24' | BJ42: Target | BK42: Forecast | BL42: Actual | BM42: Acutal 24' | BN42: Target | BO42: Forecast | BP42: Actual | BQ42: Acutal 24' | BR42: Target | BS42: Forecast | BT42: Actual | BU42: Acutal 24' | BV42: Target | BW42: Forecast
B43: TOTAL | C43: Rotowire | D43: =D44+D47+D48 -> 4823881 | F43: =SUM(F44:F48) -> #VALUE! | G43: =G44+G47+G48 -> 10213856 | H43: =H44+H47+H48 -> 791440 | I43: =I44+I47+I48 -> 709020 | J43: =SUM(J44:J48) -> 0 | K43: =K44+K47+K48 -> 835500 | L43: =L44+L47+L48 -> 756347 | N43: =SUM(N44:N48) -> 0 | O43: =O44+O47+O48 -> 796000 | P43: =P44+P47+P48 -> 883938 | R43: =SUM(R44:R48) -> 0 | S43: =S44+S47+S48 -> 938000 | T43: =T44+T47+T48 -> 2431725 | V43: =SUM(V44:V48) -> 0 | W43: =W44+W47+W48 -> 2569500 | X43: =X44+X47+X48 -> 879601 | Z43: =SUM(Z44:Z48) -> 0 | AA43: =AA44+AA47+AA48 -> 803500 | AB43: =AB44+AB47+AB48 -> 745569 | AD43: =AD44+AD47+AD48 -> #VALUE! | AE43: =AE44+AE47+AE48 -> 745000 | AF43: =AF44+AF47+AF48 -> 766986 | AG43: =AG44+AG47+AG48 -> 727136 | AH43: =SUM(AH44:AH48) -> 0 | AI43: =AI44+AI47+AI48 -> 743500 | AJ43: =AJ44+AJ47+AJ48 -> 2392156 | AL43: =SUM(AL44:AL48) -> 0 | AM43: =AM44+AM47+AM48 -> 2292000 | AN43: =AN44+AN47+AN48 -> 782551 | AO43: =AO44+AO47+AO48 -> 714061 | AP43: =SUM(AP44:AP48) -> 0 | AQ43: =AQ44+AQ47+AQ48 -> 759000 | AU43: =AU44+AU47+AU48 -> 1035795 | AV43: =SUM(AV44:AV48) -> 0 | AW43: =AW44+AW47+AW48 -> 969651 | BB43: =SUM(BB44:BB48) -> 0 | BC43: =BC44+BC47+BC48 -> 944296 | BF43: =SUM(BF44:BF48) -> 0 | BG43: =BG44+BG47+BG48 -> 2672947 | BH43: =BH44+BH47+BH48 -> 906023.02 | BJ43: =SUM(BJ44:BJ48) -> 0 | BK43: =BK44+BK47+BK48 -> 878346 | BL43: =BL44+BL47+BL48 -> 945198.27 | BM43: =BM44+BM47+BM48 -> 862631 | BN43: =SUM(BN44:BN48) -> 0 | BO43: =BO44+BO47+BO48 -> 914692 | BP43: =BP44+BP47+BP48 -> 964747 | BR43: =SUM(BR44:BR48) -> 0 | BS43: =BS44+BS47+BS48 -> 886371 | BV43: =SUM(BV44:BV48) -> 0 | BW43: =BW44+BW47+BW48 -> 2679409
B44: Rotowire | C44: Rotowire - B2C Subs | D44: =SUM(T44+AJ44+BD44+BT44) -> 2716044 | F44: =SUM(V44+AL44+BF44+BV44) -> #VALUE! | G44: =SUM(W44+AM44+BG44+BW44) -> 5876971 | H44: 475862 | I44: 402792 | J44: =IFERROR(VLOOKUP($C44,[1]vlookup!$B:$N,2,FALSE),"") | K44: =SUM(K45:K46) -> 508000 | L44: 440769 | N44: =IFERROR(VLOOKUP($C44,[1]vlookup!$B:$N,3,FALSE),"") | O44: =SUM(O45:O46) -> 462000 | P44: 523542 | R44: =IFERROR(VLOOKUP($C44,[1]vlookup!$B:$N,4,FALSE),"") | S44: =SUM(S45:S46) -> 563000 | T44: =IFERROR(SUM(H44+L44+P44),"") -> 1440173 | V44: =IFERROR(SUM(J44+N44+R44),"") | W44: =IFERROR(SUM(K44+O44+S44),"") -> 1533000 | X44: 456408 | Z44: =IFERROR(VLOOKUP($C44,[1]vlookup!$B:$N,5,FALSE),"") | AA44: =SUM(AA45:AA46) -> 442500 | AB44: 413875 | AD44: =IFERROR(VLOOKUP($C44,[1]vlookup!$B:$N,6,FALSE),"") | AE44: =AE45+AE46 -> 416000 | AF44: =SUM(AF45:AF46) -> 405588 | AG44: =SUM(AG45:AG46) -> 393059 | AH44: =IFERROR(VLOOKUP($C44,[1]vlookup!$B:$N,7,FALSE),"") | AI44: =AI45+AI46 -> 404000 | AJ44: =IFERROR(SUM(X44+AB44+AF44),"") -> 1275871 | AL44: =IFERROR(SUM(Z44+AD44+AH44),"") | AM44: =IFERROR(SUM(AA44+AE44+AI44),"") -> 1262500 | AN44: 413273 | AO44: =SUM(AO45:AO46) -> 424318 | AP44: =IFERROR(VLOOKUP($C44,[1]vlookup!$B:$N,8,FALSE),"") | AQ44: =AQ45+AQ46 -> 409000 | AT44: =SUM(AT45:AT46) -> 487745 | AU44: =SUM(AU45:AU46) -> 675234 | AV44: =IFERROR(VLOOKUP($C44,[1]vlookup!$B:$N,9,FALSE),"") | AW44: =AW45+AW46 -> 582651 | AZ44: =SUM(AZ45:AZ46) -> 584456 | BA44: =SUM(BA45:BA46) -> 505913 | BB44: =IFERROR(VLOOKUP($C44,[1]vlookup!$B:$N,10,FALSE),"") | BC44: =BC45+BC46 -> 564296 | BF44: =IFERROR(SUM(AP44+AV44+BB44),"") | BG44: =IFERROR(SUM(AQ44+AW44+BC44),"") -> 1555947 | BH44: =SUM(BH45:BH46) -> 525518.02 | BJ44: =IFERROR(VLOOKUP($C44,[1]vlookup!$B:$N,11,FALSE),"") | BK44: =BK45+BK46 -> 513346 | BL44: =SUM(BL45:BL46) -> 499581.87 | BM44: =SUM(BM45:BM46) -> 460439 | BN44: =IFERROR(VLOOKUP($C44,[1]vlookup!$B:$N,12,FALSE),"") | BO44: =BO45+BO46 -> 522807 | BP44: 576820 | BR44: =IFERROR(VLOOKUP($C44,[1]vlookup!$B:$N,13,FALSE),"") | BS44: =BS45+BS46 -> 489371 | BV44: =IFERROR(SUM(BJ44+BN44+BR44),"") | BW44: =IFERROR(SUM(BK44+BO44+BS44),"") -> 1525524
C45: Web | F45: 0 | G45: 0 | J45: =IFERROR(VLOOKUP($C45,[1]vlookup!$B:$N,2,FALSE),"") | K45: 462000 | L45: =440769-52038 -> 388731 | N45: =IFERROR(VLOOKUP($C45,[1]vlookup!$B:$N,3,FALSE),"") | O45: 415000 | R45: =IFERROR(VLOOKUP($C45,[1]vlookup!$B:$N,4,FALSE),"") | S45: 490000 | T45: =IFERROR(SUM(H45+L45+P45),"") -> 388731 | V45: =IFERROR(SUM(J45+N45+R45),"") | W45: =IFERROR(SUM(K45+O45+S45),"") -> 1367000 | Z45: =IFERROR(VLOOKUP($C45,[1]vlookup!$B:$N,5,FALSE),"") | AA45: 412000 | AD45: =IFERROR(VLOOKUP($C45,[1]vlookup!$B:$N,6,FALSE),"") | AE45: 396000 | AF45: =405588-22526-4998 -> 378064 | AG45: =378768 -> 378768 | AI45: 391000 | AJ45: =IFERROR(SUM(X45+AB45+AF45),"") | AL45: =IFERROR(SUM(Z45+AD45+AH45),"") | AM45: =IFERROR(SUM(AA45+AE45+AI45),"") -> 1199000 | AN45: 389114.8 | AO45: 383630 | AQ45: 385000 | AT45: 410924 | AU45: =396717 -> 396717 | AV45: =IFERROR(VLOOKUP($C45,[1]vlookup!$B:$N,9,FALSE),"") | AW45: 472318 | AZ45: 450960 | BA45: 434683 | BB45: =IFERROR(VLOOKUP($C45,[1]vlookup!$B:$N,10,FALSE),"") | BC45: 441841 | BF45: =IFERROR(SUM(AQ45+AV45+BB45),"") | BG45: =IFERROR(SUM(#REF!+AW45+BC45),"") | BH45: 445178.6 | BJ45: =IFERROR(VLOOKUP($C45,[1]vlookup!$B:$N,11,FALSE),"") | BK45: =437635+10000 -> 447635 | BL45: 431804.26 | BM45: 420856 | BN45: =IFERROR(VLOOKUP($C45,[1]vlookup!$B:$N,12,FALSE),"") | BO45: =427047+20000+3000 -> 450047 | BR45: =IFERROR(VLOOKUP($C45,[1]vlookup!$B:$N,13,FALSE),"") | BS45: =417812+20000-10000-4000+4000 -> 427812 | BV45: =IFERROR(SUM(BJ45+BN45+BR45),"") | BW45: =IFERROR(SUM(BK45+BO45+BS45),"") -> 1325494
C46: App | F46: 0 | G46: 0 | J46: =IFERROR(VLOOKUP($C46,[1]vlookup!$B:$N,2,FALSE),"") | K46: 46000 | L46: 52038 | N46: =IFERROR(VLOOKUP($C46,[1]vlookup!$B:$N,3,FALSE),"") | O46: 47000 | R46: =IFERROR(VLOOKUP($C46,[1]vlookup!$B:$N,4,FALSE),"") | S46: 73000 | T46: =IFERROR(SUM(H46+L46+P46),"") -> 52038 | V46: =IFERROR(SUM(J46+N46+R46),"") | W46: =IFERROR(SUM(K46+O46+S46),"") -> 166000 | Z46: =IFERROR(VLOOKUP($C46,[1]vlookup!$B:$N,5,FALSE),"") | AA46: 30500 | AD46: =IFERROR(VLOOKUP($C46,[1]vlookup!$B:$N,6,FALSE),"") | AE46: 20000 | AF46: =22526+4998 -> 27524 | AG46: 14291 | AI46: 13000 | AJ46: =IFERROR(SUM(X46+AB46+AF46),"") -> 27524 | AL46: =IFERROR(SUM(Z46+AD46+AH46),"") | AM46: =IFERROR(SUM(AA46+AE46+AI46),"") -> 63500 | AN46: =24158.53 -> 24158.53 | AO46: 40688 | AQ46: 24000 | AT46: 76821 | AU46: 278517 | AV46: =IFERROR(VLOOKUP($C46,[1]vlookup!$B:$N,9,FALSE),"") | AW46: 110333 | AZ46: 133496 | BA46: 71230 | BB46: =IFERROR(VLOOKUP($C46,[1]vlookup!$B:$N,10,FALSE),"") | BC46: 122455 | BF46: =IFERROR(SUM(AQ46+AV46+BB46),"") | BG46: =IFERROR(SUM(#REF!+AW46+BC46),"") | BH46: 80339.42 | BJ46: =IFERROR(VLOOKUP($C46,[1]vlookup!$B:$N,11,FALSE),"") | BK46: =115711-30000-20000 -> 65711 | BL46: 67777.61 | BM46: 39583 | BN46: =IFERROR(VLOOKUP($C46,[1]vlookup!$B:$N,12,FALSE),"") | BO46: =135760-30000-30000-3000 -> 72760 | BR46: =IFERROR(VLOOKUP($C46,[1]vlookup!$B:$N,13,FALSE),"") | BS46: =96559-15000-10000-5000-5000 -> 61559 | BV46: =IFERROR(SUM(BJ46+BN46+BR46),"") | BW46: =IFERROR(SUM(BK46+BO46+BS46),"") -> 200030
C47: Rotowire - Advertising | D47: =SUM(T47+AJ47+BD47+BT47) -> 514141 | F47: =SUM(V47+AL47+BF47+BV47) -> #VALUE! | G47: =SUM(W47+AM47+BG47+BW47) -> 1148500 | H47: 59327 | I47: 38138 | J47: =IFERROR(VLOOKUP($C47,[1]vlookup!$B:$N,2,FALSE),"") | K47: 64500 | L47: 59327 | M47: 46880 | N47: =IFERROR(VLOOKUP($C47,[1]vlookup!$B:$N,3,FALSE),"") | O47: 71000 | P47: 106033 | Q47: 88989 | R47: =IFERROR(VLOOKUP($C47,[1]vlookup!$B:$N,4,FALSE),"") | S47: 105000 | T47: =IFERROR(SUM(H47+L47+P47),"") -> 224687 | V47: =IFERROR(SUM(J47+N47+R47),"") | W47: =IFERROR(SUM(K47+O47+S47),"") -> 240500 | X47: 132876 | Y47: 75527 | Z47: =IFERROR(VLOOKUP($C47,[1]vlookup!$B:$N,5,FALSE),"") | AA47: 110000 | AB47: 65347 | AD47: =IFERROR(VLOOKUP($C47,[1]vlookup!$B:$N,6,FALSE),"") | AE47: 68000 | AF47: 91231 | AG47: 63024 | AH47: =IFERROR(VLOOKUP($C47,[1]vlookup!$B:$N,7,FALSE),"") | AI47: 76000 | AJ47: =IFERROR(SUM(X47+AB47+AF47),"") -> 289454 | AL47: =IFERROR(SUM(Z47+AD47+AH47),"") | AM47: =IFERROR(SUM(AA47+AE47+AI47),"") -> 254000 | AN47: 112099 | AO47: 45098 | AP47: =IFERROR(VLOOKUP($C47,[1]vlookup!$B:$N,8,FALSE),"") | AQ47: 80000 | AT47: 111648 | AU47: 84374 | AV47: =IFERROR(VLOOKUP($C47,[1]vlookup!$B:$N,9,FALSE),"") | AW47: 107000 | AZ47: 100896 | BA47: 75583 | BB47: =IFERROR(VLOOKUP($C47,[1]vlookup!$B:$N,10,FALSE),"") | BC47: 110000 | BF47: =IFERROR(SUM(AP47+AV47+BB47),"") | BG47: =IFERROR(SUM(AQ47+AW47+BC47),"") -> 297000 | BH47: 121544 | BI47: 66566 | BJ47: =IFERROR(VLOOKUP($C47,[1]vlookup!$B:$N,11,FALSE),"") | BK47: 105000 | BL47: 180968.4 | BM47: 109778 | BN47: =IFERROR(VLOOKUP($C47,[1]vlookup!$B:$N,12,FALSE),"") | BO47: 125000 | BP47: 122897 | BR47: =IFERROR(VLOOKUP($C47,[1]vlookup!$B:$N,13,FALSE),"") | BS47: 127000 | BV47: =IFERROR(SUM(BJ47+BN47+BR47),"") | BW47: =IFERROR(SUM(BK47+BO47+BS47),"") -> 357000
C48: Rotowire - B2B Content | D48: =SUM(T48+AJ48+BD48+BT48) -> 1593696 | F48: =SUM(V48+AL48+BF48+BV48) -> #VALUE! | G48: =SUM(W48+AM48+BG48+BW48) -> 3188385 | H48: 256251 | I48: 268090 | J48: =IFERROR(VLOOKUP($C48,[1]vlookup!$B:$N,2,FALSE),"") | K48: 263000 | L48: 256251 | N48: =IFERROR(VLOOKUP($C48,[1]vlookup!$B:$N,3,FALSE),"") | O48: 263000 | P48: 254363 | R48: =IFERROR(VLOOKUP($C48,[1]vlookup!$B:$N,4,FALSE),"") | S48: 270000 | T48: =IFERROR(SUM(H48+L48+P48),"") -> 766865 | V48: =IFERROR(SUM(J48+N48+R48),"") | W48: =IFERROR(SUM(K48+O48+S48),"") -> 796000 | X48: 290317 | Z48: =IFERROR(VLOOKUP($C48,[1]vlookup!$B:$N,5,FALSE),"") | AA48: 251000 | AB48: 266347 | AD48: =IFERROR(VLOOKUP($C48,[1]vlookup!$B:$N,6,FALSE),"") | AE48: 261000 | AF48: 270167 | AG48: 271053 | AH48: =IFERROR(VLOOKUP($C48,[1]vlookup!$B:$N,7,FALSE),"") | AI48: 263500 | AJ48: =IFERROR(SUM(X48+AB48+AF48),"") -> 826831 | AL48: =IFERROR(SUM(Z48+AD48+AH48),"") | AM48: =IFERROR(SUM(AA48+AE48+AI48),"") -> 775500 | AN48: 257179 | AO48: 244645 | AP48: =IFERROR(VLOOKUP($C48,[1]vlookup!$B:$N,8,FALSE),"") | AQ48: 270000 | AT48: 258775 | AU48: 276187 | AV48: =IFERROR(VLOOKUP($C48,[1]vlookup!$B:$N,9,FALSE),"") | AW48: 280000 | AZ48: 270036 | BA48: 253651 | BB48: =IFERROR(VLOOKUP($C48,[1]vlookup!$B:$N,10,FALSE),"") | BC48: 270000 | BF48: =IFERROR(SUM(AP48+AV48+BB48),"") | BG48: =IFERROR(SUM(AQ48+AW48+BC48),"") -> 820000 | BH48: 258961 | BJ48: =IFERROR(VLOOKUP($C48,[1]vlookup!$B:$N,11,FALSE),"") | BK48: =275000-15000 -> 260000 | BL48: 264648 | BM48: 292414 | BN48: =IFERROR(VLOOKUP($C48,[1]vlookup!$B:$N,12,FALSE),"") | BO48: =282000-5115-5000-5000 -> 266885 | BP48: 265030 | BR48: =IFERROR(VLOOKUP($C48,[1]vlookup!$B:$N,13,FALSE),"") | BS48: =284000-14000 -> 270000 | BV48: =IFERROR(SUM(BJ48+BN48+BR48),"") | BW48: =IFERROR(SUM(BK48+BO48+BS48),"") -> 796885

Sheet Bookies
A1: Sports Affiliate — 2026 Revenue Detail
A2: Read-only · All data flows from Forecast Input tab · Do not type here
A3: SUB-LINE | B3: METRIC | C3: Jan | D3: Feb | E3: Mar | F3: Apr | G3: May | H3: Jun | I3: Jul | J3: Aug | K3: Sep | L3: Oct | M3: Nov | N3: Dec | O3: FULL YEAR
A4: Bookies US | B4: Actual 26' | C4: ='Forecast Input'!D14 -> -3260.2155 | D4: ='Forecast Input'!E14 -> 44660 | E4: ='Forecast Input'!F14 -> 2249 | F4: ='Forecast Input'!G14 -> 0 | G4: ='Forecast Input'!H14 -> 0 | H4: ='Forecast Input'!I14 -> 0 | I4: ='Forecast Input'!J14 -> 0 | J4: ='Forecast Input'!K14 -> 0 | ... N4: ='Forecast Input'!O14 -> 0 | O4: =SUM(C4:N4) -> 43648.784
B5: Actual 25' | C5: 262576 | D5: 180289 | E5: 93554 | F5: 34926 | G5: 118110 | H5: 106250 | I5: 82816 | J5: 107660 | K5: 175588 | L5: 123948 | M5: 150687 | N5: 227007 | O5: =SUM(C5:N5) -> 1663411
B6: Forecast | C6: ='Forecast Input'!D15 -> 30000 | D6: ='Forecast Input'!E15 -> 37500 | E6: ='Forecast Input'!F15 -> 15000 | F6: ='Forecast Input'!G15 -> 55000 | G6: ='Forecast Input'!H15 -> 55000 | H6: ='Forecast Input'!I15 -> 55000 | I6: ='Forecast Input'!J15 -> 95000 | J6: ='Forecast Input'!K15 -> 105000 | ... N6: ='Forecast Input'!O15 -> 105000 | O6: =SUM(C6:N6) -> 912500
B7: Actual vs Forecast $ | C7: =IF(C4=0,"-",C4-C6) -> -33260.216 | D7: =IF(D4=0,"-",D4-D6) -> 7160 | E7: =IF(E4=0,"-",E4-E6) -> -12751 | F7: =IF(F4=0,"-",F4-F6) -> - | G7: =IF(G4=0,"-",G4-G6) -> - | H7: =IF(H4=0,"-",H4-H6) -> - | I7: =IF(I4=0,"-",I4-I6) -> - | J7: =IF(J4=0,"-",J4-J6) -> - | ... N7: =IF(N4=0,"-",N4-N6) -> -
B8: Actual vs Forecast % | C8: =IFERROR(C7/C4,"-") -> 10.201846 | D8: =IFERROR(D7/D4,"-") -> 0.16032244 | E8: =IFERROR(E7/E4,"-") -> -5.6696309 | F8: =IFERROR(F7/F4,"-") -> - | G8: =IFERROR(G7/G4,"-") -> - | H8: =IFERROR(H7/H4,"-") -> - | I8: =IFERROR(I7/I4,"-") -> - | J8: =IFERROR(J7/J4,"-") -> - | ... N8: =IFERROR(N7/N4,"-") -> -
B9: Forecast vs PY $ | C9: =IFERROR(C6-C5,"-") -> -232576 | D9: =IFERROR(D6-D5,"-") -> -142789 | E9: =IFERROR(E6-E5,"-") -> -78554 | F9: =IFERROR(F6-F5,"-") -> 20074 | G9: =IFERROR(G6-G5,"-") -> -63110 | H9: =IFERROR(H6-H5,"-") -> -51250 | I9: =IFERROR(I6-I5,"-") -> 12184 | J9: =IFERROR(J6-J5,"-") -> -2660 | ... N9: =IFERROR(N6-N5,"-") -> -122007
B10: Forecast vs PY % | C10: =IFERROR(C9/C5,"-") -> -0.88574736 | D10: =IFERROR(D9/D5,"-") -> -0.79200062 | E10: =IFERROR(E9/E5,"-") -> -0.83966479 | F10: =IFERROR(F9/F5,"-") -> 0.57475806 | G10: =IFERROR(G9/G5,"-") -> -0.5343324 | H10: =IFERROR(H9/H5,"-") -> -0.48235294 | I10: =IFERROR(I9/I5,"-") -> 0.14712133 | J10: =IFERROR(J9/J5,"-") -> -0.024707412 | ... N10: =IFERROR(N9/N5,"-") -> -0.5374592
A11: Bookies UK | B11: Actual 26' | C11: ='Forecast Input'!D16 -> 212757.88 | D11: ='Forecast Input'!E16 -> 148559.81 | E11: ='Forecast Input'!F16 -> 9433 | F11: ='Forecast Input'!G16 -> 0 | G11: ='Forecast Input'!H16 -> 0 | H11: ='Forecast Input'!I16 -> 0 | I11: ='Forecast Input'!J16 -> 0 | J11: ='Forecast Input'!K16 -> 0 | ... N11: ='Forecast Input'!O16 -> 0 | O11: =SUM(C11:N11) -> 370750.69
B12: Actual 25' | C12: 149880 | D12: 133718 | E12: 196430 | F12: 196519 | G12: 224388 | H12: 207657 | I12: 244338 | J12: 277625 | K12: 219810 | L12: 193860 | M12: 172200 | N12: 95426 | O12: =SUM(C12:N12) -> 2311851
B13: Forecast | C13: ='Forecast Input'!D17 -> 175000 | D13: ='Forecast Input'!E17 -> 177000 | E13: ='Forecast Input'!F17 -> 150000 | F13: ='Forecast Input'!G17 -> 150000 | G13: ='Forecast Input'!H17 -> 150000 | H13: ='Forecast Input'!I17 -> 150000 | I13: ='Forecast Input'!J17 -> 150000 | J13: ='Forecast Input'!K17 -> 215000 | ... N13: ='Forecast Input'!O17 -> 200000 | O13: =SUM(C13:N13) -> 2122000
B14: Actual vs Forecast $ | C14: =IF(C11=0,"-",C11-C13) -> 37757.878 | D14: =IF(D11=0,"-",D11-D13) -> -28440.193 | E14: =IF(E11=0,"-",E11-E13) -> -140567 | F14: =IF(F11=0,"-",F11-F13) -> - | G14: =IF(G11=0,"-",G11-G13) -> - | H14: =IF(H11=0,"-",H11-H13) -> - | I14: =IF(I11=0,"-",I11-I13) -> - | J14: =IF(J11=0,"-",J11-J13) -> - | ... N14: =IF(N11=0,"-",N11-N13) -> -
B15: Actual vs Forecast % | C15: =IFERROR(C14/C11,"-") -> 0.17746877 | D15: =IFERROR(D14/D11,"-") -> -0.19143935 | E15: =IFERROR(E14/E11,"-") -> -14.901622 | F15: =IFERROR(F14/F11,"-") -> - | G15: =IFERROR(G14/G11,"-") -> - | H15: =IFERROR(H14/H11,"-") -> - | I15: =IFERROR(I14/I11,"-") -> - | J15: =IFERROR(J14/J11,"-") -> - | ... N15: =IFERROR(N14/N11,"-") -> -
B16: Forecast vs PY $ | C16: =IFERROR(C13-C12,"-") -> 25120 | D16: =IFERROR(D13-D12,"-") -> 43282 | E16: =IFERROR(E13-E12,"-") -> -46430 | F16: =IFERROR(F13-F12,"-") -> -46519 | G16: =IFERROR(G13-G12,"-") -> -74388 | H16: =IFERROR(H13-H12,"-") -> -57657 | I16: =IFERROR(I13-I12,"-") -> -94338 | J16: =IFERROR(J13-J12,"-") -> -62625 | ... N16: =IFERROR(N13-N12,"-") -> 104574
B17: Forecast vs PY % | C17: =IFERROR(C16/C12,"-") -> 0.16760075 | D17: =IFERROR(D16/D12,"-") -> 0.32368118 | E17: =IFERROR(E16/E12,"-") -> -0.23636919 | F17: =IFERROR(F16/F12,"-") -> -0.23671503 | G17: =IFERROR(G16/G12,"-") -> -0.33151505 | H17: =IFERROR(H16/H12,"-") -> -0.27765498 | I17: =IFERROR(I16/I12,"-") -> -0.38609631 | J17: =IFERROR(J16/J12,"-") -> -0.22557407 | ... N17: =IFERROR(N16/N12,"-") -> 1.0958649
A18: Bookies IE | B18: Actual 26' | C18: ='Forecast Input'!D18 -> 2024.5313 | D18: ='Forecast Input'!E18 -> 6347.5797 | E18: ='Forecast Input'!F18 -> 6358 | F18: ='Forecast Input'!G18 -> 0 | G18: ='Forecast Input'!H18 -> 0 | H18: ='Forecast Input'!I18 -> 0 | I18: ='Forecast Input'!J18 -> 0 | J18: ='Forecast Input'!K18 -> 0 | ... N18: ='Forecast Input'!O18 -> 0 | O18: =SUM(C18:N18) -> 14730.111
B19: Actual 25' | C19: 10301 | D19: 13890 | E19: 14358 | F19: 20048 | G19: 16854 | H19: 17122 | I19: 14885 | J19: 14245 | K19: 9552 | L19: 9835 | M19: 8211 | N19: 4091 | O19: =SUM(C19:N19) -> 153392
B20: Forecast | C20: ='Forecast Input'!D19 -> 12500 | D20: ='Forecast Input'!E19 -> 13500 | E20: ='Forecast Input'!F19 -> 13000 | F20: ='Forecast Input'!G19 -> 13500 | G20: ='Forecast Input'!H19 -> 12000 | H20: ='Forecast Input'!I19 -> 13500 | I20: ='Forecast Input'!J19 -> 12000 | J20: ='Forecast Input'!K19 -> 14000 | ... N20: ='Forecast Input'!O19 -> 10000 | O20: =SUM(C20:N20) -> 150000
B21: Actual vs Forecast $ | C21: =IF(C18=0,"-",C18-C20) -> -10475.469 | D21: =IF(D18=0,"-",D18-D20) -> -7152.4203 | E21: =IF(E18=0,"-",E18-E20) -> -6642 | F21: =IF(F18=0,"-",F18-F20) -> - | G21: =IF(G18=0,"-",G18-G20) -> - | H21: =IF(H18=0,"-",H18-H20) -> - | I21: =IF(I18=0,"-",I18-I20) -> - | J21: =IF(J18=0,"-",J18-J20) -> - | ... N21: =IF(N18=0,"-",N18-N20) -> -
B22: Actual vs Forecast % | C22: =IFERROR(C21/C18,"-") -> -5.1742685 | D22: =IFERROR(D21/D18,"-") -> -1.1267949 | E22: =IFERROR(E21/E18,"-") -> -1.0446681 | F22: =IFERROR(F21/F18,"-") -> - | G22: =IFERROR(G21/G18,"-") -> - | H22: =IFERROR(H21/H18,"-") -> - | I22: =IFERROR(I21/I18,"-") -> - | J22: =IFERROR(J21/J18,"-") -> - | ... N22: =IFERROR(N21/N18,"-") -> -
B23: Forecast vs PY $ | C23: =IFERROR(C20-C19,"-") -> 2199 | D23: =IFERROR(D20-D19,"-") -> -390 | E23: =IFERROR(E20-E19,"-") -> -1358 | F23: =IFERROR(F20-F19,"-") -> -6548 | G23: =IFERROR(G20-G19,"-") -> -4854 | H23: =IFERROR(H20-H19,"-") -> -3622 | I23: =IFERROR(I20-I19,"-") -> -2885 | J23: =IFERROR(J20-J19,"-") -> -245 | ... N23: =IFERROR(N20-N19,"-") -> 5909
B24: Forecast vs PY % | C24: =IFERROR(C23/C19,"-") -> 0.21347442 | D24: =IFERROR(D23/D19,"-") -> -0.028077754 | E24: =IFERROR(E23/E19,"-") -> -0.094581418 | F24: =IFERROR(F23/F19,"-") -> -0.32661612 | G24: =IFERROR(G23/G19,"-") -> -0.28800285 | H24: =IFERROR(H23/H19,"-") -> -0.21154071 | I24: =IFERROR(I23/I19,"-") -> -0.19381928 | J24: =IFERROR(J23/J19,"-") -> -0.017199017 | ... N24: =IFERROR(N23/N19,"-") -> 1.4443901
A25: Bookies IN | B25: Actual 26' | C25: ='Forecast Input'!D20 -> 5566.1161 | D25: ='Forecast Input'!E20 -> 14370.106 | E25: ='Forecast Input'!F20 -> 7935 | F25: ='Forecast Input'!G20 -> 0 | G25: ='Forecast Input'!H20 -> 0 | H25: ='Forecast Input'!I20 -> 0 | I25: ='Forecast Input'!J20 -> 0 | J25: ='Forecast Input'!K20 -> 0 | ... N25: ='Forecast Input'!O20 -> 0 | O25: =SUM(C25:N25) -> 27871.222
B26: Actual 25' | O26: =SUM(C26:N26) -> 0
B27: Forecast | C27: ='Forecast Input'!D21 -> 10000 | D27: ='Forecast Input'!E21 -> 10000 | E27: ='Forecast Input'!F21 -> 8500 | F27: ='Forecast Input'!G21 -> 8000 | G27: ='Forecast Input'!H21 -> 8000 | H27: ='Forecast Input'!I21 -> 8000 | I27: ='Forecast Input'!J21 -> 8000 | J27: ='Forecast Input'!K21 -> 8000 | ... N27: ='Forecast Input'!O21 -> 8000 | O27: =SUM(C27:N27) -> 100500
B28: Actual vs Forecast $ | C28: =IF(C25=0,"-",C25-C27) -> -4433.8839 | D28: =IF(D25=0,"-",D25-D27) -> 4370.1061 | E28: =IF(E25=0,"-",E25-E27) -> -565 | F28: =IF(F25=0,"-",F25-F27) -> - | G28: =IF(G25=0,"-",G25-G27) -> - | H28: =IF(H25=0,"-",H25-H27) -> - | I28: =IF(I25=0,"-",I25-I27) -> - | J28: =IF(J25=0,"-",J25-J27) -> - | ... N28: =IF(N25=0,"-",N25-N27) -> -
B29: Actual vs Forecast % | C29: =IFERROR(C28/C25,"-") -> -0.79658489 | D29: =IFERROR(D28/D25,"-") -> 0.30411091 | E29: =IFERROR(E28/E25,"-") -> -0.071203529 | F29: =IFERROR(F28/F25,"-") -> - | G29: =IFERROR(G28/G25,"-") -> - | H29: =IFERROR(H28/H25,"-") -> - | I29: =IFERROR(I28/I25,"-") -> - | J29: =IFERROR(J28/J25,"-") -> - | ... N29: =IFERROR(N28/N25,"-") -> -
B30: Forecast vs PY $ | C30: =IFERROR(C27-C26,"-") -> 10000 | D30: =IFERROR(D27-D26,"-") -> 10000 | E30: =IFERROR(E27-E26,"-") -> 8500 | F30: =IFERROR(F27-F26,"-") -> 8000 | G30: =IFERROR(G27-G26,"-") -> 8000 | H30: =IFERROR(H27-H26,"-") -> 8000 | I30: =IFERROR(I27-I26,"-") -> 8000 | J30: =IFERROR(J27-J26,"-") -> 8000 | ... N30: =IFERROR(N27-N26,"-") -> 8000
B31: Forecast vs PY % | C31: =IFERROR(C30/C26,"-") -> - | D31: =IFERROR(D30/D26,"-") -> - | E31: =IFERROR(E30/E26,"-") -> - | F31: =IFERROR(F30/F26,"-") -> - | G31: =IFERROR(G30/G26,"-") -> - | H31: =IFERROR(H30/H26,"-") -> - | I31: =IFERROR(I30/I26,"-") -> - | J31: =IFERROR(J30/J26,"-") -> - | ... N31: =IFERROR(N30/N26,"-") -> -
A32: Bookies CA | B32: Actual 26' | C32: ='Forecast Input'!D22 -> 9408.0531 | D32: ='Forecast Input'!E22 -> 4565.4974 | E32: ='Forecast Input'!F22 -> 14841 | F32: ='Forecast Input'!G22 -> 0 | G32: ='Forecast Input'!H22 -> 0 | H32: ='Forecast Input'!I22 -> 0 | I32: ='Forecast Input'!J22 -> 0 | J32: ='Forecast Input'!K22 -> 0 | ... N32: ='Forecast Input'!O22 -> 0 | O32: =SUM(C32:N32) -> 28814.55
B33: Actual 25' | C33: 13851 | D33: 14079 | E33: 24114 | F33: 17370 | G33: 14648 | H33: 13163 | I33: 15289 | J33: 16435 | K33: 17469 | L33: 16016 | M33: 19852 | N33: 19379 | O33: =SUM(C33:N33) -> 201665
B34: Forecast | C34: ='Forecast Input'!D23 -> 17500 | D34: ='Forecast Input'!E23 -> 15000 | E34: ='Forecast Input'!F23 -> 14500 | F34: ='Forecast Input'!G23 -> 14500 | G34: ='Forecast Input'!H23 -> 14500 | H34: ='Forecast Input'!I23 -> 15000 | I34: ='Forecast Input'!J23 -> 16500 | J34: ='Forecast Input'!K23 -> 16500 | ... N34: ='Forecast Input'!O23 -> 18000 | O34: =SUM(C34:N34) -> 198500
B35: Actual vs Forecast $ | C35: =IF(C32=0,"-",C32-C34) -> -8091.9469 | D35: =IF(D32=0,"-",D32-D34) -> -10434.503 | E35: =IF(E32=0,"-",E32-E34) -> 341 | F35: =IF(F32=0,"-",F32-F34) -> - | G35: =IF(G32=0,"-",G32-G34) -> - | H35: =IF(H32=0,"-",H32-H34) -> - | I35: =IF(I32=0,"-",I32-I34) -> - | J35: =IF(J32=0,"-",J32-J34) -> - | ... N35: =IF(N32=0,"-",N32-N34) -> -
B36: Actual vs Forecast % | C36: =IFERROR(C35/C32,"-") -> -0.86010856 | D36: =IFERROR(D35/D32,"-") -> -2.2855128 | E36: =IFERROR(E35/E32,"-") -> 0.022976888 | F36: =IFERROR(F35/F32,"-") -> - | G36: =IFERROR(G35/G32,"-") -> - | H36: =IFERROR(H35/H32,"-") -> - | I36: =IFERROR(I35/I32,"-") -> - | J36: =IFERROR(J35/J32,"-") -> - | ... N36: =IFERROR(N35/N32,"-") -> -
B37: Forecast vs PY $ | C37: =IFERROR(C34-C33,"-") -> 3649 | D37: =IFERROR(D34-D33,"-") -> 921 | E37: =IFERROR(E34-E33,"-") -> -9614 | F37: =IFERROR(F34-F33,"-") -> -2870 | G37: =IFERROR(G34-G33,"-") -> -148 | H37: =IFERROR(H34-H33,"-") -> 1837 | I37: =IFERROR(I34-I33,"-") -> 1211 | J37: =IFERROR(J34-J33,"-") -> 65 | ... N37: =IFERROR(N34-N33,"-") -> -1379
B38: Forecast vs PY % | C38: =IFERROR(C37/C33,"-") -> 0.26344668 | D38: =IFERROR(D37/D33,"-") -> 0.065416578 | E38: =IFERROR(E37/E33,"-") -> -0.39868956 | F38: =IFERROR(F37/F33,"-") -> -0.1652274 | G38: =IFERROR(G37/G33,"-") -> -0.010103768 | H38: =IFERROR(H37/H33,"-") -> 0.13955785 | I38: =IFERROR(I37/I33,"-") -> 0.079207273 | J38: =IFERROR(J37/J33,"-") -> 0.0039549741 | ... N38: =IFERROR(N37/N33,"-") -> -0.071159503
A39: Bookies AU | B39: Actual 26' | C39: ='Forecast Input'!D24 -> 2960.88 | D39: ='Forecast Input'!E24 -> 687.37603 | E39: ='Forecast Input'!F24 -> -1533 | F39: ='Forecast Input'!G24 -> 0 | G39: ='Forecast Input'!H24 -> 0 | H39: ='Forecast Input'!I24 -> 0 | I39: ='Forecast Input'!J24 -> 0 | J39: ='Forecast Input'!K24 -> 0 | ... N39: ='Forecast Input'!O24 -> 0 | O39: =SUM(C39:N39) -> 2115.2561
B40: Actual 25' | O40: =SUM(C40:N40) -> 0
B41: Forecast | C41: ='Forecast Input'!D25 -> 1500 | D41: ='Forecast Input'!E25 -> 1500 | E41: ='Forecast Input'!F25 -> 1500 | F41: ='Forecast Input'!G25 -> 1500 | G41: ='Forecast Input'!H25 -> 1500 | H41: ='Forecast Input'!I25 -> 1500 | I41: ='Forecast Input'!J25 -> 1500 | J41: ='Forecast Input'!K25 -> 1500 | ... N41: ='Forecast Input'!O25 -> 1500 | O41: =SUM(C41:N41) -> 18000
B42: Actual vs Forecast $ | C42: =IF(C39=0,"-",C39-C41) -> 1460.88 | D42: =IF(D39=0,"-",D39-D41) -> -812.62397 | E42: =IF(E39=0,"-",E39-E41) -> -3033 | F42: =IF(F39=0,"-",F39-F41) -> - | G42: =IF(G39=0,"-",G39-G41) -> - | H42: =IF(H39=0,"-",H39-H41) -> - | I42: =IF(I39=0,"-",I39-I41) -> - | J42: =IF(J39=0,"-",J39-J41) -> - | ... N42: =IF(N39=0,"-",N39-N41) -> -
B43: Actual vs Forecast % | C43: =IFERROR(C42/C39,"-") -> 0.49339386 | D43: =IFERROR(D42/D39,"-") -> -1.1822117 | E43: =IFERROR(E42/E39,"-") -> 1.9784736 | F43: =IFERROR(F42/F39,"-") -> - | G43: =IFERROR(G42/G39,"-") -> - | H43: =IFERROR(H42/H39,"-") -> - | I43: =IFERROR(I42/I39,"-") -> - | J43: =IFERROR(J42/J39,"-") -> - | ... N43: =IFERROR(N42/N39,"-") -> -
B44: Forecast vs PY $ | C44: =IFERROR(C41-C40,"-") -> 1500 | D44: =IFERROR(D41-D40,"-") -> 1500 | E44: =IFERROR(E41-E40,"-") -> 1500 | F44: =IFERROR(F41-F40,"-") -> 1500 | G44: =IFERROR(G41-G40,"-") -> 1500 | H44: =IFERROR(H41-H40,"-") -> 1500 | I44: =IFERROR(I41-I40,"-") -> 1500 | J44: =IFERROR(J41-J40,"-") -> 1500 | ... N44: =IFERROR(N41-N40,"-") -> 1500
B45: Forecast vs PY % | C45: =IFERROR(C44/C40,"-") -> - | D45: =IFERROR(D44/D40,"-") -> - | E45: =IFERROR(E44/E40,"-") -> - | F45: =IFERROR(F44/F40,"-") -> - | G45: =IFERROR(G44/G40,"-") -> - | H45: =IFERROR(H44/H40,"-") -> - | I45: =IFERROR(I44/I40,"-") -> - | J45: =IFERROR(J44/J40,"-") -> - | ... N45: =IFERROR(N44/N40,"-") -> -
A46: Bookies NZ | B46: Actual 26' | C46: ='Forecast Input'!D26 -> 1721.4416 | D46: ='Forecast Input'!E26 -> 4112.945 | E46: ='Forecast Input'!F26 -> 4550 | F46: ='Forecast Input'!G26 -> 0 | G46: ='Forecast Input'!H26 -> 0 | H46: ='Forecast Input'!I26 -> 0 | I46: ='Forecast Input'!J26 -> 0 | J46: ='Forecast Input'!K26 -> 0 | ... N46: ='Forecast Input'!O26 -> 0 | O46: =SUM(C46:N46) -> 10384.387
B47: Actual 25' | C47: 3058 | D47: 3502 | E47: 7933 | F47: 8902 | G47: 5388 | H47: 6036 | I47: 10584 | J47: 7942 | K47: 876 | L47: 7170 | M47: 3508 | N47: 3201 | O47: =SUM(C47:N47) -> 68100
B48: Forecast | C48: ='Forecast Input'!D27 -> 10000 | D48: ='Forecast Input'!E27 -> 5000 | E48: ='Forecast Input'!F27 -> 10000 | F48: ='Forecast Input'!G27 -> 7500 | G48: ='Forecast Input'!H27 -> 8000 | H48: ='Forecast Input'!I27 -> 8000 | I48: ='Forecast Input'!J27 -> 8500 | J48: ='Forecast Input'!K27 -> 8500 | ... N48: ='Forecast Input'!O27 -> 8500 | O48: =SUM(C48:N48) -> 101500
B49: Actual vs Forecast $ | C49: =IF(C46=0,"-",C46-C48) -> -8278.5584 | D49: =IF(D46=0,"-",D46-D48) -> -887.05496 | E49: =IF(E46=0,"-",E46-E48) -> -5450 | F49: =IF(F46=0,"-",F46-F48) -> - | G49: =IF(G46=0,"-",G46-G48) -> - | H49: =IF(H46=0,"-",H46-H48) -> - | I49: =IF(I46=0,"-",I46-I48) -> - | J49: =IF(J46=0,"-",J46-J48) -> - | ... N49: =IF(N46=0,"-",N46-N48) -> -
B50: Actual vs Forecast % | C50: =IFERROR(C49/C46,"-") -> -4.8090846 | D50: =IFERROR(D49/D46,"-") -> -0.21567391 | E50: =IFERROR(E49/E46,"-") -> -1.1978022 | F50: =IFERROR(F49/F46,"-") -> - | G50: =IFERROR(G49/G46,"-") -> - | H50: =IFERROR(H49/H46,"-") -> - | I50: =IFERROR(I49/I46,"-") -> - | J50: =IFERROR(J49/J46,"-") -> - | ... N50: =IFERROR(N49/N46,"-") -> -
B51: Forecast vs PY $ | C51: =IFERROR(C48-C47,"-") -> 6942 | D51: =IFERROR(D48-D47,"-") -> 1498 | E51: =IFERROR(E48-E47,"-") -> 2067 | F51: =IFERROR(F48-F47,"-") -> -1402 | G51: =IFERROR(G48-G47,"-") -> 2612 | H51: =IFERROR(H48-H47,"-") -> 1964 | I51: =IFERROR(I48-I47,"-") -> -2084 | J51: =IFERROR(J48-J47,"-") -> 558 | ... N51: =IFERROR(N48-N47,"-") -> 5299
B52: Forecast vs PY % | C52: =IFERROR(C51/C47,"-") -> 2.2701112 | D52: =IFERROR(D51/D47,"-") -> 0.42775557 | E52: =IFERROR(E51/E47,"-") -> 0.26055717 | F52: =IFERROR(F51/F47,"-") -> -0.1574927 | G52: =IFERROR(G51/G47,"-") -> 0.48478099 | H52: =IFERROR(H51/H47,"-") -> 0.32538105 | I52: =IFERROR(I51/I47,"-") -> -0.19690098 | J52: =IFERROR(J51/J47,"-") -> 0.070259381 | ... N52: =IFERROR(N51/N47,"-") -> 1.6554202
A53: Bookies MX | B53: Actual 26' | C53: ='Forecast Input'!D28 -> 8337.3099 | D53: ='Forecast Input'!E28 -> 3992.0958 | E53: ='Forecast Input'!F28 -> 1794 | F53: ='Forecast Input'!G28 -> 0 | G53: ='Forecast Input'!H28 -> 0 | H53: ='Forecast Input'!I28 -> 0 | I53: ='Forecast Input'!J28 -> 0 | J53: ='Forecast Input'!K28 -> 0 | ... N53: ='Forecast Input'!O28 -> 0 | O53: =SUM(C53:N53) -> 14123.406
B54: Actual 25' | O54: =SUM(C54:N54) -> 0
B55: Forecast | C55: ='Forecast Input'!D29 -> 3000 | D55: ='Forecast Input'!E29 -> 8000 | E55: ='Forecast Input'!F29 -> 8000 | F55: ='Forecast Input'!G29 -> 5500 | G55: ='Forecast Input'!H29 -> 5500 | H55: ='Forecast Input'!I29 -> 5500 | I55: ='Forecast Input'!J29 -> 5500 | J55: ='Forecast Input'!K29 -> 5500 | ... N55: ='Forecast Input'!O29 -> 5500 | O55: =SUM(C55:N55) -> 68500
B56: Actual vs Forecast $ | C56: =IF(C53=0,"-",C53-C55) -> 5337.3099 | D56: =IF(D53=0,"-",D53-D55) -> -4007.9042 | E56: =IF(E53=0,"-",E53-E55) -> -6206 | F56: =IF(F53=0,"-",F53-F55) -> - | G56: =IF(G53=0,"-",G53-G55) -> - | H56: =IF(H53=0,"-",H53-H55) -> - | I56: =IF(I53=0,"-",I53-I55) -> - | J56: =IF(J53=0,"-",J53-J55) -> - | ... N56: =IF(N53=0,"-",N53-N55) -> -
B57: Actual vs Forecast % | C57: =IFERROR(C56/C53,"-") -> 0.6401717 | D57: =IFERROR(D56/D53,"-") -> -1.0039599 | E57: =IFERROR(E56/E53,"-") -> -3.4593088 | F57: =IFERROR(F56/F53,"-") -> - | G57: =IFERROR(G56/G53,"-") -> - | H57: =IFERROR(H56/H53,"-") -> - | I57: =IFERROR(I56/I53,"-") -> - | J57: =IFERROR(J56/J53,"-") -> - | ... N57: =IFERROR(N56/N53,"-") -> -
B58: Forecast vs PY $ | C58: =IFERROR(C55-C54,"-") -> 3000 | D58: =IFERROR(D55-D54,"-") -> 8000 | E58: =IFERROR(E55-E54,"-") -> 8000 | F58: =IFERROR(F55-F54,"-") -> 5500 | G58: =IFERROR(G55-G54,"-") -> 5500 | H58: =IFERROR(H55-H54,"-") -> 5500 | I58: =IFERROR(I55-I54,"-") -> 5500 | J58: =IFERROR(J55-J54,"-") -> 5500 | ... N58: =IFERROR(N55-N54,"-") -> 5500
B59: Forecast vs PY % | C59: =IFERROR(C58/C54,"-") -> - | D59: =IFERROR(D58/D54,"-") -> - | E59: =IFERROR(E58/E54,"-") -> - | F59: =IFERROR(F58/F54,"-") -> - | G59: =IFERROR(G58/G54,"-") -> - | H59: =IFERROR(H58/H54,"-") -> - | I59: =IFERROR(I58/I54,"-") -> - | J59: =IFERROR(J58/J54,"-") -> - | ... N59: =IFERROR(N58/N54,"-") -> -
A60: Bookies NG | B60: Actual 26' | C60: ='Forecast Input'!D30 -> 0.648964 | D60: ='Forecast Input'!E30 -> 0 | E60: ='Forecast Input'!F30 -> 0 | F60: ='Forecast Input'!G30 -> 0 | G60: ='Forecast Input'!H30 -> 0 | H60: ='Forecast Input'!I30 -> 0 | I60: ='Forecast Input'!J30 -> 0 | J60: ='Forecast Input'!K30 -> 0 | ... N60: ='Forecast Input'!O30 -> 0 | O60: =SUM(C60:N60) -> 0.648964
B61: Actual 25' | O61: =SUM(C61:N61) -> 0
B62: Forecast | C62: ='Forecast Input'!D31 -> 0 | D62: ='Forecast Input'!E31 -> 0 | E62: ='Forecast Input'!F31 -> 0 | F62: ='Forecast Input'!G31 -> 0 | G62: ='Forecast Input'!H31 -> 0 | H62: ='Forecast Input'!I31 -> 0 | I62: ='Forecast Input'!J31 -> 0 | J62: ='Forecast Input'!K31 -> 0 | ... N62: ='Forecast Input'!O31 -> 0 | O62: =SUM(C62:N62) -> 0
B63: Actual vs Forecast $ | C63: =IF(C60=0,"-",C60-C62) -> 0.648964 | D63: =IF(D60=0,"-",D60-D62) -> - | E63: =IF(E60=0,"-",E60-E62) -> - | F63: =IF(F60=0,"-",F60-F62) -> - | G63: =IF(G60=0,"-",G60-G62) -> - | H63: =IF(H60=0,"-",H60-H62) -> - | I63: =IF(I60=0,"-",I60-I62) -> - | J63: =IF(J60=0,"-",J60-J62) -> - | ... N63: =IF(N60=0,"-",N60-N62) -> -
B64: Actual vs Forecast % | C64: =IFERROR(C63/C60,"-") -> 1 | D64: =IFERROR(D63/D60,"-") -> - | E64: =IFERROR(E63/E60,"-") -> - | F64: =IFERROR(F63/F60,"-") -> - | G64: =IFERROR(G63/G60,"-") -> - | H64: =IFERROR(H63/H60,"-") -> - | I64: =IFERROR(I63/I60,"-") -> - | J64: =IFERROR(J63/J60,"-") -> - | ... N64: =IFERROR(N63/N60,"-") -> -
B65: Forecast vs PY $ | C65: =IFERROR(C62-C61,"-") -> 0 | D65: =IFERROR(D62-D61,"-") -> 0 | E65: =IFERROR(E62-E61,"-") -> 0 | F65: =IFERROR(F62-F61,"-") -> 0 | G65: =IFERROR(G62-G61,"-") -> 0 | H65: =IFERROR(H62-H61,"-") -> 0 | I65: =IFERROR(I62-I61,"-") -> 0 | J65: =IFERROR(J62-J61,"-") -> 0 | ... N65: =IFERROR(N62-N61,"-") -> 0
B66: Forecast vs PY % | C66: =IFERROR(C65/C61,"-") -> - | D66: =IFERROR(D65/D61,"-") -> - | E66: =IFERROR(E65/E61,"-") -> - | F66: =IFERROR(F65/F61,"-") -> - | G66: =IFERROR(G65/G61,"-") -> - | H66: =IFERROR(H65/H61,"-") -> - | I66: =IFERROR(I65/I61,"-") -> - | J66: =IFERROR(J65/J61,"-") -> - | ... N66: =IFERROR(N65/N61,"-") -> -
A67: Bookies NL | B67: Actual 26' | C67: ='Forecast Input'!D32 -> 601.71932 | D67: ='Forecast Input'!E32 -> 224.09292 | E67: ='Forecast Input'!F32 -> 15 | F67: ='Forecast Input'!G32 -> 0 | G67: ='Forecast Input'!H32 -> 0 | H67: ='Forecast Input'!I32 -> 0 | I67: ='Forecast Input'!J32 -> 0 | J67: ='Forecast Input'!K32 -> 0 | ... N67: ='Forecast Input'!O32 -> 0 | O67: =SUM(C67:N67) -> 840.81223
B68: Actual 25' | O68: =SUM(C68:N68) -> 0
B69: Forecast | C69: ='Forecast Input'!D33 -> 1500 | D69: ='Forecast Input'!E33 -> 1500 | E69: ='Forecast Input'!F33 -> 1500 | F69: ='Forecast Input'!G33 -> 1500 | G69: ='Forecast Input'!H33 -> 1500 | H69: ='Forecast Input'!I33 -> 1500 | I69: ='Forecast Input'!J33 -> 1500 | J69: ='Forecast Input'!K33 -> 1500 | ... N69: ='Forecast Input'!O33 -> 1500 | O69: =SUM(C69:N69) -> 18000
B70: Actual vs Forecast $ | C70: =IF(C67=0,"-",C67-C69) -> -898.28068 | D70: =IF(D67=0,"-",D67-D69) -> -1275.9071 | E70: =IF(E67=0,"-",E67-E69) -> -1485 | F70: =IF(F67=0,"-",F67-F69) -> - | G70: =IF(G67=0,"-",G67-G69) -> - | H70: =IF(H67=0,"-",H67-H69) -> - | I70: =IF(I67=0,"-",I67-I69) -> - | J70: =IF(J67=0,"-",J67-J69) -> - | ... N70: =IF(N67=0,"-",N67-N69) -> -
B71: Actual vs Forecast % | C71: =IFERROR(C70/C67,"-") -> -1.4928567 | D71: =IFERROR(D70/D67,"-") -> -5.6936521 | E71: =IFERROR(E70/E67,"-") -> -99 | F71: =IFERROR(F70/F67,"-") -> - | G71: =IFERROR(G70/G67,"-") -> - | H71: =IFERROR(H70/H67,"-") -> - | I71: =IFERROR(I70/I67,"-") -> - | J71: =IFERROR(J70/J67,"-") -> - | ... N71: =IFERROR(N70/N67,"-") -> -
B72: Forecast vs PY $ | C72: =IFERROR(C69-C68,"-") -> 1500 | D72: =IFERROR(D69-D68,"-") -> 1500 | E72: =IFERROR(E69-E68,"-") -> 1500 | F72: =IFERROR(F69-F68,"-") -> 1500 | G72: =IFERROR(G69-G68,"-") -> 1500 | H72: =IFERROR(H69-H68,"-") -> 1500 | I72: =IFERROR(I69-I68,"-") -> 1500 | J72: =IFERROR(J69-J68,"-") -> 1500 | ... N72: =IFERROR(N69-N68,"-") -> 1500
B73: Forecast vs PY % | C73: =IFERROR(C72/C68,"-") -> - | D73: =IFERROR(D72/D68,"-") -> - | E73: =IFERROR(E72/E68,"-") -> - | F73: =IFERROR(F72/F68,"-") -> - | G73: =IFERROR(G72/G68,"-") -> - | H73: =IFERROR(H72/H68,"-") -> - | I73: =IFERROR(I72/I68,"-") -> - | J73: =IFERROR(J72/J68,"-") -> - | ... N73: =IFERROR(N72/N68,"-") -> -
A74: Bookies BR | B74: Actual 26' | C74: ='Forecast Input'!D34 -> 111.69258 | D74: ='Forecast Input'!E34 -> 260.21518 | E74: ='Forecast Input'!F34 -> -77 | F74: ='Forecast Input'!G34 -> 0 | G74: ='Forecast Input'!H34 -> 0 | H74: ='Forecast Input'!I34 -> 0 | I74: ='Forecast Input'!J34 -> 0 | J74: ='Forecast Input'!K34 -> 0 | ... N74: ='Forecast Input'!O34 -> 0 | O74: =SUM(C74:N74) -> 294.90776
B75: Actual 25' | O75: =SUM(C75:N75) -> 0
B76: Forecast | C76: ='Forecast Input'!D35 -> 100 | D76: ='Forecast Input'!E35 -> 100 | E76: ='Forecast Input'!F35 -> 100 | F76: ='Forecast Input'!G35 -> 100 | G76: ='Forecast Input'!H35 -> 100 | H76: ='Forecast Input'!I35 -> 100 | I76: ='Forecast Input'!J35 -> 100 | J76: ='Forecast Input'!K35 -> 100 | ... N76: ='Forecast Input'!O35 -> 100 | O76: =SUM(C76:N76) -> 1200
B77: Actual vs Forecast $ | C77: =IF(C74=0,"-",C74-C76) -> 11.692585 | D77: =IF(D74=0,"-",D74-D76) -> 160.21518 | E77: =IF(E74=0,"-",E74-E76) -> -177 | F77: =IF(F74=0,"-",F74-F76) -> - | G77: =IF(G74=0,"-",G74-G76) -> - | H77: =IF(H74=0,"-",H74-H76) -> - | I77: =IF(I74=0,"-",I74-I76) -> - | J77: =IF(J74=0,"-",J74-J76) -> - | ... N77: =IF(N74=0,"-",N74-N76) -> -
B78: Actual vs Forecast % | C78: =IFERROR(C77/C74,"-") -> 0.10468542 | D78: =IFERROR(D77/D74,"-") -> 0.61570266 | E78: =IFERROR(E77/E74,"-") -> 2.2987013 | F78: =IFERROR(F77/F74,"-") -> - | G78: =IFERROR(G77/G74,"-") -> - | H78: =IFERROR(H77/H74,"-") -> - | I78: =IFERROR(I77/I74,"-") -> - | J78: =IFERROR(J77/J74,"-") -> - | ... N78: =IFERROR(N77/N74,"-") -> -
B79: Forecast vs PY $ | C79: =IFERROR(C76-C75,"-") -> 100 | D79: =IFERROR(D76-D75,"-") -> 100 | E79: =IFERROR(E76-E75,"-") -> 100 | F79: =IFERROR(F76-F75,"-") -> 100 | G79: =IFERROR(G76-G75,"-") -> 100 | H79: =IFERROR(H76-H75,"-") -> 100 | I79: =IFERROR(I76-I75,"-") -> 100 | J79: =IFERROR(J76-J75,"-") -> 100 | ... N79: =IFERROR(N76-N75,"-") -> 100
B80: Forecast vs PY % | C80: =IFERROR(C79/C75,"-") -> - | D80: =IFERROR(D79/D75,"-") -> - | E80: =IFERROR(E79/E75,"-") -> - | F80: =IFERROR(F79/F75,"-") -> - | G80: =IFERROR(G79/G75,"-") -> - | H80: =IFERROR(H79/H75,"-") -> - | I80: =IFERROR(I79/I75,"-") -> - | J80: =IFERROR(J79/J75,"-") -> - | ... N80: =IFERROR(N79/N75,"-") -> -
A81: Bookies GX | B81: Actual 26' | C81: ='Forecast Input'!D36 -> 167.97545 | D81: ='Forecast Input'!E36 -> 546 | E81: ='Forecast Input'!F36 -> 651 | F81: ='Forecast Input'!G36 -> 0 | G81: ='Forecast Input'!H36 -> 0 | H81: ='Forecast Input'!I36 -> 0 | I81: ='Forecast Input'!J36 -> 0 | J81: ='Forecast Input'!K36 -> 0 | ... N81: ='Forecast Input'!O36 -> 0 | O81: =SUM(C81:N81) -> 1364.9755
B82: Actual 25' | I82: 2105 | J82: 1380 | K82: 740 | L82: 252 | M82: 336 | N82: 768 | O82: =SUM(C82:N82) -> 5581
B83: Forecast | C83: ='Forecast Input'!D37 -> 100 | D83: ='Forecast Input'!E37 -> 100 | E83: ='Forecast Input'!F37 -> 100 | F83: ='Forecast Input'!G37 -> 100 | G83: ='Forecast Input'!H37 -> 100 | H83: ='Forecast Input'!I37 -> 100 | I83: ='Forecast Input'!J37 -> 100 | J83: ='Forecast Input'!K37 -> 100 | ... N83: ='Forecast Input'!O37 -> 100 | O83: =SUM(C83:N83) -> 1200
B84: Actual vs Forecast $ | C84: =IF(C81=0,"-",C81-C83) -> 67.975453 | D84: =IF(D81=0,"-",D81-D83) -> 446 | E84: =IF(E81=0,"-",E81-E83) -> 551 | F84: =IF(F81=0,"-",F81-F83) -> - | G84: =IF(G81=0,"-",G81-G83) -> - | H84: =IF(H81=0,"-",H81-H83) -> - | I84: =IF(I81=0,"-",I81-I83) -> - | J84: =IF(J81=0,"-",J81-J83) -> - | ... N84: =IF(N81=0,"-",N81-N83) -> -
B85: Actual vs Forecast % | C85: =IFERROR(C84/C81,"-") -> 0.40467492 | D85: =IFERROR(D84/D81,"-") -> 0.81684982 | E85: =IFERROR(E84/E81,"-") -> 0.84639017 | F85: =IFERROR(F84/F81,"-") -> - | G85: =IFERROR(G84/G81,"-") -> - | H85: =IFERROR(H84/H81,"-") -> - | I85: =IFERROR(I84/I81,"-") -> - | J85: =IFERROR(J84/J81,"-") -> - | ... N85: =IFERROR(N84/N81,"-") -> -
B86: Forecast vs PY $ | C86: =IFERROR(C83-C82,"-") -> 100 | D86: =IFERROR(D83-D82,"-") -> 100 | E86: =IFERROR(E83-E82,"-") -> 100 | F86: =IFERROR(F83-F82,"-") -> 100 | G86: =IFERROR(G83-G82,"-") -> 100 | H86: =IFERROR(H83-H82,"-") -> 100 | I86: =IFERROR(I83-I82,"-") -> -2005 | J86: =IFERROR(J83-J82,"-") -> -1280 | ... N86: =IFERROR(N83-N82,"-") -> -668
B87: Forecast vs PY % | C87: =IFERROR(C86/C82,"-") -> - | D87: =IFERROR(D86/D82,"-") -> - | E87: =IFERROR(E86/E82,"-") -> - | F87: =IFERROR(F86/F82,"-") -> - | G87: =IFERROR(G86/G82,"-") -> - | H87: =IFERROR(H86/H82,"-") -> - | I87: =IFERROR(I86/I82,"-") -> -0.95249406 | J87: =IFERROR(J86/J82,"-") -> -0.92753623 | ... N87: =IFERROR(N86/N82,"-") -> -0.86979167
A88: Bookies ES | B88: Actual 26' | C88: ='Forecast Input'!D38 -> 0 | D88: ='Forecast Input'!E38 -> 5.797546 | E88: ='Forecast Input'!F38 -> 289 | F88: ='Forecast Input'!G38 -> 0 | G88: ='Forecast Input'!H38 -> 0 | H88: ='Forecast Input'!I38 -> 0 | I88: ='Forecast Input'!J38 -> 0 | J88: ='Forecast Input'!K38 -> 0 | ... N88: ='Forecast Input'!O38 -> 0 | O88: =SUM(C88:N88) -> 294.79755
B89: Actual 25' | O89: =SUM(C89:N89) -> 0
B90: Forecast | C90: ='Forecast Input'!D39 -> 100 | D90: ='Forecast Input'!E39 -> 100 | E90: ='Forecast Input'!F39 -> 100 | F90: ='Forecast Input'!G39 -> 500 | G90: ='Forecast Input'!H39 -> 500 | H90: ='Forecast Input'!I39 -> 500 | I90: ='Forecast Input'!J39 -> 1000 | J90: ='Forecast Input'!K39 -> 1000 | ... N90: ='Forecast Input'!O39 -> 1000 | O90: =SUM(C90:N90) -> 7800
B91: Actual vs Forecast $ | C91: =IF(C88=0,"-",C88-C90) -> - | D91: =IF(D88=0,"-",D88-D90) -> -94.202454 | E91: =IF(E88=0,"-",E88-E90) -> 189 | F91: =IF(F88=0,"-",F88-F90) -> - | G91: =IF(G88=0,"-",G88-G90) -> - | H91: =IF(H88=0,"-",H88-H90) -> - | I91: =IF(I88=0,"-",I88-I90) -> - | J91: =IF(J88=0,"-",J88-J90) -> - | ... N91: =IF(N88=0,"-",N88-N90) -> -
B92: Actual vs Forecast % | C92: =IFERROR(C91/C88,"-") -> - | D92: =IFERROR(D91/D88,"-") -> -16.248677 | E92: =IFERROR(E91/E88,"-") -> 0.65397924 | F92: =IFERROR(F91/F88,"-") -> - | G92: =IFERROR(G91/G88,"-") -> - | H92: =IFERROR(H91/H88,"-") -> - | I92: =IFERROR(I91/I88,"-") -> - | J92: =IFERROR(J91/J88,"-") -> - | ... N92: =IFERROR(N91/N88,"-") -> -
B93: Forecast vs PY $ | C93: =IFERROR(C90-C89,"-") -> 100 | D93: =IFERROR(D90-D89,"-") -> 100 | E93: =IFERROR(E90-E89,"-") -> 100 | F93: =IFERROR(F90-F89,"-") -> 500 | G93: =IFERROR(G90-G89,"-") -> 500 | H93: =IFERROR(H90-H89,"-") -> 500 | I93: =IFERROR(I90-I89,"-") -> 1000 | J93: =IFERROR(J90-J89,"-") -> 1000 | ... N93: =IFERROR(N90-N89,"-") -> 1000
B94: Forecast vs PY % | C94: =IFERROR(C93/C89,"-") -> - | D94: =IFERROR(D93/D89,"-") -> - | E94: =IFERROR(E93/E89,"-") -> - | F94: =IFERROR(F93/F89,"-") -> - | G94: =IFERROR(G93/G89,"-") -> - | H94: =IFERROR(H93/H89,"-") -> - | I94: =IFERROR(I93/I89,"-") -> - | J94: =IFERROR(J93/J89,"-") -> - | ... N94: =IFERROR(N93/N89,"-") -> -
A95: Bookmakers | B95: Actual 26' | C95: ='Forecast Input'!D40 -> -13263.989 | D95: ='Forecast Input'!E40 -> 17347.598 | E95: ='Forecast Input'!F40 -> 14186 | F95: ='Forecast Input'!G40 -> 0 | G95: ='Forecast Input'!H40 -> 0 | H95: ='Forecast Input'!I40 -> 0 | I95: ='Forecast Input'!J40 -> 0 | J95: ='Forecast Input'!K40 -> 0 | ... N95: ='Forecast Input'!O40 -> 0 | O95: =SUM(C95:N95) -> 18269.609
B96: Actual 25' | C96: 12385 | D96: 12236 | E96: 15559 | F96: 27495 | G96: 14343 | H96: 9118 | I96: 21964 | J96: 14702 | K96: 14774 | L96: 17638 | M96: 9330 | N96: 17106 | O96: =SUM(C96:N96) -> 186650
B97: Forecast | C97: ='Forecast Input'!D41 -> 12500 | D97: ='Forecast Input'!E41 -> 12500 | E97: ='Forecast Input'!F41 -> 18500 | F97: ='Forecast Input'!G41 -> 12500 | G97: ='Forecast Input'!H41 -> 12500 | H97: ='Forecast Input'!I41 -> 12500 | I97: ='Forecast Input'!J41 -> 12500 | J97: ='Forecast Input'!K41 -> 12500 | ... N97: ='Forecast Input'!O41 -> 12500 | O97: =SUM(C97:N97) -> 156000
B98: Actual vs Forecast $ | C98: =IF(C95=0,"-",C95-C97) -> -25763.989 | D98: =IF(D95=0,"-",D95-D97) -> 4847.5977 | E98: =IF(E95=0,"-",E95-E97) -> -4314 | F98: =IF(F95=0,"-",F95-F97) -> - | G98: =IF(G95=0,"-",G95-G97) -> - | H98: =IF(H95=0,"-",H95-H97) -> - | I98: =IF(I95=0,"-",I95-I97) -> - | J98: =IF(J95=0,"-",J95-J97) -> - | ... N98: =IF(N95=0,"-",N95-N97) -> -
B99: Actual vs Forecast % | C99: =IFERROR(C98/C95,"-") -> 1.9424013 | D99: =IFERROR(D98/D95,"-") -> 0.27943914 | E99: =IFERROR(E98/E95,"-") -> -0.30410264 | F99: =IFERROR(F98/F95,"-") -> - | G99: =IFERROR(G98/G95,"-") -> - | H99: =IFERROR(H98/H95,"-") -> - | I99: =IFERROR(I98/I95,"-") -> - | J99: =IFERROR(J98/J95,"-") -> - | ... N99: =IFERROR(N98/N95,"-") -> -
B100: Forecast vs PY $ | C100: =IFERROR(C97-C96,"-") -> 115 | D100: =IFERROR(D97-D96,"-") -> 264 | E100: =IFERROR(E97-E96,"-") -> 2941 | F100: =IFERROR(F97-F96,"-") -> -14995 | G100: =IFERROR(G97-G96,"-") -> -1843 | H100: =IFERROR(H97-H96,"-") -> 3382 | I100: =IFERROR(I97-I96,"-") -> -9464 | J100: =IFERROR(J97-J96,"-") -> -2202 | ... N100: =IFERROR(N97-N96,"-") -> -4606
...

Sheet Local
A1: Local — 2026 Revenue Detail
A2: Read-only · All data flows from Forecast Input tab · Do not type here
A3: SUB-LINE | B3: METRIC | C3: Jan | D3: Feb | E3: Mar | F3: Apr | G3: May | H3: Jun | I3: Jul | J3: Aug | K3: Sep | L3: Oct | M3: Nov | N3: Dec | O3: FULL YEAR
A4: BetArizona | B4: Actual 26' | C4: ='Forecast Input'!D48 -> 13350.067 | D4: ='Forecast Input'!E48 -> 8927.3897 | E4: ='Forecast Input'!F48 -> 15835.692 | F4: ='Forecast Input'!G48 -> 0 | G4: ='Forecast Input'!H48 -> 0 | H4: ='Forecast Input'!I48 -> 0 | I4: ='Forecast Input'!J48 -> 0 | J4: ='Forecast Input'!K48 -> 0 | ... N4: ='Forecast Input'!O48 -> 0 | O4: =SUM(C4:N4) -> 38113.149
B5: Actual 25' | C5: 25952 | D5: 33627 | E5: 28519 | F5: 21157 | G5: 12620 | H5: 25900 | I5: 19409 | J5: 17970 | K5: 29500 | L5: 20405 | M5: 39625 | N5: 35224 | O5: =SUM(C5:N5) -> 309908
B6: Forecast | C6: ='Forecast Input'!D49 -> 20000 | D6: ='Forecast Input'!E49 -> 12000 | E6: ='Forecast Input'!F49 -> 10000 | F6: ='Forecast Input'!G49 -> 5000 | G6: ='Forecast Input'!H49 -> 3000 | H6: ='Forecast Input'!I49 -> 3000 | I6: ='Forecast Input'!J49 -> 3000 | J6: ='Forecast Input'!K49 -> 5000 | ... N6: ='Forecast Input'!O49 -> 15000 | O6: =SUM(C6:N6) -> 126000
B7: Actual vs Forecast $ | C7: =IF(C4=0,"-",C4-C6) -> -6649.9328 | D7: =IF(D4=0,"-",D4-D6) -> -3072.6103 | E7: =IF(E4=0,"-",E4-E6) -> 5835.6918 | F7: =IF(F4=0,"-",F4-F6) -> - | G7: =IF(G4=0,"-",G4-G6) -> - | H7: =IF(H4=0,"-",H4-H6) -> - | I7: =IF(I4=0,"-",I4-I6) -> - | J7: =IF(J4=0,"-",J4-J6) -> - | ... N7: =IF(N4=0,"-",N4-N6) -> -
B8: Actual vs Forecast % | C8: =IFERROR(C7/C4,"-") -> -0.4981198 | D8: =IFERROR(D7/D4,"-") -> -0.3441779 | E8: =IFERROR(E7/E4,"-") -> 0.36851512 | F8: =IFERROR(F7/F4,"-") -> - | G8: =IFERROR(G7/G4,"-") -> - | H8: =IFERROR(H7/H4,"-") -> - | I8: =IFERROR(I7/I4,"-") -> - | J8: =IFERROR(J7/J4,"-") -> - | ... N8: =IFERROR(N7/N4,"-") -> -
B9: Forecast vs PY $ | C9: =IFERROR(C6-C5,"-") -> -5952 | D9: =IFERROR(D6-D5,"-") -> -21627 | E9: =IFERROR(E6-E5,"-") -> -18519 | F9: =IFERROR(F6-F5,"-") -> -16157 | G9: =IFERROR(G6-G5,"-") -> -9620 | H9: =IFERROR(H6-H5,"-") -> -22900 | I9: =IFERROR(I6-I5,"-") -> -16409 | J9: =IFERROR(J6-J5,"-") -> -12970 | ... N9: =IFERROR(N6-N5,"-") -> -20224
B10: Forecast vs PY % | C10: =IFERROR(C9/C5,"-") -> -0.22934649 | D10: =IFERROR(D9/D5,"-") -> -0.6431439 | E10: =IFERROR(E9/E5,"-") -> -0.64935657 | F10: =IFERROR(F9/F5,"-") -> -0.7636716 | G10: =IFERROR(G9/G5,"-") -> -0.76228209 | H10: =IFERROR(H9/H5,"-") -> -0.88416988 | I10: =IFERROR(I9/I5,"-") -> -0.84543253 | J10: =IFERROR(J9/J5,"-") -> -0.72175849 | ... N10: =IFERROR(N9/N5,"-") -> -0.57415399
A11: BetVirginia | B11: Actual 26' | C11: ='Forecast Input'!D50 -> 10130.181 | D11: ='Forecast Input'!E50 -> 2170.761 | E11: ='Forecast Input'!F50 -> 4496.6503 | F11: ='Forecast Input'!G50 -> 0 | G11: ='Forecast Input'!H50 -> 0 | H11: ='Forecast Input'!I50 -> 0 | I11: ='Forecast Input'!J50 -> 0 | J11: ='Forecast Input'!K50 -> 0 | ... N11: ='Forecast Input'!O50 -> 0 | O11: =SUM(C11:N11) -> 16797.592
B12: Actual 25' | C12: 8347 | D12: 6119 | E12: 11631 | F12: 11407 | G12: 3718 | H12: 12099 | I12: 4995 | J12: -4308 | K12: -2147 | L12: 1431 | M12: 16201 | N12: 11309 | O12: =SUM(C12:N12) -> 80802
B13: Forecast | C13: ='Forecast Input'!D51 -> 15000 | D13: ='Forecast Input'!E51 -> 12000 | E13: ='Forecast Input'!F51 -> 10000 | F13: ='Forecast Input'!G51 -> 8000 | G13: ='Forecast Input'!H51 -> 3000 | H13: ='Forecast Input'!I51 -> 3000 | I13: ='Forecast Input'!J51 -> 3000 | J13: ='Forecast Input'!K51 -> 5000 | ... N13: ='Forecast Input'!O51 -> 10000 | O13: =SUM(C13:N13) -> 95000
B14: Actual vs Forecast $ | C14: =IF(C11=0,"-",C11-C13) -> -4869.8193 | D14: =IF(D11=0,"-",D11-D13) -> -9829.239 | E14: =IF(E11=0,"-",E11-E13) -> -5503.3497 | F14: =IF(F11=0,"-",F11-F13) -> - | G14: =IF(G11=0,"-",G11-G13) -> - | H14: =IF(H11=0,"-",H11-H13) -> - | I14: =IF(I11=0,"-",I11-I13) -> - | J14: =IF(J11=0,"-",J11-J13) -> - | ... N14: =IF(N11=0,"-",N11-N13) -> -
B15: Actual vs Forecast % | C15: =IFERROR(C14/C11,"-") -> -0.48072383 | D15: =IFERROR(D14/D11,"-") -> -4.5280153 | E15: =IFERROR(E14/E11,"-") -> -1.2238776 | F15: =IFERROR(F14/F11,"-") -> - | G15: =IFERROR(G14/G11,"-") -> - | H15: =IFERROR(H14/H11,"-") -> - | I15: =IFERROR(I14/I11,"-") -> - | J15: =IFERROR(J14/J11,"-") -> - | ... N15: =IFERROR(N14/N11,"-") -> -
B16: Forecast vs PY $ | C16: =IFERROR(C13-C12,"-") -> 6653 | D16: =IFERROR(D13-D12,"-") -> 5881 | E16: =IFERROR(E13-E12,"-") -> -1631 | F16: =IFERROR(F13-F12,"-") -> -3407 | G16: =IFERROR(G13-G12,"-") -> -718 | H16: =IFERROR(H13-H12,"-") -> -9099 | I16: =IFERROR(I13-I12,"-") -> -1995 | J16: =IFERROR(J13-J12,"-") -> 9308 | ... N16: =IFERROR(N13-N12,"-") -> -1309
B17: Forecast vs PY % | C17: =IFERROR(C16/C12,"-") -> 0.79705283 | D17: =IFERROR(D16/D12,"-") -> 0.96110476 | E17: =IFERROR(E16/E12,"-") -> -0.1402287 | F17: =IFERROR(F16/F12,"-") -> -0.29867625 | G17: =IFERROR(G16/G12,"-") -> -0.19311458 | H17: =IFERROR(H16/H12,"-") -> -0.75204562 | I17: =IFERROR(I16/I12,"-") -> -0.3993994 | J17: =IFERROR(J16/J12,"-") -> -2.1606314 | ... N17: =IFERROR(N16/N12,"-") -> -0.11574852
A18: BetKansas | B18: Actual 26' | C18: ='Forecast Input'!D52 -> -9.983818 | D18: ='Forecast Input'!E52 -> 14220.312 | E18: ='Forecast Input'!F52 -> 9727.514 | F18: ='Forecast Input'!G52 -> 0 | G18: ='Forecast Input'!H52 -> 0 | H18: ='Forecast Input'!I52 -> 0 | I18: ='Forecast Input'!J52 -> 0 | J18: ='Forecast Input'!K52 -> 0 | ... N18: ='Forecast Input'!O52 -> 0 | O18: =SUM(C18:N18) -> 23937.842
B19: Actual 25' | C19: 29632 | D19: 38576 | E19: -3469 | F19: 12101 | G19: 7921 | H19: 3012 | I19: 8772 | J19: 8463 | K19: 13515 | L19: 18456 | M19: 39401 | N19: 112948 | O19: =SUM(C19:N19) -> 289328
B20: Forecast | C20: ='Forecast Input'!D53 -> 20000 | D20: ='Forecast Input'!E53 -> 5000 | E20: ='Forecast Input'!F53 -> 5000 | F20: ='Forecast Input'!G53 -> 2000 | G20: ='Forecast Input'!H53 -> 1000 | H20: ='Forecast Input'!I53 -> 1000 | I20: ='Forecast Input'!J53 -> 1000 | J20: ='Forecast Input'!K53 -> 5000 | ... N20: ='Forecast Input'!O53 -> 15000 | O20: =SUM(C20:N20) -> 90000
B21: Actual vs Forecast $ | C21: =IF(C18=0,"-",C18-C20) -> -20009.984 | D21: =IF(D18=0,"-",D18-D20) -> 9220.3123 | E21: =IF(E18=0,"-",E18-E20) -> 4727.514 | F21: =IF(F18=0,"-",F18-F20) -> - | G21: =IF(G18=0,"-",G18-G20) -> - | H21: =IF(H18=0,"-",H18-H20) -> - | I21: =IF(I18=0,"-",I18-I20) -> - | J21: =IF(J18=0,"-",J18-J20) -> - | ... N21: =IF(N18=0,"-",N18-N20) -> -
B22: Actual vs Forecast % | C22: =IFERROR(C21/C18,"-") -> 2004.2416 | D22: =IFERROR(D21/D18,"-") -> 0.64839028 | E22: =IFERROR(E21/E18,"-") -> 0.48599406 | F22: =IFERROR(F21/F18,"-") -> - | G22: =IFERROR(G21/G18,"-") -> - | H22: =IFERROR(H21/H18,"-") -> - | I22: =IFERROR(I21/I18,"-") -> - | J22: =IFERROR(J21/J18,"-") -> - | ... N22: =IFERROR(N21/N18,"-") -> -
B23: Forecast vs PY $ | C23: =IFERROR(C20-C19,"-") -> -9632 | D23: =IFERROR(D20-D19,"-") -> -33576 | E23: =IFERROR(E20-E19,"-") -> 8469 | F23: =IFERROR(F20-F19,"-") -> -10101 | G23: =IFERROR(G20-G19,"-") -> -6921 | H23: =IFERROR(H20-H19,"-") -> -2012 | I23: =IFERROR(I20-I19,"-") -> -7772 | J23: =IFERROR(J20-J19,"-") -> -3463 | ... N23: =IFERROR(N20-N19,"-") -> -97948
B24: Forecast vs PY % | C24: =IFERROR(C23/C19,"-") -> -0.325054 | D24: =IFERROR(D23/D19,"-") -> -0.87038573 | E24: =IFERROR(E23/E19,"-") -> -2.4413376 | F24: =IFERROR(F23/F19,"-") -> -0.8347244 | G24: =IFERROR(G23/G19,"-") -> -0.87375331 | H24: =IFERROR(H23/H19,"-") -> -0.66799469 | I24: =IFERROR(I23/I19,"-") -> -0.88600091 | J24: =IFERROR(J23/J19,"-") -> -0.40919296 | ... N24: =IFERROR(N23/N19,"-") -> -0.86719552
A25: BetOhio | B25: Actual 26' | C25: ='Forecast Input'!D54 -> 4945.2445 | D25: ='Forecast Input'!E54 -> 2880.0743 | E25: ='Forecast Input'!F54 -> 8564.9448 | F25: ='Forecast Input'!G54 -> 0 | G25: ='Forecast Input'!H54 -> 0 | H25: ='Forecast Input'!I54 -> 0 | I25: ='Forecast Input'!J54 -> 0 | J25: ='Forecast Input'!K54 -> 0 | ... N25: ='Forecast Input'!O54 -> 0 | O25: =SUM(C25:N25) -> 16390.264
B26: Actual 25' | C26: 12393 | D26: 13647 | E26: 3500 | F26: 4685 | G26: 10614 | H26: 7328 | I26: 7509 | J26: 16516 | K26: 11589 | L26: 9730 | M26: 4398 | N26: 9978 | O26: =SUM(C26:N26) -> 111887
B27: Forecast | C27: ='Forecast Input'!D55 -> 10000 | D27: ='Forecast Input'!E55 -> 5000 | E27: ='Forecast Input'!F55 -> 5000 | F27: ='Forecast Input'!G55 -> 2000 | G27: ='Forecast Input'!H55 -> 1000 | H27: ='Forecast Input'!I55 -> 1000 | I27: ='Forecast Input'!J55 -> 1000 | J27: ='Forecast Input'!K55 -> 3000 | ... N27: ='Forecast Input'!O55 -> 10000 | O27: =SUM(C27:N27) -> 64000
B28: Actual vs Forecast $ | C28: =IF(C25=0,"-",C25-C27) -> -5054.7555 | D28: =IF(D25=0,"-",D25-D27) -> -2119.9257 | E28: =IF(E25=0,"-",E25-E27) -> 3564.9448 | F28: =IF(F25=0,"-",F25-F27) -> - | G28: =IF(G25=0,"-",G25-G27) -> - | H28: =IF(H25=0,"-",H25-H27) -> - | I28: =IF(I25=0,"-",I25-I27) -> - | J28: =IF(J25=0,"-",J25-J27) -> - | ... N28: =IF(N25=0,"-",N25-N27) -> -
B29: =IFERROR(IF(Local!C4=0,Local!C4,Local!C6),Local!C6) -> 20000 | C29: =IFERROR(C28/C25,"-") -> -1.0221447 | D29: =IFERROR(D28/D25,"-") -> -0.73606635 | E29: =IFERROR(E28/E25,"-") -> 0.41622507 | F29: =IFERROR(F28/F25,"-") -> - | G29: =IFERROR(G28/G25,"-") -> - | H29: =IFERROR(H28/H25,"-") -> - | I29: =IFERROR(I28/I25,"-") -> - | J29: =IFERROR(J28/J25,"-") -> - | ... N29: =IFERROR(N28/N25,"-") -> -
B30: Forecast vs PY $ | C30: =IFERROR(C27-C26,"-") -> -2393 | D30: =IFERROR(D27-D26,"-") -> -8647 | E30: =IFERROR(E27-E26,"-") -> 1500 | F30: =IFERROR(F27-F26,"-") -> -2685 | G30: =IFERROR(G27-G26,"-") -> -9614 | H30: =IFERROR(H27-H26,"-") -> -6328 | I30: =IFERROR(I27-I26,"-") -> -6509 | J30: =IFERROR(J27-J26,"-") -> -13516 | ... N30: =IFERROR(N27-N26,"-") -> 22
B31: Forecast vs PY % | C31: =IFERROR(C30/C26,"-") -> -0.19309288 | D31: =IFERROR(D30/D26,"-") -> -0.63361911 | E31: =IFERROR(E30/E26,"-") -> 0.42857143 | F31: =IFERROR(F30/F26,"-") -> -0.57310566 | G31: =IFERROR(G30/G26,"-") -> -0.90578481 | H31: =IFERROR(H30/H26,"-") -> -0.86353712 | I31: =IFERROR(I30/I26,"-") -> -0.86682647 | J31: =IFERROR(J30/J26,"-") -> -0.81835796 | ... N31: =IFERROR(N30/N26,"-") -> 0.0022048507
A32: BetKentucky | B32: Actual 26' | C32: ='Forecast Input'!D56 -> 2176.933 | D32: ='Forecast Input'!E56 -> 1425.0822 | E32: ='Forecast Input'!F56 -> 3628.2569 | F32: ='Forecast Input'!G56 -> 0 | G32: ='Forecast Input'!H56 -> 0 | H32: ='Forecast Input'!I56 -> 0 | I32: ='Forecast Input'!J56 -> 0 | J32: ='Forecast Input'!K56 -> 0 | ... N32: ='Forecast Input'!O56 -> 0 | O32: =SUM(C32:N32) -> 7230.272
B33: Actual 25' | C33: 4304 | D33: 10330 | E33: 5596 | F33: 5224 | G33: 9752 | H33: 1949 | I33: 7827 | J33: 3555 | K33: 5693 | L33: 1686 | M33: 19135 | N33: 10698 | O33: =SUM(C33:N33) -> 85749
B34: Forecast | C34: ='Forecast Input'!D57 -> 5000 | D34: ='Forecast Input'!E57 -> 3000 | E34: ='Forecast Input'!F57 -> 3000 | F34: ='Forecast Input'!G57 -> 2000 | G34: ='Forecast Input'!H57 -> 1000 | H34: ='Forecast Input'!I57 -> 1000 | I34: ='Forecast Input'!J57 -> 1000 | J34: ='Forecast Input'!K57 -> 3000 | ... N34: ='Forecast Input'!O57 -> 5000 | O34: =SUM(C34:N34) -> 37000
B35: Actual vs Forecast $ | C35: =IF(C32=0,"-",C32-C34) -> -2823.067 | D35: =IF(D32=0,"-",D32-D34) -> -1574.9178 | E35: =IF(E32=0,"-",E32-E34) -> 628.25686 | F35: =IF(F32=0,"-",F32-F34) -> - | G35: =IF(G32=0,"-",G32-G34) -> - | H35: =IF(H32=0,"-",H32-H34) -> - | I35: =IF(I32=0,"-",I32-I34) -> - | J35: =IF(J32=0,"-",J32-J34) -> - | ... N35: =IF(N32=0,"-",N32-N34) -> -
B36: Actual vs Forecast % | C36: =IFERROR(C35/C32,"-") -> -1.2968093 | D36: =IFERROR(D35/D32,"-") -> -1.1051418 | E36: =IFERROR(E35/E32,"-") -> 0.17315666 | F36: =IFERROR(F35/F32,"-") -> - | G36: =IFERROR(G35/G32,"-") -> - | H36: =IFERROR(H35/H32,"-") -> - | I36: =IFERROR(I35/I32,"-") -> - | J36: =IFERROR(J35/J32,"-") -> - | ... N36: =IFERROR(N35/N32,"-") -> -
B37: Forecast vs PY $ | C37: =IFERROR(C34-C33,"-") -> 696 | D37: =IFERROR(D34-D33,"-") -> -7330 | E37: =IFERROR(E34-E33,"-") -> -2596 | F37: =IFERROR(F34-F33,"-") -> -3224 | G37: =IFERROR(G34-G33,"-") -> -8752 | H37: =IFERROR(H34-H33,"-") -> -949 | I37: =IFERROR(I34-I33,"-") -> -6827 | J37: =IFERROR(J34-J33,"-") -> -555 | ... N37: =IFERROR(N34-N33,"-") -> -5698
B38: Forecast vs PY % | C38: =IFERROR(C37/C33,"-") -> 0.16171004 | D38: =IFERROR(D37/D33,"-") -> -0.70958374 | E38: =IFERROR(E37/E33,"-") -> -0.46390279 | F38: =IFERROR(F37/F33,"-") -> -0.61715161 | G38: =IFERROR(G37/G33,"-") -> -0.89745693 | H38: =IFERROR(H37/H33,"-") -> -0.48691637 | I38: =IFERROR(I37/I33,"-") -> -0.87223713 | J38: =IFERROR(J37/J33,"-") -> -0.15611814 | ... N38: =IFERROR(N37/N33,"-") -> -0.53262292
A39: BetMassachusetts | B39: Actual 26' | C39: ='Forecast Input'!D58 -> 7974.6974 | D39: ='Forecast Input'!E58 -> 6956.5644 | E39: ='Forecast Input'!F58 -> 2045.0664 | F39: ='Forecast Input'!G58 -> 0 | G39: ='Forecast Input'!H58 -> 0 | H39: ='Forecast Input'!I58 -> 0 | I39: ='Forecast Input'!J58 -> 0 | J39: ='Forecast Input'!K58 -> 0 | ... N39: ='Forecast Input'!O58 -> 0 | O39: =SUM(C39:N39) -> 16976.328
B40: Actual 25' | C40: 9949 | D40: 12310 | E40: 16264 | F40: 9129 | G40: 13298 | H40: 9341 | I40: 7608 | J40: 8090 | K40: 15495 | L40: 7050 | M40: 4883 | N40: 7909 | O40: =SUM(C40:N40) -> 121326
B41: Forecast | C41: ='Forecast Input'!D59 -> 15000 | D41: ='Forecast Input'!E59 -> 12000 | E41: ='Forecast Input'!F59 -> 10000 | F41: ='Forecast Input'!G59 -> 8000 | G41: ='Forecast Input'!H59 -> 3000 | H41: ='Forecast Input'!I59 -> 3000 | I41: ='Forecast Input'!J59 -> 3000 | J41: ='Forecast Input'!K59 -> 5000 | ... N41: ='Forecast Input'!O59 -> 10000 | O41: =SUM(C41:N41) -> 95000
B42: Actual vs Forecast $ | C42: =IF(C39=0,"-",C39-C41) -> -7025.3026 | D42: =IF(D39=0,"-",D39-D41) -> -5043.4356 | E42: =IF(E39=0,"-",E39-E41) -> -7954.9336 | F42: =IF(F39=0,"-",F39-F41) -> - | G42: =IF(G39=0,"-",G39-G41) -> - | H42: =IF(H39=0,"-",H39-H41) -> - | I42: =IF(I39=0,"-",I39-I41) -> - | J42: =IF(J39=0,"-",J39-J41) -> - | ... N42: =IF(N39=0,"-",N39-N41) -> -
B43: Actual vs Forecast % | C43: =IFERROR(C42/C39,"-") -> -0.88094911 | D43: =IFERROR(D42/D39,"-") -> -0.72498943 | E43: =IFERROR(E42/E39,"-") -> -3.8898167 | F43: =IFERROR(F42/F39,"-") -> - | G43: =IFERROR(G42/G39,"-") -> - | H43: =IFERROR(H42/H39,"-") -> - | I43: =IFERROR(I42/I39,"-") -> - | J43: =IFERROR(J42/J39,"-") -> - | ... N43: =IFERROR(N42/N39,"-") -> -
B44: Forecast vs PY $ | C44: =IFERROR(C41-C40,"-") -> 5051 | D44: =IFERROR(D41-D40,"-") -> -310 | E44: =IFERROR(E41-E40,"-") -> -6264 | F44: =IFERROR(F41-F40,"-") -> -1129 | G44: =IFERROR(G41-G40,"-") -> -10298 | H44: =IFERROR(H41-H40,"-") -> -6341 | I44: =IFERROR(I41-I40,"-") -> -4608 | J44: =IFERROR(J41-J40,"-") -> -3090 | ... N44: =IFERROR(N41-N40,"-") -> 2091
B45: Forecast vs PY % | C45: =IFERROR(C44/C40,"-") -> 0.50768921 | D45: =IFERROR(D44/D40,"-") -> -0.025182778 | E45: =IFERROR(E44/E40,"-") -> -0.38514511 | F45: =IFERROR(F44/F40,"-") -> -0.12367182 | G45: =IFERROR(G44/G40,"-") -> -0.77440217 | H45: =IFERROR(H44/H40,"-") -> -0.67883524 | I45: =IFERROR(I44/I40,"-") -> -0.60567823 | J45: =IFERROR(J44/J40,"-") -> -0.38195303 | ... N45: =IFERROR(N44/N40,"-") -> 0.26438235
A46: BetTennessee | B46: Actual 26' | C46: ='Forecast Input'!D60 -> 1911.806 | D46: ='Forecast Input'!E60 -> -363.29582 | E46: ='Forecast Input'!F60 -> 2161.5845 | F46: ='Forecast Input'!G60 -> 0 | G46: ='Forecast Input'!H60 -> 0 | H46: ='Forecast Input'!I60 -> 0 | I46: ='Forecast Input'!J60 -> 0 | J46: ='Forecast Input'!K60 -> 0 | ... N46: ='Forecast Input'!O60 -> 0 | O46: =SUM(C46:N46) -> 3710.0947
B47: Actual 25' | C47: 6638 | D47: 2241 | E47: 2815 | F47: 3024 | G47: 1989 | H47: 3108 | I47: 1121 | J47: 1128 | K47: 4372 | L47: 3778 | M47: 1859 | N47: 1994 | O47: =SUM(C47:N47) -> 34067
B48: Forecast | C48: ='Forecast Input'!D61 -> 5000 | D48: ='Forecast Input'!E61 -> 3000 | E48: ='Forecast Input'!F61 -> 3000 | F48: ='Forecast Input'!G61 -> 2000 | G48: ='Forecast Input'!H61 -> 1000 | H48: ='Forecast Input'!I61 -> 1000 | I48: ='Forecast Input'!J61 -> 1000 | J48: ='Forecast Input'!K61 -> 3000 | ... N48: ='Forecast Input'!O61 -> 5000 | O48: =SUM(C48:N48) -> 37000
B49: Actual vs Forecast $ | C49: =IF(C46=0,"-",C46-C48) -> -3088.194 | D49: =IF(D46=0,"-",D46-D48) -> -3363.2958 | E49: =IF(E46=0,"-",E46-E48) -> -838.4155 | F49: =IF(F46=0,"-",F46-F48) -> - | G49: =IF(G46=0,"-",G46-G48) -> - | H49: =IF(H46=0,"-",H46-H48) -> - | I49: =IF(I46=0,"-",I46-I48) -> - | J49: =IF(J46=0,"-",J46-J48) -> - | ... N49: =IF(N46=0,"-",N46-N48) -> -
B50: Actual vs Forecast % | C50: =IFERROR(C49/C46,"-") -> -1.6153281 | D50: =IFERROR(D49/D46,"-") -> 9.2577333 | E50: =IFERROR(E49/E46,"-") -> -0.3878708 | F50: =IFERROR(F49/F46,"-") -> - | G50: =IFERROR(G49/G46,"-") -> - | H50: =IFERROR(H49/H46,"-") -> - | I50: =IFERROR(I49/I46,"-") -> - | J50: =IFERROR(J49/J46,"-") -> - | ... N50: =IFERROR(N49/N46,"-") -> -
B51: Forecast vs PY $ | C51: =IFERROR(C48-C47,"-") -> -1638 | D51: =IFERROR(D48-D47,"-") -> 759 | E51: =IFERROR(E48-E47,"-") -> 185 | F51: =IFERROR(F48-F47,"-") -> -1024 | G51: =IFERROR(G48-G47,"-") -> -989 | H51: =IFERROR(H48-H47,"-") -> -2108 | I51: =IFERROR(I48-I47,"-") -> -121 | J51: =IFERROR(J48-J47,"-") -> 1872 | ... N51: =IFERROR(N48-N47,"-") -> 3006
B52: Forecast vs PY % | C52: =IFERROR(C51/C47,"-") -> -0.24676107 | D52: =IFERROR(D51/D47,"-") -> 0.33868809 | E52: =IFERROR(E51/E47,"-") -> 0.065719361 | F52: =IFERROR(F51/F47,"-") -> -0.33862434 | G52: =IFERROR(G51/G47,"-") -> -0.49723479 | H52: =IFERROR(H51/H47,"-") -> -0.67824968 | I52: =IFERROR(I51/I47,"-") -> -0.10793934 | J52: =IFERROR(J51/J47,"-") -> 1.6595745 | ... N52: =IFERROR(N51/N47,"-") -> 1.5075226
A53: LouisianaBets | B53: Actual 26' | C53: ='Forecast Input'!D62 -> -376.13058 | D53: ='Forecast Input'!E62 -> -1212.1453 | E53: ='Forecast Input'!F62 -> 1384.8506 | F53: ='Forecast Input'!G62 -> 0 | G53: ='Forecast Input'!H62 -> 0 | H53: ='Forecast Input'!I62 -> 0 | I53: ='Forecast Input'!J62 -> 0 | J53: ='Forecast Input'!K62 -> 0 | ... N53: ='Forecast Input'!O62 -> 0 | O53: =SUM(C53:N53) -> -203.42531
B54: Actual 25' | C54: 1385 | D54: 3496 | E54: 4130 | F54: 257 | G54: 3319 | H54: 2293 | I54: 3306 | J54: 1352 | K54: 3128 | L54: 3018 | M54: 2816 | N54: 1098 | O54: =SUM(C54:N54) -> 29598
B55: Forecast | C55: ='Forecast Input'!D63 -> 5000 | D55: ='Forecast Input'!E63 -> 1000 | E55: ='Forecast Input'!F63 -> 1000 | F55: ='Forecast Input'!G63 -> 1000 | G55: ='Forecast Input'!H63 -> 1000 | H55: ='Forecast Input'!I63 -> 1000 | I55: ='Forecast Input'!J63 -> 1000 | J55: ='Forecast Input'!K63 -> 1000 | ... N55: ='Forecast Input'!O63 -> 1000 | O55: =SUM(C55:N55) -> 16000
B56: Actual vs Forecast $ | C56: =IF(C53=0,"-",C53-C55) -> -5376.1306 | D56: =IF(D53=0,"-",D53-D55) -> -2212.1453 | E56: =IF(E53=0,"-",E53-E55) -> 384.85057 | F56: =IF(F53=0,"-",F53-F55) -> - | G56: =IF(G53=0,"-",G53-G55) -> - | H56: =IF(H53=0,"-",H53-H55) -> - | I56: =IF(I53=0,"-",I53-I55) -> - | J56: =IF(J53=0,"-",J53-J55) -> - | ... N56: =IF(N53=0,"-",N53-N55) -> -
B57: Actual vs Forecast % | C57: =IFERROR(C56/C53,"-") -> 14.293256 | D57: =IFERROR(D56/D53,"-") -> 1.8249836 | E57: =IFERROR(E56/E53,"-") -> 0.27790043 | F57: =IFERROR(F56/F53,"-") -> - | G57: =IFERROR(G56/G53,"-") -> - | H57: =IFERROR(H56/H53,"-") -> - | I57: =IFERROR(I56/I53,"-") -> - | J57: =IFERROR(J56/J53,"-") -> - | ... N57: =IFERROR(N56/N53,"-") -> -
B58: Forecast vs PY $ | C58: =IFERROR(C55-C54,"-") -> 3615 | D58: =IFERROR(D55-D54,"-") -> -2496 | E58: =IFERROR(E55-E54,"-") -> -3130 | F58: =IFERROR(F55-F54,"-") -> 743 | G58: =IFERROR(G55-G54,"-") -> -2319 | H58: =IFERROR(H55-H54,"-") -> -1293 | I58: =IFERROR(I55-I54,"-") -> -2306 | J58: =IFERROR(J55-J54,"-") -> -352 | ... N58: =IFERROR(N55-N54,"-") -> -98
B59: Forecast vs PY % | C59: =IFERROR(C58/C54,"-") -> 2.6101083 | D59: =IFERROR(D58/D54,"-") -> -0.71395881 | E59: =IFERROR(E58/E54,"-") -> -0.75786925 | F59: =IFERROR(F58/F54,"-") -> 2.8910506 | G59: =IFERROR(G58/G54,"-") -> -0.69870443 | H59: =IFERROR(H58/H54,"-") -> -0.5638901 | I59: =IFERROR(I58/I54,"-") -> -0.69751966 | J59: =IFERROR(J58/J54,"-") -> -0.26035503 | ... N59: =IFERROR(N58/N54,"-") -> -0.089253188
A60: BetColorado | B60: Actual 26' | C60: ='Forecast Input'!D64 -> 1756.431 | D60: ='Forecast Input'!E64 -> 7497.8106 | E60: ='Forecast Input'!F64 -> 1043.8384 | F60: ='Forecast Input'!G64 -> 0 | G60: ='Forecast Input'!H64 -> 0 | H60: ='Forecast Input'!I64 -> 0 | I60: ='Forecast Input'!J64 -> 0 | J60: ='Forecast Input'!K64 -> 0 | ... N60: ='Forecast Input'!O64 -> 0 | O60: =SUM(C60:N60) -> 10298.08
B61: Actual 25' | C61: 13281 | D61: 14120 | E61: 6051 | F61: 6371 | G61: 4117 | H61: 4549 | I61: 3404 | J61: 4967 | K61: 12787 | L61: 7690 | M61: 6492 | N61: 596 | O61: =SUM(C61:N61) -> 84425
B62: Forecast | C62: ='Forecast Input'!D65 -> 5000 | D62: ='Forecast Input'!E65 -> 3000 | E62: ='Forecast Input'!F65 -> 3000 | F62: ='Forecast Input'!G65 -> 2000 | G62: ='Forecast Input'!H65 -> 1000 | H62: ='Forecast Input'!I65 -> 1000 | I62: ='Forecast Input'!J65 -> 1000 | J62: ='Forecast Input'!K65 -> 3000 | ... N62: ='Forecast Input'!O65 -> 5000 | O62: =SUM(C62:N62) -> 37000
B63: Actual vs Forecast $ | C63: =IF(C60=0,"-",C60-C62) -> -3243.569 | D63: =IF(D60=0,"-",D60-D62) -> 4497.8106 | E63: =IF(E60=0,"-",E60-E62) -> -1956.1616 | F63: =IF(F60=0,"-",F60-F62) -> - | G63: =IF(G60=0,"-",G60-G62) -> - | H63: =IF(H60=0,"-",H60-H62) -> - | I63: =IF(I60=0,"-",I60-I62) -> - | J63: =IF(J60=0,"-",J60-J62) -> - | ... N63: =IF(N60=0,"-",N60-N62) -> -
B64: Actual vs Forecast % | C64: =IFERROR(C63/C60,"-") -> -1.8466817 | D64: =IFERROR(D63/D60,"-") -> 0.5998832 | E64: =IFERROR(E63/E60,"-") -> -1.8740081 | F64: =IFERROR(F63/F60,"-") -> - | G64: =IFERROR(G63/G60,"-") -> - | H64: =IFERROR(H63/H60,"-") -> - | I64: =IFERROR(I63/I60,"-") -> - | J64: =IFERROR(J63/J60,"-") -> - | ... N64: =IFERROR(N63/N60,"-") -> -
B65: Forecast vs PY $ | C65: =IFERROR(C62-C61,"-") -> -8281 | D65: =IFERROR(D62-D61,"-") -> -11120 | E65: =IFERROR(E62-E61,"-") -> -3051 | F65: =IFERROR(F62-F61,"-") -> -4371 | G65: =IFERROR(G62-G61,"-") -> -3117 | H65: =IFERROR(H62-H61,"-") -> -3549 | I65: =IFERROR(I62-I61,"-") -> -2404 | J65: =IFERROR(J62-J61,"-") -> -1967 | ... N65: =IFERROR(N62-N61,"-") -> 4404
B66: Forecast vs PY % | C66: =IFERROR(C65/C61,"-") -> -0.62352233 | D66: =IFERROR(D65/D61,"-") -> -0.78753541 | E66: =IFERROR(E65/E61,"-") -> -0.50421418 | F66: =IFERROR(F65/F61,"-") -> -0.68607754 | G66: =IFERROR(G65/G61,"-") -> -0.75710469 | H66: =IFERROR(H65/H61,"-") -> -0.78017147 | I66: =IFERROR(I65/I61,"-") -> -0.70622797 | J66: =IFERROR(J65/J61,"-") -> -0.39601369 | ... N66: =IFERROR(N65/N61,"-") -> 7.3892617
A67: IndianaBets | B67: Actual 26' | C67: ='Forecast Input'!D66 -> 2.894005 | D67: ='Forecast Input'!E66 -> 42.601367 | E67: ='Forecast Input'!F66 -> 39.869312 | F67: ='Forecast Input'!G66 -> 0 | G67: ='Forecast Input'!H66 -> 0 | H67: ='Forecast Input'!I66 -> 0 | I67: ='Forecast Input'!J66 -> 0 | J67: ='Forecast Input'!K66 -> 0 | ... N67: ='Forecast Input'!O66 -> 0 | O67: =SUM(C67:N67) -> 85.364684
B68: Actual 25' | G68: 1 | I68: 0 | J68: 15 | K68: 305 | L68: 4 | M68: -24 | N68: -370 | O68: =SUM(C68:N68) -> -69
B69: Forecast | C69: ='Forecast Input'!D67 -> 0 | D69: ='Forecast Input'!E67 -> 0 | E69: ='Forecast Input'!F67 -> 0 | F69: ='Forecast Input'!G67 -> 0 | G69: ='Forecast Input'!H67 -> 0 | H69: ='Forecast Input'!I67 -> 0 | I69: ='Forecast Input'!J67 -> 0 | J69: ='Forecast Input'!K67 -> 0 | ... N69: ='Forecast Input'!O67 -> 0 | O69: =SUM(C69:N69) -> 0
B70: Actual vs Forecast $ | C70: =IF(C67=0,"-",C67-C69) -> 2.894005 | D70: =IF(D67=0,"-",D67-D69) -> 42.601367 | E70: =IF(E67=0,"-",E67-E69) -> 39.869312 | F70: =IF(F67=0,"-",F67-F69) -> - | G70: =IF(G67=0,"-",G67-G69) -> - | H70: =IF(H67=0,"-",H67-H69) -> - | I70: =IF(I67=0,"-",I67-I69) -> - | J70: =IF(J67=0,"-",J67-J69) -> - | ... N70: =IF(N67=0,"-",N67-N69) -> -
B71: Actual vs Forecast % | C71: =IFERROR(C70/C67,"-") -> 1 | D71: =IFERROR(D70/D67,"-") -> 1 | E71: =IFERROR(E70/E67,"-") -> 1 | F71: =IFERROR(F70/F67,"-") -> - | G71: =IFERROR(G70/G67,"-") -> - | H71: =IFERROR(H70/H67,"-") -> - | I71: =IFERROR(I70/I67,"-") -> - | J71: =IFERROR(J70/J67,"-") -> - | ... N71: =IFERROR(N70/N67,"-") -> -
B72: Forecast vs PY $ | C72: =IFERROR(C69-C68,"-") -> 0 | D72: =IFERROR(D69-D68,"-") -> 0 | E72: =IFERROR(E69-E68,"-") -> 0 | F72: =IFERROR(F69-F68,"-") -> 0 | G72: =IFERROR(G69-G68,"-") -> -1 | H72: =IFERROR(H69-H68,"-") -> 0 | I72: =IFERROR(I69-I68,"-") -> 0 | J72: =IFERROR(J69-J68,"-") -> -15 | ... N72: =IFERROR(N69-N68,"-") -> 370
B73: Forecast vs PY % | C73: =IFERROR(C72/C68,"-") -> - | D73: =IFERROR(D72/D68,"-") -> - | E73: =IFERROR(E72/E68,"-") -> - | F73: =IFERROR(F72/F68,"-") -> - | G73: =IFERROR(G72/G68,"-") -> -1 | H73: =IFERROR(H72/H68,"-") -> - | I73: =IFERROR(I72/I68,"-") -> - | J73: =IFERROR(J72/J68,"-") -> -1 | ... N73: =IFERROR(N72/N68,"-") -> -1
A74: IowaBets | B74: Actual 26' | C74: ='Forecast Input'!D68 -> 84.286657 | D74: ='Forecast Input'!E68 -> 268.81932 | E74: ='Forecast Input'!F68 -> -18.937923 | F74: ='Forecast Input'!G68 -> 0 | G74: ='Forecast Input'!H68 -> 0 | H74: ='Forecast Input'!I68 -> 0 | I74: ='Forecast Input'!J68 -> 0 | J74: ='Forecast Input'!K68 -> 0 | ... N74: ='Forecast Input'!O68 -> 0 | O74: =SUM(C74:N74) -> 334.16806
B75: Actual 25' | M75: 5 | N75: 0 | O75: =SUM(C75:N75) -> 5
B76: Forecast | C76: ='Forecast Input'!D69 -> 100 | D76: ='Forecast Input'!E69 -> 100 | E76: ='Forecast Input'!F69 -> 100 | F76: ='Forecast Input'!G69 -> 100 | G76: ='Forecast Input'!H69 -> 100 | H76: ='Forecast Input'!I69 -> 100 | I76: ='Forecast Input'!J69 -> 100 | J76: ='Forecast Input'!K69 -> 100 | ... N76: ='Forecast Input'!O69 -> 100 | O76: =SUM(C76:N76) -> 1200
B77: Actual vs Forecast $ | C77: =IF(C74=0,"-",C74-C76) -> -15.713343 | D77: =IF(D74=0,"-",D74-D76) -> 168.81932 | E77: =IF(E74=0,"-",E74-E76) -> -118.93792 | F77: =IF(F74=0,"-",F74-F76) -> - | G77: =IF(G74=0,"-",G74-G76) -> - | H77: =IF(H74=0,"-",H74-H76) -> - | I77: =IF(I74=0,"-",I74-I76) -> - | J77: =IF(J74=0,"-",J74-J76) -> - | ... N77: =IF(N74=0,"-",N74-N76) -> -
B78: Actual vs Forecast % | C78: =IFERROR(C77/C74,"-") -> -0.18642741 | D78: =IFERROR(D77/D74,"-") -> 0.62800293 | E78: =IFERROR(E77/E74,"-") -> 6.2804101 | F78: =IFERROR(F77/F74,"-") -> - | G78: =IFERROR(G77/G74,"-") -> - | H78: =IFERROR(H77/H74,"-") -> - | I78: =IFERROR(I77/I74,"-") -> - | J78: =IFERROR(J77/J74,"-") -> - | ... N78: =IFERROR(N77/N74,"-") -> -
B79: Forecast vs PY $ | C79: =IFERROR(C76-C75,"-") -> 100 | D79: =IFERROR(D76-D75,"-") -> 100 | E79: =IFERROR(E76-E75,"-") -> 100 | F79: =IFERROR(F76-F75,"-") -> 100 | G79: =IFERROR(G76-G75,"-") -> 100 | H79: =IFERROR(H76-H75,"-") -> 100 | I79: =IFERROR(I76-I75,"-") -> 100 | J79: =IFERROR(J76-J75,"-") -> 100 | ... N79: =IFERROR(N76-N75,"-") -> 100
B80: Forecast vs PY % | C80: =IFERROR(C79/C75,"-") -> - | D80: =IFERROR(D79/D75,"-") -> - | E80: =IFERROR(E79/E75,"-") -> - | F80: =IFERROR(F79/F75,"-") -> - | G80: =IFERROR(G79/G75,"-") -> - | H80: =IFERROR(H79/H75,"-") -> - | I80: =IFERROR(I79/I75,"-") -> - | J80: =IFERROR(J79/J75,"-") -> - | ... N80: =IFERROR(N79/N75,"-") -> -
A81: EmpireStakes | B81: Actual 26' | C81: ='Forecast Input'!D70 -> 353.48925 | D81: ='Forecast Input'!E70 -> 275.81462 | E81: ='Forecast Input'!F70 -> 355.8336 | F81: ='Forecast Input'!G70 -> 0 | G81: ='Forecast Input'!H70 -> 0 | H81: ='Forecast Input'!I70 -> 0 | I81: ='Forecast Input'!J70 -> 0 | J81: ='Forecast Input'!K70 -> 0 | ... N81: ='Forecast Input'!O70 -> 0 | O81: =SUM(C81:N81) -> 985.13747
B82: Actual 25' | C82: 375 | D82: 200 | E82: 652 | F82: 1838 | G82: 633 | H82: 594 | I82: 675 | J82: 1396 | K82: 520 | L82: 300 | M82: 425 | N82: -324 | O82: =SUM(C82:N82) -> 7284
B83: Forecast | C83: ='Forecast Input'!D71 -> 500 | D83: ='Forecast Input'!E71 -> 500 | E83: ='Forecast Input'!F71 -> 500 | F83: ='Forecast Input'!G71 -> 500 | G83: ='Forecast Input'!H71 -> 500 | H83: ='Forecast Input'!I71 -> 500 | I83: ='Forecast Input'!J71 -> 500 | J83: ='Forecast Input'!K71 -> 500 | ... N83: ='Forecast Input'!O71 -> 500 | O83: =SUM(C83:N83) -> 6000
B84: Actual vs Forecast $ | C84: =IF(C81=0,"-",C81-C83) -> -146.51075 | D84: =IF(D81=0,"-",D81-D83) -> -224.18538 | E84: =IF(E81=0,"-",E81-E83) -> -144.1664 | F84: =IF(F81=0,"-",F81-F83) -> - | G84: =IF(G81=0,"-",G81-G83) -> - | H84: =IF(H81=0,"-",H81-H83) -> - | I84: =IF(I81=0,"-",I81-I83) -> - | J84: =IF(J81=0,"-",J81-J83) -> - | ... N84: =IF(N81=0,"-",N81-N83) -> -
B85: Actual vs Forecast % | C85: =IFERROR(C84/C81,"-") -> -0.41447018 | D85: =IFERROR(D84/D81,"-") -> -0.81281181 | E85: =IFERROR(E84/E81,"-") -> -0.40515115 | F85: =IFERROR(F84/F81,"-") -> - | G85: =IFERROR(G84/G81,"-") -> - | H85: =IFERROR(H84/H81,"-") -> - | I85: =IFERROR(I84/I81,"-") -> - | J85: =IFERROR(J84/J81,"-") -> - | ... N85: =IFERROR(N84/N81,"-") -> -
B86: Forecast vs PY $ | C86: =IFERROR(C83-C82,"-") -> 125 | D86: =IFERROR(D83-D82,"-") -> 300 | E86: =IFERROR(E83-E82,"-") -> -152 | F86: =IFERROR(F83-F82,"-") -> -1338 | G86: =IFERROR(G83-G82,"-") -> -133 | H86: =IFERROR(H83-H82,"-") -> -94 | I86: =IFERROR(I83-I82,"-") -> -175 | J86: =IFERROR(J83-J82,"-") -> -896 | ... N86: =IFERROR(N83-N82,"-") -> 824
B87: Forecast vs PY % | C87: =IFERROR(C86/C82,"-") -> 0.33333333 | D87: =IFERROR(D86/D82,"-") -> 1.5 | E87: =IFERROR(E86/E82,"-") -> -0.23312883 | F87: =IFERROR(F86/F82,"-") -> -0.72796518 | G87: =IFERROR(G86/G82,"-") -> -0.21011058 | H87: =IFERROR(H86/H82,"-") -> -0.15824916 | I87: =IFERROR(I86/I82,"-") -> -0.25925926 | J87: =IFERROR(J86/J82,"-") -> -0.64183381 | ... N87: =IFERROR(N86/N82,"-") -> -2.5432099
A88: IllinoisBet | B88: Actual 26' | C88: ='Forecast Input'!D72 -> 2255.8122 | D88: ='Forecast Input'!E72 -> 2409.3806 | E88: ='Forecast Input'!F72 -> 577.10828 | F88: ='Forecast Input'!G72 -> 0 | G88: ='Forecast Input'!H72 -> 0 | H88: ='Forecast Input'!I72 -> 0 | I88: ='Forecast Input'!J72 -> 0 | J88: ='Forecast Input'!K72 -> 0 | ... N88: ='Forecast Input'!O72 -> 0 | O88: =SUM(C88:N88) -> 5242.3011
B89: Actual 25' | C89: 2084 | D89: 801 | E89: 476 | F89: 298 | G89: 766 | H89: 344 | I89: 900 | J89: 1217 | K89: 3448 | L89: 1275 | M89: 851 | N89: 299 | O89: =SUM(C89:N89) -> 12759
B90: Forecast | C90: ='Forecast Input'!D73 -> 1000 | D90: ='Forecast Input'!E73 -> 1000 | E90: ='Forecast Input'!F73 -> 1000 | F90: ='Forecast Input'!G73 -> 1000 | G90: ='Forecast Input'!H73 -> 1000 | H90: ='Forecast Input'!I73 -> 1000 | I90: ='Forecast Input'!J73 -> 1000 | J90: ='Forecast Input'!K73 -> 1000 | ... N90: ='Forecast Input'!O73 -> 1000 | O90: =SUM(C90:N90) -> 12000
B91: Actual vs Forecast $ | C91: =IF(C88=0,"-",C88-C90) -> 1255.8122 | D91: =IF(D88=0,"-",D88-D90) -> 1409.3806 | E91: =IF(E88=0,"-",E88-E90) -> -422.89172 | F91: =IF(F88=0,"-",F88-F90) -> - | G91: =IF(G88=0,"-",G88-G90) -> - | H91: =IF(H88=0,"-",H88-H90) -> - | I91: =IF(I88=0,"-",I88-I90) -> - | J91: =IF(J88=0,"-",J88-J90) -> - | ... N91: =IF(N88=0,"-",N88-N90) -> -
B92: Actual vs Forecast % | C92: =IFERROR(C91/C88,"-") -> 0.55670068 | D92: =IFERROR(D91/D88,"-") -> 0.58495557 | E92: =IFERROR(E91/E88,"-") -> -0.73277707 | F92: =IFERROR(F91/F88,"-") -> - | G92: =IFERROR(G91/G88,"-") -> - | H92: =IFERROR(H91/H88,"-") -> - | I92: =IFERROR(I91/I88,"-") -> - | J92: =IFERROR(J91/J88,"-") -> - | ... N92: =IFERROR(N91/N88,"-") -> -
B93: Forecast vs PY $ | C93: =IFERROR(C90-C89,"-") -> -1084 | D93: =IFERROR(D90-D89,"-") -> 199 | E93: =IFERROR(E90-E89,"-") -> 524 | F93: =IFERROR(F90-F89,"-") -> 702 | G93: =IFERROR(G90-G89,"-") -> 234 | H93: =IFERROR(H90-H89,"-") -> 656 | I93: =IFERROR(I90-I89,"-") -> 100 | J93: =IFERROR(J90-J89,"-") -> -217 | ... N93: =IFERROR(N90-N89,"-") -> 701
B94: Forecast vs PY % | C94: =IFERROR(C93/C89,"-") -> -0.52015355 | D94: =IFERROR(D93/D89,"-") -> 0.24843945 | E94: =IFERROR(E93/E89,"-") -> 1.1008403 | F94: =IFERROR(F93/F89,"-") -> 2.3557047 | G94: =IFERROR(G93/G89,"-") -> 0.30548303 | H94: =IFERROR(H93/H89,"-") -> 1.9069767 | I94: =IFERROR(I93/I89,"-") -> 0.11111111 | J94: =IFERROR(J93/J89,"-") -> -0.17830731 | ... N94: =IFERROR(N93/N89,"-") -> 2.3444816
A95: BetMaryland | B95: Actual 26' | C95: ='Forecast Input'!D74 -> 4598.3043 | D95: ='Forecast Input'!E74 -> 1835.8361 | E95: ='Forecast Input'!F74 -> 2995.1123 | F95: ='Forecast Input'!G74 -> 0 | G95: ='Forecast Input'!H74 -> 0 | H95: ='Forecast Input'!I74 -> 0 | I95: ='Forecast Input'!J74 -> 0 | J95: ='Forecast Input'!K74 -> 0 | ... N95: ='Forecast Input'!O74 -> 0 | O95: =SUM(C95:N95) -> 9429.2527
B96: Actual 25' | C96: 13633 | D96: 11228 | E96: 15021 | F96: 7016 | G96: 7528 | H96: 8290 | I96: 17115 | J96: 10308 | K96: 19007 | L96: 7929 | M96: 6643 | N96: 3278 | O96: =SUM(C96:N96) -> 126996
B97: Forecast | C97: ='Forecast Input'!D75 -> 15000 | D97: ='Forecast Input'!E75 -> 12000 | E97: ='Forecast Input'!F75 -> 10000 | F97: ='Forecast Input'!G75 -> 8000 | G97: ='Forecast Input'!H75 -> 3000 | H97: ='Forecast Input'!I75 -> 3000 | I97: ='Forecast Input'!J75 -> 3000 | J97: ='Forecast Input'!K75 -> 5000 | ... N97: ='Forecast Input'!O75 -> 10000 | O97: =SUM(C97:N97) -> 95000
B98: Actual vs Forecast $ | C98: =IF(C95=0,"-",C95-C97) -> -10401.696 | D98: =IF(D95=0,"-",D95-D97) -> -10164.164 | E98: =IF(E95=0,"-",E95-E97) -> -7004.8877 | F98: =IF(F95=0,"-",F95-F97) -> - | G98: =IF(G95=0,"-",G95-G97) -> - | H98: =IF(H95=0,"-",H95-H97) -> - | I98: =IF(I95=0,"-",I95-I97) -> - | J98: =IF(J95=0,"-",J95-J97) -> - | ... N98: =IF(N95=0,"-",N95-N97) -> -
B99: Actual vs Forecast % | C99: =IFERROR(C98/C95,"-") -> -2.2620721 | D99: =IFERROR(D98/D95,"-") -> -5.5365312 | E99: =IFERROR(E98/E95,"-") -> -2.338773 | F99: =IFERROR(F98/F95,"-") -> - | G99: =IFERROR(G98/G95,"-") -> - | H99: =IFERROR(H98/H95,"-") -> - | I99: =IFERROR(I98/I95,"-") -> - | J99: =IFERROR(J98/J95,"-") -> - | ... N99: =IFERROR(N98/N95,"-") -> -
B100: Forecast vs PY $ | C100: =IFERROR(C97-C96,"-") -> 1367 | D100: =IFERROR(D97-D96,"-") -> 772 | E100: =IFERROR(E97-E96,"-") -> -5021 | F100: =IFERROR(F97-F96,"-") -> 984 | G100: =IFERROR(G97-G96,"-") -> -4528 | H100: =IFERROR(H97-H96,"-") -> -5290 | I100: =IFERROR(I97-I96,"-") -> -14115 | J100: =IFERROR(J97-J96,"-") -> -5308 | ... N100: =IFERROR(N97-N96,"-") -> 6722
...

Sheet Partnerships
A1: Partnerships — 2026 Revenue Detail
A2: Read-only · All data flows from Forecast Input tab · Do not type here
A3: SUB-LINE | B3: METRIC | C3: Jan | D3: Feb | E3: Mar | F3: Apr | G3: May | H3: Jun | I3: Jul | J3: Aug | K3: Sep | L3: Oct | M3: Nov | N3: Dec | O3: FULL YEAR
A4: GAN Affiliate | B4: Actual 26' | C4: ='Forecast Input'!D45 -> 618795.88 | D4: ='Forecast Input'!E45 -> 746747.75 | E4: ='Forecast Input'!F45 -> 496449.58 | F4: ='Forecast Input'!G45 -> 0 | G4: ='Forecast Input'!H45 -> 0 | H4: ='Forecast Input'!I45 -> 0 | I4: ='Forecast Input'!J45 -> 0 | J4: ='Forecast Input'!K45 -> 0 | ... N4: ='Forecast Input'!O45 -> 0 | O4: =SUM(C4:N4) -> 1861993.2
B5: Actual 25' | C5: 149624 | D5: 138899 | E5: 87640 | F5: 76728 | G5: 45398 | H5: 150082 | I5: 95941 | J5: 57341 | K5: 96010 | L5: 103279 | M5: 242777 | N5: 306012 | O5: =SUM(C5:N5) -> 1549731
B6: Forecast | C6: ='Forecast Input'!D46 -> 500000 | D6: ='Forecast Input'!E46 -> 700000 | E6: ='Forecast Input'!F46 -> 550000 | F6: ='Forecast Input'!G46 -> 350000 | G6: ='Forecast Input'!H46 -> 300000 | H6: ='Forecast Input'!I46 -> 300000 | I6: ='Forecast Input'!J46 -> 300000 | J6: ='Forecast Input'!K46 -> 400000 | ... N6: ='Forecast Input'!O46 -> 500000 | O6: =SUM(C6:N6) -> 5500000
B7: Actual vs Forecast $ | C7: =IF(C4=0,"-",C4-C6) -> 118795.88 | D7: =IF(D4=0,"-",D4-D6) -> 46747.75 | E7: =IF(E4=0,"-",E4-E6) -> -53550.421 | F7: =IF(F4=0,"-",F4-F6) -> - | G7: =IF(G4=0,"-",G4-G6) -> - | H7: =IF(H4=0,"-",H4-H6) -> - | I7: =IF(I4=0,"-",I4-I6) -> - | J7: =IF(J4=0,"-",J4-J6) -> - | ... N7: =IF(N4=0,"-",N4-N6) -> -
B8: Actual vs Forecast % | C8: =IFERROR(C7/C4,"-") -> 0.1919791 | D8: =IFERROR(D7/D4,"-") -> 0.062601795 | E8: =IFERROR(E7/E4,"-") -> -0.10786679 | F8: =IFERROR(F7/F4,"-") -> - | G8: =IFERROR(G7/G4,"-") -> - | H8: =IFERROR(H7/H4,"-") -> - | I8: =IFERROR(I7/I4,"-") -> - | J8: =IFERROR(J7/J4,"-") -> - | ... N8: =IFERROR(N7/N4,"-") -> -
B9: Forecast vs PY $ | C9: =IFERROR(C6-C5,"-") -> 350376 | D9: =IFERROR(D6-D5,"-") -> 561101 | E9: =IFERROR(E6-E5,"-") -> 462360 | F9: =IFERROR(F6-F5,"-") -> 273272 | G9: =IFERROR(G6-G5,"-") -> 254602 | H9: =IFERROR(H6-H5,"-") -> 149918 | I9: =IFERROR(I6-I5,"-") -> 204059 | J9: =IFERROR(J6-J5,"-") -> 342659 | ... N9: =IFERROR(N6-N5,"-") -> 193988
B10: Forecast vs PY % | C10: =IFERROR(C9/C5,"-") -> 2.3417099 | D10: =IFERROR(D9/D5,"-") -> 4.0396331 | E10: =IFERROR(E9/E5,"-") -> 5.2756732 | F10: =IFERROR(F9/F5,"-") -> 3.5615681 | G10: =IFERROR(G9/G5,"-") -> 5.6082206 | H10: =IFERROR(H9/H5,"-") -> 0.99890726 | I10: =IFERROR(I9/I5,"-") -> 2.1269218 | J10: =IFERROR(J9/J5,"-") -> 5.9758114 | ... N10: =IFERROR(N9/N5,"-") -> 0.63392285
A12: TOTAL PARTNERSHIPS | C12: =IFERROR(IF(C4>0,C4,C6),C6) -> 618795.88 | D12: =IFERROR(IF(D4>0,D4,D6),D6) -> 746747.75 | E12: =IFERROR(IF(E4>0,E4,E6),E6) -> 496449.58 | F12: =IFERROR(IF(F4>0,F4,F6),F6) -> 350000 | G12: =IFERROR(IF(G4>0,G4,G6),G6) -> 300000 | H12: =IFERROR(IF(H4>0,H4,H6),H6) -> 300000 | I12: =IFERROR(IF(I4>0,I4,I6),I6) -> 300000 | J12: =IFERROR(IF(J4>0,J4,J6),J6) -> 400000 | ... N12: =IFERROR(IF(N4>0,N4,N6),N6) -> 500000 | O12: =SUM(C12:N12) -> 5611993.2

Sheet OJ+OO
A1: Odds / OpticOdds — 2026 Revenue Detail
A2: Read-only · All data flows from Forecast Input tab · Do not type here
A3: SUB-LINE | B3: METRIC | C3: Jan | D3: Feb | E3: Mar | F3: Apr | G3: May | H3: Jun | I3: Jul | J3: Aug | K3: Sep | L3: Oct | M3: Nov | N3: Dec | O3: FULL YEAR
A4: Subscriptions (OJ + DGF) | B4: Actual 26' | C4: ='Forecast Input'!D103 -> 1498880 | D4: ='Forecast Input'!E103 -> 1372295 | E4: ='Forecast Input'!F103 -> 1352236.2 | F4: ='Forecast Input'!G103 -> 0 | G4: ='Forecast Input'!H103 -> 0 | H4: ='Forecast Input'!I103 -> 0 | I4: ='Forecast Input'!J103 -> 0 | J4: ='Forecast Input'!K103 -> 0 | ... N4: ='Forecast Input'!O103 -> 0 | O4: =SUM(C4:N4) -> 4223411.2
B5: Actual 25' | C5: 1930757.6 | D5: 1909424.9 | E5: 1868854 | F5: 1697395.9 | G5: 1687225 | H5: 1580380 | I5: 1387227.4 | J5: 1324941.3 | K5: 1417964.9 | L5: 1597457.5 | M5: 1755938.6 | N5: 1764508.9 | O5: =SUM(C5:N5) -> 19922076
B6: Forecast | C6: ='Forecast Input'!D104 -> 1526458 | D6: ='Forecast Input'!E104 -> 1440286 | E6: ='Forecast Input'!F104 -> 1415579 | F6: ='Forecast Input'!G104 -> 1288619 | G6: ='Forecast Input'!H104 -> 1239950 | H6: ='Forecast Input'!I104 -> 1146396 | I6: ='Forecast Input'!J104 -> 1072744 | J6: ='Forecast Input'!K104 -> 1050237 | ... N6: ='Forecast Input'!O104 -> 1612359 | O6: =SUM(C6:N6) -> 16196202
B7: Actual vs Forecast $ | C7: =IF(C4=0,"-",C4-C6) -> -27578.006 | D7: =IF(D4=0,"-",D4-D6) -> -67990.963 | E7: =IF(E4=0,"-",E4-E6) -> -63342.825 | F7: =IF(F4=0,"-",F4-F6) -> - | G7: =IF(G4=0,"-",G4-G6) -> - | H7: =IF(H4=0,"-",H4-H6) -> - | I7: =IF(I4=0,"-",I4-I6) -> - | J7: =IF(J4=0,"-",J4-J6) -> - | ... N7: =IF(N4=0,"-",N4-N6) -> -
B8: Actual vs Forecast % | C8: =IFERROR(C7/C4,"-") -> -0.018399076 | D8: =IFERROR(D7/D4,"-") -> -0.049545441 | E8: =IFERROR(E7/E4,"-") -> -0.046843019 | F8: =IFERROR(F7/F4,"-") -> - | G8: =IFERROR(G7/G4,"-") -> - | H8: =IFERROR(H7/H4,"-") -> - | I8: =IFERROR(I7/I4,"-") -> - | J8: =IFERROR(J7/J4,"-") -> - | ... N8: =IFERROR(N7/N4,"-") -> -
B9: Forecast vs PY $ | C9: =IFERROR(C6-C5,"-") -> -404299.63 | D9: =IFERROR(D6-D5,"-") -> -469138.93 | E9: =IFERROR(E6-E5,"-") -> -453274.98 | F9: =IFERROR(F6-F5,"-") -> -408776.92 | G9: =IFERROR(G6-G5,"-") -> -447275 | H9: =IFERROR(H6-H5,"-") -> -433984 | I9: =IFERROR(I6-I5,"-") -> -314483.42 | J9: =IFERROR(J6-J5,"-") -> -274704.29 | ... N9: =IFERROR(N6-N5,"-") -> -152149.93
B10: Forecast vs PY % | C10: =IFERROR(C9/C5,"-") -> -0.20939947 | D10: =IFERROR(D9/D5,"-") -> -0.24569645 | E10: =IFERROR(E9/E5,"-") -> -0.24254168 | F10: =IFERROR(F9/F5,"-") -> -0.24082591 | G10: =IFERROR(G9/G5,"-") -> -0.26509505 | H10: =IFERROR(H9/H5,"-") -> -0.27460737 | I10: =IFERROR(I9/I5,"-") -> -0.22669925 | J10: =IFERROR(J9/J5,"-") -> -0.20733318 | ... N10: =IFERROR(N9/N5,"-") -> -0.086227919
A11: DGF Affiliate | B11: Actual 26' | C11: ='Forecast Input'!D105 -> 0 | D11: ='Forecast Input'!E105 -> 0 | E11: ='Forecast Input'!F105 -> 0 | F11: ='Forecast Input'!G105 -> 0 | G11: ='Forecast Input'!H105 -> 0 | H11: ='Forecast Input'!I105 -> 0 | I11: ='Forecast Input'!J105 -> 0 | J11: ='Forecast Input'!K105 -> 0 | ... N11: ='Forecast Input'!O105 -> 0 | O11: =SUM(C11:N11) -> 0
B12: Actual 25' | C12: 300 | D12: 450 | E12: 75 | F12: 1350 | G12: 0 | H12: 0 | I12: 0 | J12: 0 | K12: 0 | L12: 50 | M12: 0 | N12: 0 | O12: =SUM(C12:N12) -> 2225
B13: Forecast | C13: ='Forecast Input'!D106 -> 0 | D13: ='Forecast Input'!E106 -> 0 | E13: ='Forecast Input'!F106 -> 0 | F13: ='Forecast Input'!G106 -> 0 | G13: ='Forecast Input'!H106 -> 0 | H13: ='Forecast Input'!I106 -> 0 | I13: ='Forecast Input'!J106 -> 0 | J13: ='Forecast Input'!K106 -> 0 | ... N13: ='Forecast Input'!O106 -> 0 | O13: =SUM(C13:N13) -> 0
B14: Actual vs Forecast $ | C14: =IF(C11=0,"-",C11-C13) -> - | D14: =IF(D11=0,"-",D11-D13) -> - | E14: =IF(E11=0,"-",E11-E13) -> - | F14: =IF(F11=0,"-",F11-F13) -> - | G14: =IF(G11=0,"-",G11-G13) -> - | H14: =IF(H11=0,"-",H11-H13) -> - | I14: =IF(I11=0,"-",I11-I13) -> - | J14: =IF(J11=0,"-",J11-J13) -> - | ... N14: =IF(N11=0,"-",N11-N13) -> -
B15: Actual vs Forecast % | C15: =IFERROR(C14/C11,"-") -> - | D15: =IFERROR(D14/D11,"-") -> - | E15: =IFERROR(E14/E11,"-") -> - | F15: =IFERROR(F14/F11,"-") -> - | G15: =IFERROR(G14/G11,"-") -> - | H15: =IFERROR(H14/H11,"-") -> - | I15: =IFERROR(I14/I11,"-") -> - | J15: =IFERROR(J14/J11,"-") -> - | ... N15: =IFERROR(N14/N11,"-") -> -
B16: Forecast vs PY $ | C16: =IFERROR(C13-C12,"-") -> -300 | D16: =IFERROR(D13-D12,"-") -> -450 | E16: =IFERROR(E13-E12,"-") -> -75 | F16: =IFERROR(F13-F12,"-") -> -1350 | G16: =IFERROR(G13-G12,"-") -> 0 | H16: =IFERROR(H13-H12,"-") -> 0 | I16: =IFERROR(I13-I12,"-") -> 0 | J16: =IFERROR(J13-J12,"-") -> 0 | ... N16: =IFERROR(N13-N12,"-") -> 0
B17: Forecast vs PY % | C17: =IFERROR(C16/C12,"-") -> -1 | D17: =IFERROR(D16/D12,"-") -> -1 | E17: =IFERROR(E16/E12,"-") -> -1 | F17: =IFERROR(F16/F12,"-") -> -1 | G17: =IFERROR(G16/G12,"-") -> - | H17: =IFERROR(H16/H12,"-") -> - | I17: =IFERROR(I16/I12,"-") -> - | J17: =IFERROR(J16/J12,"-") -> - | ... N17: =IFERROR(N16/N12,"-") -> -
A18: OJ Affiliate | B18: Actual 26' | C18: ='Forecast Input'!D107 -> 92646.238 | D18: ='Forecast Input'!E107 -> 62782.833 | E18: ='Forecast Input'!F107 -> 92995.439 | F18: ='Forecast Input'!G107 -> 0 | G18: ='Forecast Input'!H107 -> 0 | H18: ='Forecast Input'!I107 -> 0 | I18: ='Forecast Input'!J107 -> 0 | J18: ='Forecast Input'!K107 -> 0 | ... N18: ='Forecast Input'!O107 -> 0 | O18: =SUM(C18:N18) -> 248424.51
B19: Actual 25' | C19: 157962.19 | D19: 151489.3 | E19: 183351.61 | F19: 232501.72 | G19: 189289.32 | H19: 152710.81 | I19: 128186.82 | J19: 166921.82 | K19: 243360.81 | L19: 182653.6 | M19: 141666.11 | N19: 151884.45 | O19: =SUM(C19:N19) -> 2081978.5
B20: Forecast | C20: ='Forecast Input'!D108 -> 150000 | D20: ='Forecast Input'!E108 -> 150000 | E20: ='Forecast Input'!F108 -> 90000 | F20: ='Forecast Input'!G108 -> 70000 | G20: ='Forecast Input'!H108 -> 70000 | H20: ='Forecast Input'!I108 -> 70000 | I20: ='Forecast Input'!J108 -> 70000 | J20: ='Forecast Input'!K108 -> 70000 | ... N20: ='Forecast Input'!O108 -> 70000 | O20: =SUM(C20:N20) -> 1020000
B21: Actual vs Forecast $ | C21: =IF(C18=0,"-",C18-C20) -> -57353.762 | D21: =IF(D18=0,"-",D18-D20) -> -87217.167 | E21: =IF(E18=0,"-",E18-E20) -> 2995.4392 | F21: =IF(F18=0,"-",F18-F20) -> - | G21: =IF(G18=0,"-",G18-G20) -> - | H21: =IF(H18=0,"-",H18-H20) -> - | I21: =IF(I18=0,"-",I18-I20) -> - | J21: =IF(J18=0,"-",J18-J20) -> - | ... N21: =IF(N18=0,"-",N18-N20) -> -
B22: Actual vs Forecast % | C22: =IFERROR(C21/C18,"-") -> -0.61906196 | D22: =IFERROR(D21/D18,"-") -> -1.3891882 | E22: =IFERROR(E21/E18,"-") -> 0.032210603 | F22: =IFERROR(F21/F18,"-") -> - | G22: =IFERROR(G21/G18,"-") -> - | H22: =IFERROR(H21/H18,"-") -> - | I22: =IFERROR(I21/I18,"-") -> - | J22: =IFERROR(J21/J18,"-") -> - | ... N22: =IFERROR(N21/N18,"-") -> -
B23: Forecast vs PY $ | C23: =IFERROR(C20-C19,"-") -> -7962.1851 | D23: =IFERROR(D20-D19,"-") -> -1489.3036 | E23: =IFERROR(E20-E19,"-") -> -93351.613 | F23: =IFERROR(F20-F19,"-") -> -162501.72 | G23: =IFERROR(G20-G19,"-") -> -119289.32 | H23: =IFERROR(H20-H19,"-") -> -82710.813 | I23: =IFERROR(I20-I19,"-") -> -58186.819 | J23: =IFERROR(J20-J19,"-") -> -96921.821 | ... N23: =IFERROR(N20-N19,"-") -> -81884.446
B24: Forecast vs PY % | C24: =IFERROR(C23/C19,"-") -> -0.050405641 | D24: =IFERROR(D23/D19,"-") -> -0.009831081 | E24: =IFERROR(E23/E19,"-") -> -0.50913985 | F24: =IFERROR(F23/F19,"-") -> -0.69892695 | G24: =IFERROR(G23/G19,"-") -> -0.63019572 | H24: =IFERROR(H23/H19,"-") -> -0.54161727 | I24: =IFERROR(I23/I19,"-") -> -0.45392202 | J24: =IFERROR(J23/J19,"-") -> -0.58064201 | ... N24: =IFERROR(N23/N19,"-") -> -0.53912331
A25: Optic Rev Share | B25: Actual 26' | C25: ='Forecast Input'!D109 -> 236708.1 | D25: ='Forecast Input'!E109 -> 175526.1 | E25: ='Forecast Input'!F109 -> 249908.77 | F25: ='Forecast Input'!G109 -> 0 | G25: ='Forecast Input'!H109 -> 0 | H25: ='Forecast Input'!I109 -> 0 | I25: ='Forecast Input'!J109 -> 0 | J25: ='Forecast Input'!K109 -> 0 | ... N25: ='Forecast Input'!O109 -> 0 | O25: =SUM(C25:N25) -> 662142.97
B26: Actual 25' | C26: 176984.67 | D26: 0 | E26: 1877.22 | F26: 0 | G26: 12500 | H26: 0 | I26: 9600 | J26: 0 | K26: 0 | L26: 0 | M26: 0 | N26: 0 | O26: =SUM(C26:N26) -> 200961.89
B27: Forecast | C27: ='Forecast Input'!D110 -> 236708 | D27: ='Forecast Input'!E110 -> 175526 | E27: ='Forecast Input'!F110 -> 197086 | F27: ='Forecast Input'!G110 -> 202500 | G27: ='Forecast Input'!H110 -> 202500 | H27: ='Forecast Input'!I110 -> 202500 | I27: ='Forecast Input'!J110 -> 202500 | J27: ='Forecast Input'!K110 -> 202500 | ... N27: ='Forecast Input'!O110 -> 562500 | O27: =SUM(C27:N27) -> 3711820
B28: Actual vs Forecast $ | C28: =IF(C25=0,"-",C25-C27) -> 0.1 | D28: =IF(D25=0,"-",D25-D27) -> 0.1 | E28: =IF(E25=0,"-",E25-E27) -> 52822.77 | F28: =IF(F25=0,"-",F25-F27) -> - | G28: =IF(G25=0,"-",G25-G27) -> - | H28: =IF(H25=0,"-",H25-H27) -> - | I28: =IF(I25=0,"-",I25-I27) -> - | J28: =IF(J25=0,"-",J25-J27) -> - | ... N28: =IF(N25=0,"-",N25-N27) -> -
B29: Actual vs Forecast % | C29: =IFERROR(C28/C25,"-") -> 4.2246125e-07 | D29: =IFERROR(D28/D25,"-") -> 5.6971584e-07 | E29: =IFERROR(E28/E25,"-") -> 0.21136821 | F29: =IFERROR(F28/F25,"-") -> - | G29: =IFERROR(G28/G25,"-") -> - | H29: =IFERROR(H28/H25,"-") -> - | I29: =IFERROR(I28/I25,"-") -> - | J29: =IFERROR(J28/J25,"-") -> - | ... N29: =IFERROR(N28/N25,"-") -> -
B30: Forecast vs PY $ | C30: =IFERROR(C27-C26,"-") -> 59723.33 | D30: =IFERROR(D27-D26,"-") -> 175526 | E30: =IFERROR(E27-E26,"-") -> 195208.78 | F30: =IFERROR(F27-F26,"-") -> 202500 | G30: =IFERROR(G27-G26,"-") -> 190000 | H30: =IFERROR(H27-H26,"-") -> 202500 | I30: =IFERROR(I27-I26,"-") -> 192900 | J30: =IFERROR(J27-J26,"-") -> 202500 | ... N30: =IFERROR(N27-N26,"-") -> 562500
B31: Forecast vs PY % | C31: =IFERROR(C30/C26,"-") -> 0.33744917 | D31: =IFERROR(D30/D26,"-") -> - | E31: =IFERROR(E30/E26,"-") -> 103.98823 | F31: =IFERROR(F30/F26,"-") -> - | G31: =IFERROR(G30/G26,"-") -> 15.2 | H31: =IFERROR(H30/H26,"-") -> - | I31: =IFERROR(I30/I26,"-") -> 20.09375 | J31: =IFERROR(J30/J26,"-") -> - | ... N31: =IFERROR(N30/N26,"-") -> -
A32: OpticOdds Subscriptions | B32: Actual 26' | C32: ='Forecast Input'!D111 -> 1395039.8 | D32: ='Forecast Input'!E111 -> 1172189.1 | E32: ='Forecast Input'!F111 -> 1502403.7 | F32: ='Forecast Input'!G111 -> 0 | G32: ='Forecast Input'!H111 -> 0 | H32: ='Forecast Input'!I111 -> 0 | I32: ='Forecast Input'!J111 -> 0 | J32: ='Forecast Input'!K111 -> 0 | ... N32: ='Forecast Input'!O111 -> 0 | O32: =SUM(C32:N32) -> 4069632.6
B33: Actual 25' | C33: 681756.66 | D33: 813531.51 | E33: 1048711.2 | F33: 1039637.3 | G33: 1080978.4 | H33: 1106566.7 | I33: 1180902.9 | J33: 1248188.3 | K33: 1294109.7 | L33: 1473017.4 | M33: 1542719.1 | N33: 1810823 | O33: =SUM(C33:N33) -> 14320942
B34: Forecast | C34: ='Forecast Input'!D112 -> 1287156 | D34: ='Forecast Input'!E112 -> 1423321 | E34: ='Forecast Input'!F112 -> 1499107 | F34: ='Forecast Input'!G112 -> 1555531 | G34: ='Forecast Input'!H112 -> 1588108 | H34: ='Forecast Input'!I112 -> 1588108 | I34: ='Forecast Input'!J112 -> 1591365 | J34: ='Forecast Input'!K112 -> 1591365 | ... N34: ='Forecast Input'!O112 -> 1734779 | O34: =SUM(C34:N34) -> 18652583
B35: Actual vs Forecast $ | C35: =IF(C32=0,"-",C32-C34) -> 107883.79 | D35: =IF(D32=0,"-",D32-D34) -> -251131.94 | E35: =IF(E32=0,"-",E32-E34) -> 3296.7248 | F35: =IF(F32=0,"-",F32-F34) -> - | G35: =IF(G32=0,"-",G32-G34) -> - | H35: =IF(H32=0,"-",H32-H34) -> - | I35: =IF(I32=0,"-",I32-I34) -> - | J35: =IF(J32=0,"-",J32-J34) -> - | ... N35: =IF(N32=0,"-",N32-N34) -> -
B36: Actual vs Forecast % | C36: =IFERROR(C35/C32,"-") -> 0.077333842 | D36: =IFERROR(D35/D32,"-") -> -0.21424184 | E36: =IFERROR(E35/E32,"-") -> 0.0021943002 | F36: =IFERROR(F35/F32,"-") -> - | G36: =IFERROR(G35/G32,"-") -> - | H36: =IFERROR(H35/H32,"-") -> - | I36: =IFERROR(I35/I32,"-") -> - | J36: =IFERROR(J35/J32,"-") -> - | ... N36: =IFERROR(N35/N32,"-") -> -
B37: Forecast vs PY $ | C37: =IFERROR(C34-C33,"-") -> 605399.34 | D37: =IFERROR(D34-D33,"-") -> 609789.49 | E37: =IFERROR(E34-E33,"-") -> 450395.79 | F37: =IFERROR(F34-F33,"-") -> 515893.69 | G37: =IFERROR(G34-G33,"-") -> 507129.63 | H37: =IFERROR(H34-H33,"-") -> 481541.32 | I37: =IFERROR(I34-I33,"-") -> 410462.14 | J37: =IFERROR(J34-J33,"-") -> 343176.68 | ... N37: =IFERROR(N34-N33,"-") -> -76044
B38: Forecast vs PY % | C38: =IFERROR(C37/C33,"-") -> 0.88799915 | D38: =IFERROR(D37/D33,"-") -> 0.74955854 | E38: =IFERROR(E37/E33,"-") -> 0.42947551 | F38: =IFERROR(F37/F33,"-") -> 0.49622468 | G38: =IFERROR(G37/G33,"-") -> 0.46913948 | H38: =IFERROR(H37/H33,"-") -> 0.43516701 | I38: =IFERROR(I37/I33,"-") -> 0.34758332 | J38: =IFERROR(J37/J33,"-") -> 0.27493982 | ... N38: =IFERROR(N37/N33,"-") -> -0.041994165
A40: TOTAL ODDS / OPTICODDS | C40: =IFERROR(IF(C4+C11+C18+C25+C32>0,C4+C11+C18+C25+C32,C6+C13+C20+C27+C34),C6+C13+C20+C27+C34) -> 3223274.1 | D40: =IFERROR(IF(D4+D11+D18+D25+D32>0,D4+D11+D18+D25+D32,D6+D13+D20+D27+D34),D6+D13+D20+D27+D34) -> 2782793 | E40: =IFERROR(IF(E4+E11+E18+E25+E32>0,E4+E11+E18+E25+E32,E6+E13+E20+E27+E34),E6+E13+E20+E27+E34) -> 3197544.1 | F40: =IFERROR(IF(F4+F11+F18+F25+F32>0,F4+F11+F18+F25+F32,F6+F13+F20+F27+F34),F6+F13+F20+F27+F34) -> 3116650 | G40: =IFERROR(IF(G4+G11+G18+G25+G32>0,G4+G11+G18+G25+G32,G6+G13+G20+G27+G34),G6+G13+G20+G27+G34) -> 3100558 | H40: =IFERROR(IF(H4+H11+H18+H25+H32>0,H4+H11+H18+H25+H32,H6+H13+H20+H27+H34),H6+H13+H20+H27+H34) -> 3007004 | I40: =IFERROR(IF(I4+I11+I18+I25+I32>0,I4+I11+I18+I25+I32,I6+I13+I20+I27+I34),I6+I13+I20+I27+I34) -> 2936609 | J40: =IFERROR(IF(J4+J11+J18+J25+J32>0,J4+J11+J18+J25+J32,J6+J13+J20+J27+J34),J6+J13+J20+J27+J34) -> 2914102 | ... N40: =IFERROR(IF(N4+N11+N18+N25+N32>0,N4+N11+N18+N25+N32,N6+N13+N20+N27+N34),N6+N13+N20+N27+N34) -> 3979638 | O40: =SUM(C40:N40) -> 39192989
